Workbook

Sheet KODE PROJECT UPDATE SEP 25
A2: NO | B2: NAMA PELANGGAN | C2: SEGMENTASI | D2: NAMA PROJECT | E2: KODE PROJECT | F2: KETERANGAN
A3: 1 | B3: PT GAGAS ENERGI INDONESIA | C3: BUSINESS SOLUTION | D3: PENGADAAN CCTV SPBG LAMPUNG | E3: BS-001
A4: 2 | B4: PT WIDAR MANDRIPA NUSANTARA | C4: BUSINESS SOLUTION | D4: ABSEN ONLINE | E4: BS-002
A5: 3 | B5: PT PERTAMINA (PERSERO) | C5: BUSINESS SOLUTION | D5: PENYEDIAAN JASA LAYANAN KLASIFIKASI KEAMANAN INFORMASI | E5: BS-003
A6: 4 | B6: PT PERUSAHAAN GAS NEGARA | C6: BUSINESS SOLUTION | D6: PEKERJAAN PENGADAAN DAN PEMASANGAN PRESSURE MONITORING DEVICE PLN TARAHAN LAMPUNG | E6: BS-004 | F6: IOGM
A7: 5 | B7: SAKA INDONESIA PANGKAH LTD | C7: BUSINESS SOLUTION | D7: SMART PRESENCE SUBSCRIPTON | E7: BS-005
A8: 6 | B8: PT GAGAS ENERGI INDONESIA | C8: BUSINESS SOLUTION | D8: PENGADAAN CCTV SPBG PONDOK UNGU | E8: BS-006
A9: 7 | B9: PT ALGAS | C9: BUSINESS SOLUTION | D9: PROJECT INSTAL EVC VEMMTEC V5 SYSTEM BILLING AVE PGNCOM | E9: BS-007
A10: 8 | B10: PT PERTAMINA (PERSERO) | C10: BUSINESS SOLUTION | D10: PERPANJANGAN SUPPORT MAIL SECURITY GATEAWAY PERTAMINA PERSERO | E10: BS-008
A11: 9 | B11: PT PERUSAHAAN GAS NEGARA | C11: BUSINESS SOLUTION | D11: LAPTOP OWNERSHIP PROGRAM 2019-2020 | E11: BS-009 | F11: ICT
A12: 10 | B12: PT TELEMEDIA DINAMIKA SARANA | C12: BUSINESS SOLUTION | D12: LAPTOP OWNERSHIP GASNET | E12: BS-010
A13: 11 | B13: PT PERUSAHAAN GAS NEGARA | C13: BUSINESS SOLUTION | D13: SISTEM RESTRUKTURISASI DAN PENGENDALIAN PEMAKAIAN GAS REVAS-2023 | E13: BS-011 | F13: REVAS
A14: 12 | B14: PT PERUSAHAAN GAS NEGARA | C14: BUSINESS SOLUTION | D14: PENGADAAN JASA PEMELIHARAAN PREPAID MANAGEMENT SYSTEM DAN LAYANAN PENDUKUNG REVENUE ASSURANCE | E14: BS-012 | F14: REVAS
A15: 13 | B15: PT PERUSAHAAN GAS NEGARA | C15: BUSINESS SOLUTION | D15: DASHBOARD MOBILE APPS (DASHBOARD PSAIMS) | E15: BS-013 | F15: HSSE
A16: 14 | B16: PT PERUSAHAAN GAS NEGARA | C16: BUSINESS SOLUTION | D16: MOBILE APPS DEVELOPMENT (HSSE PASSPORT) | E16: BS-014 | F16: HSSE
A17: 15 | B17: PT PERUSAHAAN GAS NEGARA | C17: BUSINESS SOLUTION | D17: RELOKASI PMD PAYA PASIR KE DELI SERDANG | E17: BS-015 | F17: IOGM
A18: 16 | B18: PT KILANG PERTAMINA INTERNASIONAL | C18: BUSINESS SOLUTION | D18: JASA PENDAMPINGAN SERTIFIKASI ISO 27001:2022 | E18: BS-016
A19: 17 | B19: PT PERUSAHAAN GAS NEGARA | C19: BUSINESS SOLUTION | D19: KELTON | E19: BS-017
A20: 18 | B20: PT PERUSAHAAN GAS NEGARA | C20: BUSINESS SOLUTION | D20: PMD | E20: BS-018
A21: 19 | B21: PT NUSANTARA REGAS | C21: BUSINESS SOLUTION | D21: Jasa Event IT Security Jan 2024 - Des 2025 | E21: BS-019
A22: 20 | B22: PERUSAHAAN GAS NEGARA - IOGM | C22: BUSINESS SOLUTION | D22: Pekerjaan Pengadaan dan Pemasangan Pressure Monitoring Device Batang Tahun 2025 | E22: BS-020 | F22: IOGM
A23: 21 | B23: PT PERTAMINA (PERSERO) | C23: BUSINESS SOLUTION | D23: Penyediaan Lisensi OriginPro Pertamina Tahun 2025 | E23: BS-021
A24: 22 | B24: PT PERUSAHAAN GAS NEGARA | C24: BUSINESS SOLUTION | D24: Pengembangan Aplikasi SHARE Modul SIM TJSL | E24: BS-022 | F24: CSR
A25: 23 | B25: PT PERTAMINA PATRA NIAGA | C25: BUSINESS SOLUTION | D25: Pekerjaan Maintenance CCTV & Infrastruktur PPN MOR1 FT Labuhan Deli | E25: BS-023
A26: 24 | B26: PT TRANSPORTASI GAS INDONESIA | C26: BUSINESS SOLUTION | D26: Pengadaan Firewall Amandemen Perjanjian Pengadaan Link Metro Ethemet Dan Colocation Data Center Utama PT Transportasi Gas Indonesia | E26: BS-024
A27: 25 | B27: PT SUPREME ENERGY RANTAU DEDAP | C27: BUSINESS SOLUTION | D27: Pekerjaan System ATS ECM Suite 25 di PT Supreme Energy Rantau Dedap (SERD) | E27: BS-025
A28: 26 | B28: PT SUPREME ENERGY MUARA LABOH | C28: BUSINESS SOLUTION | D28: Pekerjaan System ATS ECM Suite 25 di PT Supreme Energy Muara Laboh (SEML) | E28: BS-026
A29: 27 | C29: BUSINESS SOLUTION | D29: Pekerjaan BER Test DC Kemendagri | E29: BS-027
A30: 28 | C30: BUSINESS SOLUTION | D30: Sewa BERT Test Kemendagri | E30: BS-028
A31: 29 | B31: PT KILANG PERTAMINA INTERNASIONAL | C31: BUSINESS SOLUTION | D31: Pengadaan Jasa Pendampingan Surveillance Sertifikasi ISO/IEC 27001:2022 DI PT KPI | E31: BS-029
A32: 30 | B32: PT KILANG PERTAMINA INTERNASIONAL | C32: BUSINESS SOLUTION | D32: Pengadaan Jasa Implementasi Data Governance Di PT Kilang Pertamina Internasional | E32: BS-030
A34: 1 | B34: PT PERUSAHAAN GAS NEGARA | C34: MANAGED SERVICE | D34: JASA PEMELIHARAAN DAN PENGEMBANGAN PREPAID MANAGEMENT SYSTEM - 2023 | E34: MS-001 | F34: REVAS
A35: 2 | B35: PT PERUSAHAAN GAS NEGARA | C35: MANAGED SERVICE | D35: AMD JASA PEMELIHARAAN DAN PENGEMBANGAN PREPAID MANAGEMENT SYSTEM 2023 | E35: MS-002 | F35: REVAS
A36: 3 | B36: PT PERUSAHAAN GAS NEGARA | C36: MANAGED SERVICE | D36: PEKERJAAN JASA OPERASI DAN PEMELIHARAAN GAS MANAGEMEN SISTEM | E36: MS-003 | F36: IOGM
A37: 4 | B37: PT PERUSAHAAN GAS NEGARA | C37: MANAGED SERVICE | D37: PENYEDIAAN LAYANAN SISTEM RADIO KOMUNIKASI | E37: MS-004 | F37: IOGM
A38: 5 | B38: PT PGAS SOLUTION | C38: MANAGED SERVICE | D38: COLOCATION BACKUP DATA CENTER | E38: MS-005
A39: 6 | B39: PT PGAS SOLUTION | C39: MANAGED SERVICE | D39: SEWA LAPTOP PGASOL 3 (WO 2) | E39: MS-006
A40: 7 | B40: PT PGAS SOLUTION | C40: MANAGED SERVICE | D40: SEWA LAPTOP PGASOL 4 (WO 3) | E40: MS-007
A41: 8 | B41: PT PGAS SOLUTION | C41: MANAGED SERVICE | D41: SEWA LAPTOP PGASOL 5 (WO 4) | E41: MS-008
A42: 9 | B42: PT PGAS SOLUTION | C42: MANAGED SERVICE | D42: PENYEDIAAN LAYANAN CLOUD VIRTUAL PRIVATE SERVER (KONTRAK PAYUNG) | E42: MS-009
A43: 10 | B43: PT PGAS SOLUTION | C43: MANAGED SERVICE | D43: PENYEDIAAN LAYANAN CLOUD VIRTUAL PRIVATE SERVER (TAGIHAN TRIWULAN TECH SUPPORT) | E43: MS-010
A44: 11 | B44: PT PGAS SOLUTION | C44: MANAGED SERVICE | D44: CLOUD VPS - WO (LAYANAN BAAS & UPGRADE RESOURCES) | E44: MS-011
A45: 12 | B45: SCM | C45: MANAGED SERVICE | D45: JASA OPERASIONAL CONTACT CENTER | E45: MS-012
A46: 13 | B46: PT KALIMANTAN JAWA GAS | C46: MANAGED SERVICE | D46: PENYEDIAAN, PENGELOLAAN, DAN PEMELIHARAAN PERANGKAT SI (IPPBX, SERVER DATA, SERTA WEBSITE & DOMAIN, ROUTER DAN LINK DEDICATED PGN ONE | E46: MS-013
A47: 14 | B47: KPU | C47: MANAGED SERVICE | D47: CLOUD HOSTING | E47: MS-014
A48: 15 | B48: PT GAGAS ENERGI INDONESIA | C48: MANAGED SERVICE | D48: JASA SEWA PERANGKAT DAN SISTEM AMR UNTUK PELANGGAN CNG | E48: MS-015
A49: 16 | B49: PT GAGAS ENERGI INDONESIA | C49: MANAGED SERVICE | D49: ABSEN ONLINE | E49: MS-016
... A70: 37 | B70: PT GAGAS ENERGI INDONESIA | C70: MANAGED SERVICE | D70: PENGADAAN CCTV MRU GROGOL | E70: MS-037
A71: 38 | B71: PT PERUSAHAAN GAS NEGARA | C71: MANAGED SERVICE | D71: JASA PEMELIHARAAN DAN MONITORING SISTEM MANAGEMENT INFORMASI LEGAL | E71: MS-038 | F71: LEGAL
A72: 39 | B72: PT PERUSAHAAN GAS NEGARA | C72: MANAGED SERVICE | D72: MANAGE SERVICE SEWA INFRASTRUKTUR DATA CENTER | E72: MS-039 | F72: ICT
A73: 40 | B73: PT PERTAMINA (PERSERO) | C73: MANAGED SERVICE | D73: PENYEDIAAN JASA LAYANAN OFFLINE BACKUP -PHASE 1 | E73: MS-040
A74: 41 | B74: PT PELITA AIR SERVICE | C74: MANAGED SERVICE | D74: PENGADAAN SOC, PAM & LAYANAN MANAGED SERVICE SECURITY | E74: MS-041
A75: 42 | B75: PT PERTAMINA (PERSERO) | C75: MANAGED SERVICE | D75: PENGADAAN JASA MANAGED SERVICE SECURITY ASSESSMENT (MSSA) | E75: MS-042
A76: 43 | B76: PT PERTAMINA (PERSERO) | C76: MANAGED SERVICE | D76: SEWA PERANGKAT STORAGE DAN NTP SERVER PT PERTAMINA (PERSERO) | E76: MS-043
A77: 44 | B77: PT PERTAMINA (PERSERO) | C77: MANAGED SERVICE | D77: PENYEDIAAN LAYANAN PLATFORM PILOT APLIKASI MODERN | E77: MS-044
A78: 45 | B78: PT PERUSAHAAN GAS NEGARA | C78: MANAGED SERVICE | D78: PENGADAAN SEWA PERANGKAT INFRASTRUKTUR TEKNOLOGI INFORMASI | E78: MS-045 | F78: ICT
A79: 46 | B79: PT PERUSAHAAN GAS NEGARA | C79: MANAGED SERVICE | D79: MS IT MAINTENANCE | E79: MS-046 | F79: ICT
A80: 47 | B80: PT PERUSAHAAN GAS NEGARA | C80: MANAGED SERVICE | D80: MS APPLICATION AND INTEGRATION SOLUTION 2024 / MS APPLICATION AND INTEGRATION SOLUTION 2025 | E80: MS-047 | F80: ICT
A81: 48 | B81: PT PERUSAHAAN GAS NEGARA | C81: MANAGED SERVICE | D81: MS OT SECURITY 2024 / MS OT SECURITY 2025 | E81: MS-048 | F81: ICT
A82: 49 | B82: PT PERUSAHAAN GAS NEGARA | C82: MANAGED SERVICE | D82: MS IT-OT SOC ENHANCEMENT 2024 / MS CYBER SECURITY 2025 | E82: MS-049 | F82: ICT
A83: 50 | B83: PT PERUSAHAAN GAS NEGARA | C83: MANAGED SERVICE | D83: PERAPIHAN STANDARISASI INFRASTRUKTUR IT & PERGANTIAN UPS 2024 | E83: MS-050 | F83: ICT
A84: 51 | B84: PT PERUSAHAAN GAS NEGARA | C84: MANAGED SERVICE | D84: MS CYBER SECURITY AWARENESS 2025 | E84: MS-051 | F84: ICT
A85: 52 | B85: PT PERUSAHAAN GAS NEGARA | C85: MANAGED SERVICE | D85: PEKERJAAN PENGADAAN LISENSI PIRANTI LUNAK PERIODE IV (COMPILATION) | E85: MS-052 | F85: ICT
A86: 53 | B86: PT PERUSAHAAN GAS NEGARA | C86: MANAGED SERVICE | D86: PEKERJAAN MANAGED SERVICE BACKUP MANAGEMENT | E86: MS-053 | F86: ICT
A87: 54 | B87: TRANSPORTASI GAS INDONESIA | C87: MANAGED SERVICE | D87: AMANDEMEN PEKERJAAN JASA KOMUNIKASI LINK V-SAT SCPC, FIBER OPTIC METROE DAN INTERNET 2023-2026 | E87: MS-054
A88: 55 | B88: TRANSPORTASI GAS INDONESIA | C88: MANAGED SERVICE | D88: AMANDEMEN II PEKERJAAN JASA KOMUNIKASI LINK V-SAT SCPC, FIBER OPTIC METROE DAN INTERNET 2023-2026 | E88: MS-055
A89: 56 | B89: TRANSPORTASI GAS INDONESIA | C89: MANAGED SERVICE | D89: AMANDEMEN PENGADAAN LINK METRO ETHERNET & COLOCATION DATA CENTER UTAMA | E89: MS-056
A90: 57 | B90: PT PERTAMINA HULU ENERGI | C90: MANAGED SERVICE | D90: PHE RADIO KOMUNIKASI | E90: MS-057
A91: 58 | B91: PT PERUSAHAAN GAS NEGARA | C91: MANAGED SERVICE | D91: JASA PEMELIHARAAN DAN UPGRADE APLIKASI HOLISTIC | E91: MS-058 | F91: HSE
A92: 59 | B92: JADESTONE | C92: MANAGED SERVICE | D92: LAYANAN PROVISION OF COMMUNICATION LINK FROM AGPF TO TGI (8 JANUARI-7 JANUARI 2027) | E92: MS-059
A93: 60 | B93: JADESTONE | C93: MANAGED SERVICE | D93: AMANDEMEN LAYANAN PROVISION OF COMMUNICATION LINK FROM AGPF TO TGI (8 JANUARI-7 JANUARI 2027) LINK SAKERNAN | E93: MS-060
A94: 61 | B94: PT PERUSAHAAN GAS NEGARA | C94: MANAGED SERVICE | D94: INTEGRATED MONITORING CENTER (IMOC) | E94: MS-061 | F94: IOGM
A95: 62 | B95: PT NUSANTARA REGAS | C95: MANAGED SERVICE | D95: Pekerjaan Jasa Pengadaan Event IT Security PT Nusantara Rega | E95: MS-062
A96: 63 | B96: PT PERTAMINA INTERNATIONAL SHIPPING | C96: MANAGED SERVICE | D96: PENYEDIAAN PERANGKAT MULTIMEDIA BALLROOM DAN MINI GALERY | E96: MS-063
A97: 64 | B97: PT NUSANTARA REGAS | C97: MANAGED SERVICE | D97: Interfacing Data Scada ke Aplikasi GMS | E97: MS-064
A98: 65 | B98: PT PERTAMINA DRILLING SERVICES INDONESIA | C98: MANAGED SERVICE | D98: PENGADAAN MONITOR HMI | E98: MS-065
A99: 66 | B99: PT PGN LNG INDONESIA | C99: MANAGED SERVICE | D99: Sewa Layanan Cloud (dan VAPT) | E99: MS-066
A100: 67 | B100: PT PERUSAHAAN GAS NEGARA | C100: MANAGED SERVICE | D100: PEKERJAAN VAPT & TECHNICAL SERVICE CYBER SECURITY | E100: MS-067 | F100: ICT
A101: 68 | B101: PT PERTAMINA GAS | C101: MANAGED SERVICE | D101: Jasa Pengadaan Pengelolaan lntegrasi Data dan Pemeliharaan Sistem Data Acquisition Transportasi Minyak & Gas Bumi Tahun 2025 | E101: MS-068
A102: 69 | B102: PT NUSANTARA REGAS | C102: MANAGED SERVICE | D102: Interfacing Data Scada ke Aplikasi GMS | E102: MS-069
A103: 70 | B103: PT PERTAMINA GEOTHERMAL ENERGY | C103: MANAGED SERVICE | D103: Layanan Cyber Security Operation Center (CSOC) | E103: MS-070
A104: 71 | B104: PT PERUSAHAAN GAS NEGARA | C104: MANAGED SERVICE | D104: Pekerjaan Jasa Sewa Penyediaan Collocation Master Data Center dan Backup data Center | E104: MS-071 | F104: IOGM
A105: 72 | B105: PT PGN LNG INDONESIA | C105: MANAGED SERVICE | D105: Managed Service Access Point dan Switch | E105: MS-072
A106: 73 | B106: PT KILANG PERTAMINA INTERNASIONAL | C106: MANAGED SERVICE | D106: Penyediaan Layanan Security Operation Center Information Technology (SOC IT) | E106: MS-073
A107: 74 | B107: PT KALIMANTAN JAWA GAS | C107: MANAGED SERVICE | D107: Pengadaan Jasa penyediaan Perangkat Sistem Informasi | E107: MS-074
A108: 75 | B108: PT PERUSAHAAN GAS NEGARA | C108: MANAGED SERVICE | D108: Pekerjaan Penyediaan Layanan Sewa Server YKPP PGN | E108: MS-075 | F108: YKPP
A109: 76 | B109: PT NUSANTARA REGAS | C109: MANAGED SERVICE | D109: Pekerjaan Pengadaan Jasa Implementasi SIEM dan SOC | E109: MS-076
A110: 77 | B110: PT PERUSAHAAN GAS NEGARA | C110: MANAGED SERVICE | D110: Enhancement Aplikasi System Integrasi Datamart & Tools Monitoring Dashboard Management Kinerja Niaga | E110: MS-077 | F110: MSCM
A111: 78 | B111: 0 | C111: 0 | E111: MS-078
A112: 79 | B112: 0 | C112: 0 | E112: MS-079
A113: 80 | B113: PT PERMATA GRAHA NUSANTARA | C113: MANAGED SERVICE | D113: Pengadaan Vulnerability Assesment dan Penetration Testing | E113: MS-080
A114: 81 | B114: PT PERTAMINA PATRA NIAGA | C114: MANAGED SERVICE | D114: Pekerjaan Sewa Router Untuk Layanan Dual Link SPBU | E114: MS-081
A115: 82 | B115: PT PERTAMINA GAS | C115: MANAGED SERVICE | D115: Pengelolaan Integrasi Data dan Pemeliharaan Sistem Data Acquisition Transportasi Minyak & Gas Bumi | E115: MS-082
A116: 83 | B116: PT PERUSAHAAN GAS NEGARA | C116: MANAGED SERVICE | D116: Pekerjaan Jasa Sewa Penyediaan Collocation Master Data Center dan Backup data Center | E116: MS-083
A117: 84 | B117: PT PERKEBUNAN NUSANTARA | C117: MANAGED SERVICE | D117: Penyediaan layanan Managed Service Security Operation Center (SOC) | E117: MS-084
A118: 85 | B118: PT PERTAMINA PATRA NIAGA | C118: MANAGED SERVICE | D118: Pengadaan Implementasi Security Operation Center (SOC) di Kantor Pusat Wisma Tugu II | E118: MS-085
A119: 86 | B119: PT PERTAMINA (PERSERO) | C119: MANAGED SERVICE | D119: Pengadaan Sewa Perangkat Storage san NTP Server Pertamina | E119: MS-086
A120: 87 | B120: PT PERTAMINA (PERSERO) | C120: MANAGED SERVICE | D120: Tindak Lanjut Pekerjaan Jasa Managed Service Security Assessment (MSSA) | E120: MS-087
A121: 88 | B121: PT PGAS SOLUTION | C121: MANAGED SERVICE | D121: VAPT dan Technical Service Cyber Security | E121: MS-088
A122: 89 | B122: PT PERUSAHAAN GAS NEGARA | C122: MANAGED SERVICE | D122: Managed Service Cyber Security (MSCS) Tahun 2026 | E122: MS-089 | F122: ICT
...

Sheet KODE PROJECT BARU
A2: LIST PEKERJAAN ONGOING PER 1 JUNI 2026
A4: Group ID | B4: Project ID Lama | C4: Project ID Baru | D4: Project_client | E4: Project Name | G4: GRUP | H4: KODE | I4: KODE | K4: Nomor | L4: CLIENT2 | M4: INITIAL | N4: GRUP
G5: HOLDING | H5: G1 | I5: G1 | K5: 1 | L5: PT Perusahaan Gas Negara | M5: PGN | N5: G2
B6: BS-019 | C6: BS-019 | D6: NRG | E6: Jasa Event IT Security Januari 2024 - Desember 2025 | G6: SHG | H6: G2 | I6: G2 | K6: 2 | L6: PT PGN LNG Indonesia | M6: PLI | N6: G3
B7: MS-020 | C7: MS-020 | D7: NRG | E7: Layanan Radio Komunikasi-Trunking 24 Bulan | G7: PGN GROUP | H7: G3 | I7: G3 | K7: 3 | L7: PT Pertamina Gas | M7: PTG | N7: G3
B8: MS-062 | C8: MS-062 | D8: NRG | E8: Pekerjaan Jasa Pengadaan Event IT Security PT Nusantara Regas | G8: PERTAMINA GROUP | H8: G4 | I8: G4 | K8: 4 | L8: PT Pertamina Persero | M8: PTM | N8: G1
B9: MS-077 | C9: MS-077 | D9: PGN | E9: Enhancement Aplikasi System Integrasi Datamart & Tools Monitoring Dashboard Management Kinerja Niaga | G9: NON PERTAMINA | H9: G5 | I9: G5 | K9: 5 | L9: PT Nusantara Regas | M9: NRG | N9: G3
B10: BS-023 | C10: BS-023 | D10: PPN | E10: Pekerjaan Maintenance CCTV & Infrastruktur PPN MOR1 FT Labuhan Deli | K10: 6 | L10: PT Saka Energi Indonesia | M10: SAKA | N10: G3
B11: BS-024 | C11: BS-024 | D11: TGI | E11: Pengadaan Firewall Amandemen Perjanjian Pengadaan Link Metro Ethemet Dan Colocation Data Center Utama PT Transportasi Gas Indonesia | K11: 7 | L11: PT Pertamina Energi Terminal | M11: PET | N11: G4
B12: BS-025 | C12: BS-025 | D12: SERD | E12: Pekerjaan System ATS ECM Suite 25 di PT Supreme Energy Rantau Dedap (SERD) | K12: 8 | L12: PT Pelita Air Service | M12: PAS | N12: G5
B13: BS-026 | C13: BS-026 | D13: SEML | E13: Pekerjaan System ATS ECM Suite 25 di PT Supreme Energy Muara Laboh (SEML) | K13: 9 | L13: PT PGAS Solution | M13: PSOL | N13: G3
B14: BS-027 | C14: BS-027 | E14: Pekerjaan BER Test DC Kemendagri | K14: 10 | L14: PT Pertamina Hulu Energi | M14: PHE | N14: G4
B15: BS-028 | C15: BS-028 | E15: Sewa BERT Test Kemendagri | K15: 11 | L15: PT Kalimantan Jawa gas | M15: KJG | N15: G3
B16: BS-029 | C16: BS-029 | D16: KPI | E16: Pengadaan Jasa Pendampingan Surveillance Sertifikasi ISO/IEC 27001:2022 DI PT KPI | K16: 12 | L16: PT Pertamina International Shipping | M16: PIS | N16: G4
K17: 13 | L17: PT Gagas Energi Indonesia | M17: GGS | N17: G3
C18: PS-000-00 | D18: PLI | E18: Pengadaan CCTV PT PGN LNG | K18: 14 | L18: PT Widar Mandripa Nusantara | M18: WDR | N18: G3
A19: G3 | B19: MS-026 | C19: PS-001-00 | D19: PTG | E19: Manage Service Layanan Printer, Scanner, Multimedia dan UPS System di PT Pertamina Gas | K19: 15 | L19: PT Pertamina Geothermal Energy | M19: PGE | N19: G4
A20: G4 | B20: MS-081 | C20: PS-002-00 | D20: PPN | E20: Pekerjaan Sewa Router Untuk Layanan Dual Link SPBU | K20: 16 | L20: PT Kilang Pertamina Internasional | M20: KPI | N20: G4
A21: G4 | B21: MS-016 | C21: PS-003-00 | D21: WDR | E21: Pengadaan Sewa Aplikasi Absensi Online (Bimasakti) PT Widar Mandripa Nusantara | K21: 17 | L21: PT Pertamina Patra Niaga | M21: PPN | N21: G4
A22: G1 | B22: MS-031 | C22: PS-004-00 | D22: PTM | E22: Pengelolaan & Pengembangan Servicedesk Shared Services Pertamina | K22: 18 | L22: PT Nippon Shokubai Indonesia | M22: NSI | N22: G5
A23: G3 | B23: MS-074 | C23: PS-005-00 | D23: KJG | E23: Pengadaan Jasa penyediaan Perangkat Sistem Informasi | K23: 19 | L23: PT Pertagas Niaga | M23: PTGN | N23: G3
A24: G3 | B24: MS-088 | C24: PS-006-00 | D24: PSOL | E24: Implementasi Vulnerability Assessment & Penetration Test (VAPT) dan Technical Service Cyber Security | K24: 20 | L24: Yayasan Kesehatan Pertamina | M24: YKP | N24: G4
A25: G2 | B25: MS-075 | C25: PS-007-00 | D25: PGN | E25: Pekerjaan Penyediaan Layanan Sewa Server YKPP PGN | K25: 21 | L25: PT Pekerbunan Nusantara I
A26: G2 | B26: MS-100 | C26: PS-008-00 | D26: PGN | E26: Jasa Teknikal Asistensi Sistem Manajemen Informasi Legal (SMILE) | K26: 22 | L26: PT Pekerbunan Nusantara III
A27: G3 | B27: MS-076 | C27: PS-009-00 | D27: NRG | E27: Jasa Implementasi Security Information Event Management (SIEM) dan Security Operation Center (SOC) | K27: 23 | L27: PT Pekerbunan Nusantara IV
A28: G1 | C28: PS-010-00 | D28: PTM | E28: Penyediaan Jasa Dukungan Operasional Fungsi Shared Services ICT Tahun | K28: 24 | L28: PT Sinergi Gula Nusantara
A29: G2 | B29: MS-098 | C29: PS-011-00 | D29: PGN | E29: Penyediaan Lisensi Piranti Lunak dan Annual Technical Support | K29: 25 | L29: PT Riset Perkebunan Nusantara
A30: G1 | C30: PS-012-00 | D30: PTM | E30: Pengadaan Jasa Penyediaan Endpoint Security | K30: 26 | L30: PT LPP Agro Nusantara
A31: G1 | B31: MS-086 | C31: PS-013-00 | D31: PTM | E31: Pengadaan Sewa Perangkat Storage san NTP Server Pertamina | K31: 27 | L31: PT Kharisma Pemasaran Bersama Nusantara
A32: G1 | B32: MS-040 | C32: PS-014-00 | D32: PTM | E32: Penyediaan Jasa Layanan Offline Backup AWS Phase 1 | K32: 28 | L32: PT Industri Karet Nusantara
A33: G1 | B33: MS-087 | C33: PS-015-00 | D33: PTM | E33: Tindak Lanjut Pekerjaan Jasa Managed Service Security Assessment (MSSA) | K33: 29 | L33: PT Sri Pamela Medika Nusantara
A34: G2 | B34: MS-012 | C34: PS-016-00 | D34: PGN | E34: Jasa Managed Service Pengelolaan Layanan Pelanggan Melalui Contact Center | K34: 30 | L34: PT Kawasan Industri Nusantara
A35: G2 | B35: MS-061 | C35: PS-017-00 | D35: PGN | E35: Jasa Penyediaan Perangkat Multimedia dan Peralatan Pendukung Ruang Integrated Monitoring Center (IMOC) | K35: 31 | L35: PT Bio Industri Nusantara
A36: G2 | C36: PS-018-00 | D36: PGN | E36: Managed Service Aplication Integration Solutions (MSAIS) | K36: 32 | L36: PT Supreme Energi Muara Laboh
A37: G2 | C37: PS-018-01 | D37: PGN | E37: Managed Service Aplication Integration Solutions (MSAIS): Jasa enhancement E-SMS 2026 | K37: 33 | L37: PT Supreme Energi Rantau Dedap
A38: G2 | C38: PS-018-02 | D38: PGN | E38: Pekerjaan Enhancement 16 KB Page File (Android), Multifactor Authentification (MFA) (Android & IOS) Serta Implementasi Progressive Web App (PWA)
A39: G2 | C39: PS-018-03 | D39: PGN | E39: Pekerjaan Pengelolaan & Dukungan Aplikasi Kepelangganan PGN Tahun 2026
A40: G2 | B40: MS-053 | C40: PS-019-00 | D40: PGN | E40: Managed Service Backup Management (Vinchin)
A41: G2 | B41: MS-049 | C41: PS-020-00 | D41: PGN | E41: Managed Service Cyber Security (MSCS)
A42: G2 | B42: MS-048 | C42: PS-021-00 | D42: PGN | E42: Managed Service OT Security (MSOT)
A43: G2 | B43: MS-039 | C43: PS-022-00 | D43: PGN | E43: Managed Service Sewa Infrastruktur Data Center (Aletra)
A44: G2 | B44: MS-046 | C44: PS-023-00 | D44: PGN | E44: Managed Service Teknologi Informasi (MSTI)
A45: G2 | B45: MS-003 | C45: PS-024-00 | D45: PGN | E45: Pekerjaan Jasa Operasi dan Pemeliharaan Terintegrasi Gas Management System (PJOPTGMS)
A46: G2 | B46: MS-071 | C46: PS-025-00 | D46: PGN | E46: Pekerjaan Jasa Sewa Penyediaan Collocation Master Data Center dan Backup data Center
A47: G2 | B47: MS-078 | C47: PS-026-00 | D47: PGN | E47: Pengadaan Jasa Managed Service E-KYC
A48: G2 | C48: PS-027-00 | D48: PGN | E48: Penyediaan Jasa Layanan Notifikasi SMS Penagihan Piutang Pelanggan Tahun 2026
A49: G2 | B49: MS-004 | C49: PS-028-00 | D49: PGN | E49: Penyediaan Layanan Sistem Radio Komunikasi
A50: G2 | B50: MS-079 | C50: PS-029-00 | D50: PGN | E50: Penyediaan Lisensi Piranti Lunak Periode IV (Google Maps)
A51: G2 | B51: MS-045 | C51: PS-030-00 | D51: PGN | E51: Sewa Perangkat Infrastruktur Teknologi Informasi (Sangfor)
A52: G2 | C52: PS-031-00 | D52: PGN | E52: Penyediaan Personil Tenaga Alih Daya (TAD) di PT Perusahaan Gas Negara (PGN) HSSE Untuk Rencana Pekerjaan PGN Digital HSSE Campaign
A53: G2 | C53: PS-032-00 | D53: PGN | E53: Penyediaan Aplikasi Point of Sales untuk Pemberdayaan Aset
A54: G2 | C54: PS-033-00 | D54: PGN | E54: Managed Service Cyber Security Awareness
A55: G3 | B55: MS-019 | C55: PS-034-00 | D55: PLI | E55: Jasa Pemeliharaan Sistem Kontrol dan Telekomunikasi Offtake Station (OTS) & Onshore Receiving Facilities (ORF)
A56: G3 | B56: MS-025 | C56: PS-035-00 | D56: PTG | E56: Layanan Sewa Perangkat Server dan Network Teknologi Informasi dan Layanan Sewa Perangkat Infrastruktur Teknologi Informasi SPO Nusantara
A57: G3 | B57: MS-028 | C57: PS-036-00 | D57: PTG | E57: Manage Service Layanan Perangkat Command Crisis Center PT Pertamina Gas
A58: G3 | B58: MS-072 | C58: PS-037-00 | D58: PLI | E58: Managed Service Access Point dan Switch
A59: G3 | B59: MS-017 | C59: PS-038-00 | D59: PLI | E59: Managed Service SD-WAN
A60: G3 | B60: MS-029 | C60: PS-039-00 | D60: PTG | E60: Managed Service Sewa layanan IP Phone System
A61: G3 | B61: MS-066 | C61: PS-040-00 | D61: PLI | E61: Pekerjaan Layanan Cloud (dan VAPT)
A62: G3 | B62: MS-016 | C62: PS-041-00 | D62: GGS | E62: Pengadaan Sewa Aplikasi Absensi Online (Bimasakti) PT Gagas Energi Indonesia
A63: G3 | B63: MS-016 | C63: PS-042-00 | D63: SAKA | E63: Pengadaan Sewa Aplikasi Absensi Online (Bimasakti) PT Saka Energi Indonesia
A64: G3 | B64: MS-082 | C64: PS-043-00 | D64: PTG | E64: Pengelolaan Integrasi Data dan Pemeliharaan Sistem Data Acquisition Transportasi Minyak & Gas Bumi
A65: G4 | B65: MS-085 | C65: PS-044-00 | D65: PPN | E65: Pengadaan Implementasi Security Operation Center (SOC) di Kantor Pusat Wisma Tugu II
A66: G4 | B66: MS-092 | C66: PS-045-00 | D66: PIS | E66: Penyediaan Perangkat Multimedia Ballroom dan Mini Galery
... A68: G4 | B68: MS-057 | C68: PS-047-00 | D68: PHE | E68: Layanan Telekomunikasi Site
A69: G4 | C69: PS-048-00 | D69: PIS | E69: Pekerjaan Jasa Pengelolaan Modul Smartship dan Pemeliharaan Sensor Kapal
A70: G5 | C70: PS-049-00 | D70: NSI | E70: Pengadaan Jasa Sewa Radio Komunikasi
A71: G5 | C71: PS-050-00 | D71: PAS | E71: Pengadaan SOC (Security Operation Center), PAM (Priviledge Access Management) dan Layanan Managed Service Security
A72: G5 | B72: MS-084 | C72: PS-051-00 | D72: PTPN | E72: Penyediaan Layanan Managed Services Security Operation Center (SOC) PTPN III
A73: G3 | C73: PS-052-00 | D73: PTGN | E73: Pengadaan Strategic Cyber Security Assesment & Prevention Management Penetration Testing
A74: G4 | C74: PS-053-00 | D74: YKP | E74: Penetration Testing All Care System
A75: G3 | C75: PS-054-00 | D75: TGI | E75: Pengadaan Firewall Amandemen Perjanjian Pengadaan Link Metro Ethemet Dan Colocation Data Center Utama
A76: G4 | C76: PS-055-00 | D76: PPN | E76: Jasa Keamanan Operasi Cyber Security PT Kilang Pertamina Internasional
A77: G4 | C77: PS-056-00 | D77: PPN | E77: Pengadaan Jasa Pengembangan & Pemeliharaan Aplikasi Pendukung IT Project Pertamina Patra Niaga
A78: G4 | B78: BS-030 | C78: PS-057-00 | D78: KPI | E78: Pengadaan Jasa Implementasi Data Governance Di PT Kilang Pertamina Internasional
A79: G2 | C79: PS-058-00 | D79: PGN | E79: Penyediaan Perangkat Network System Refreshment
A80: G1 | C80: PS-059-00 | D80: PTM | E80: Penyediaan Jasa Klasifikasi Keamanan Informasi
A81: G2 | B81: MS-077 | C81: PS-060-00 | D81: PGN | E81: Enhancement Aplikasi System Integrasi Datamart & Tools Monitoring Dashboard Management Kinerja Niaga
A82: G2 | C82: PS-061-00 | D82: PGN | E82: Pengadaan Monitor PGN GCG & Compliance
A83: G3 | C83: PS-062-00 | D83: PTG | E83: Security Awareness-Cyber Security BSSN Forum untuk AP/JV PT Pertamina Gas 2026
C84: PS-063-00 | D84: PTPN | E84: Penyediaan Layanan Managed Services Security Operation Center (SOC) PTPN I
C85: PS-064-00 | D85: PTPN | E85: Penyediaan Layanan Managed Services Security Operation Center (SOC) PTPN IV
C86: PS-065-00 | D86: PTPN | E86: Penyediaan Layanan Managed Services Security Operation Center (SOC) PT SGN
C87: PS-066-00 | D87: PTPN | E87: Penyediaan Layanan Managed Services Security Operation Center (SOC) PT RPN
C88: PS-067-00 | D88: PTPN | E88: Penyediaan Layanan Managed Services Security Operation Center (SOC) PT LPP AN
C89: PS-068-00 | D89: PTPN | E89: Penyediaan Layanan Managed Services Security Operation Center (SOC) PT KPBN
C90: PS-069-00 | D90: PTPN | E90: Penyediaan Layanan Managed Services Security Operation Center (SOC) PT IKN
C91: PS-070-00 | D91: PTPN | E91: Penyediaan Layanan Managed Services Security Operation Center (SOC) PT SPMN
C92: PS-071-00 | D92: PTPN | E92: Penyediaan Layanan Managed Services Security Operation Center (SOC) PT KIN
C93: PS-072-00 | D93: PTPN | E93: Penyediaan Layanan Managed Services Security Operation Center (SOC) PT BIN
C94: PS-073-00 | D94: PTM | E94: Penyediaan ATS & Lisensi SIEM

Sheet PROGNOSA 2026
B2: No | C2: Kode Project | D2: Nama Pekerjaan | E2: Aktivity | F2: Satuan Kerja | G2: PIC | H2: Prognosa Biaya | I2: Periode | J2: Partner | K2: Keterangan | L2: Tahun
B3: 0 | C3: PS-024-00 | D3: =_xlfn.XLOOKUP(C3,'KODE PROJECT BARU'!$C$5:$C$98,'KODE PROJECT BARU'!$E$5:$E$98,"N/A",0,1) -> #NAME? | E3: Biaya Pekerja | F3: DMO | G3: Fikar | H3: 1000 | I3: AGUSTUS | J3: PT Personel Alih Daya
C6: PS-019-00 | D6: =_xlfn.XLOOKUP(C6,'KODE PROJECT BARU'!$C$5:$C$98,'KODE PROJECT BARU'!$E$5:$E$98,"N/A",0,1) -> #NAME? | E6: BIAYA BUFFER | F6: DMO | G6: CHYNTIA | H6: 3117000 | I6: JULI | J6: =UPPER(J3) -> PT PERSONEL ALIH DAYA | L6: 2026
C7: PS-019-00 | D7: =_xlfn.XLOOKUP(C7,'KODE PROJECT BARU'!$C$5:$C$98,'KODE PROJECT BARU'!$E$5:$E$98,"N/A",0,1) -> #NAME? | E7: BIAYA BUFFER | F7: DMO | G7: CHYNTIA | H7: 3117000 | I7: OKTOBER | J7: PT PERSONEL ALIH DAYA | L7: 2026
C8: PS-019-00 | D8: =_xlfn.XLOOKUP(C8,'KODE PROJECT BARU'!$C$5:$C$98,'KODE PROJECT BARU'!$E$5:$E$98,"N/A",0,1) -> #NAME? | E8: BIAYA BUFFER | F8: DMO | G8: CHYNTIA | H8: 3117000 | I8: DESEMBER | J8: PT PERSONEL ALIH DAYA | L8: 2026
C9: PS-019-00 | D9: =_xlfn.XLOOKUP(C9,'KODE PROJECT BARU'!$C$5:$C$98,'KODE PROJECT BARU'!$E$5:$E$98,"N/A",0,1) -> #NAME? | E9: UPAH | F9: DMO | G9: CHYNTIA | H9: 27622955 | I9: JULI | J9: PT PERSONEL ALIH DAYA | L9: 2026
C10: PS-019-00 | D10: =_xlfn.XLOOKUP(C10,'KODE PROJECT BARU'!$C$5:$C$98,'KODE PROJECT BARU'!$E$5:$E$98,"N/A",0,1) -> #NAME? | E10: UPAH | F10: DMO | G10: CHYNTIA | H10: 27622955 | I10: AGUSTUS | J10: PT PERSONEL ALIH DAYA | L10: 2026
C11: PS-019-00 | D11: =_xlfn.XLOOKUP(C11,'KODE PROJECT BARU'!$C$5:$C$98,'KODE PROJECT BARU'!$E$5:$E$98,"N/A",0,1) -> #NAME? | E11: UPAH | F11: DMO | G11: CHYNTIA | H11: 27622955 | I11: SEPTEMBER | J11: PT PERSONEL ALIH DAYA | L11: 2026
C12: PS-019-00 | D12: =_xlfn.XLOOKUP(C12,'KODE PROJECT BARU'!$C$5:$C$98,'KODE PROJECT BARU'!$E$5:$E$98,"N/A",0,1) -> #NAME? | E12: UPAH | F12: DMO | G12: CHYNTIA | H12: 27622955 | I12: OKTOBER | J12: PT PERSONEL ALIH DAYA | L12: 2026
C13: PS-019-00 | D13: =_xlfn.XLOOKUP(C13,'KODE PROJECT BARU'!$C$5:$C$98,'KODE PROJECT BARU'!$E$5:$E$98,"N/A",0,1) -> #NAME? | E13: UPAH | F13: DMO | G13: CHYNTIA | H13: 27622955 | I13: NOVEMBER | J13: PT PERSONEL ALIH DAYA | L13: 2026
C14: PS-019-00 | D14: =_xlfn.XLOOKUP(C14,'KODE PROJECT BARU'!$C$5:$C$98,'KODE PROJECT BARU'!$E$5:$E$98,"N/A",0,1) -> #NAME? | E14: UPAH | F14: DMO | G14: CHYNTIA | H14: 27622955 | I14: DESEMBER | J14: PT PERSONEL ALIH DAYA | L14: 2026
C15: PS-019-00 | D15: =_xlfn.XLOOKUP(C15,'KODE PROJECT BARU'!$C$5:$C$98,'KODE PROJECT BARU'!$E$5:$E$98,"N/A",0,1) -> #NAME? | E15: PIKET NATARU | F15: DMO | G15: CHYNTIA | H15: 2168861 | I15: DESEMBER | J15: PT PERSONEL ALIH DAYA | L15: 2026
C16: PS-019-00 | D16: =_xlfn.XLOOKUP(C16,'KODE PROJECT BARU'!$C$5:$C$98,'KODE PROJECT BARU'!$E$5:$E$98,"N/A",0,1) -> #NAME? | E16: SPPD | F16: DMO | G16: CHYNTIA | H16: 12149698 | I16: DESEMBER | J16: PT PERSONEL ALIH DAYA | L16: 2026
C17: PS-019-00 | D17: =_xlfn.XLOOKUP(C17,'KODE PROJECT BARU'!$C$5:$C$98,'KODE PROJECT BARU'!$E$5:$E$98,"N/A",0,1) -> #NAME? | E17: TRAINING | F17: DMO | G17: CHYNTIA | H17: 4119200 | I17: DESEMBER | J17: PT PERSONEL ALIH DAYA | L17: 2026
C18: PS-019-00 | D18: =_xlfn.XLOOKUP(C18,'KODE PROJECT BARU'!$C$5:$C$98,'KODE PROJECT BARU'!$E$5:$E$98,"N/A",0,1) -> #NAME? | E18: WORKSHOP | F18: DMO | G18: CHYNTIA | H18: 248988231 | I18: DESEMBER | J18: PT PERSONEL ALIH DAYA | L18: 2026
... C21: PS-040-00 | D21: =_xlfn.XLOOKUP(C21,'KODE PROJECT BARU'!$C$5:$C$98,'KODE PROJECT BARU'!$E$5:$E$98,"N/A",0,1) -> #NAME? | E21: VAPT 2 | F21: OSM | G21: RIKI | H21: 27500000 | I21: DESEMBER | J21: PT. CYNNEX INTEGRASI SOLUSI | L21: 2026
C22: PS-040-00 | D22: =_xlfn.XLOOKUP(C22,'KODE PROJECT BARU'!$C$5:$C$98,'KODE PROJECT BARU'!$E$5:$E$98,"N/A",0,1) -> #NAME? | E22: CLOUD VPS | F22: OSM | G22: RIKI | H22: =360000000/3 -> 120000000 | I22: DESEMBER | J22: PT DATACOMM DIANGRAHA | L22: 2026
C23: PS-040-00 | D23: =_xlfn.XLOOKUP(C23,'KODE PROJECT BARU'!$C$5:$C$98,'KODE PROJECT BARU'!$E$5:$E$98,"N/A",0,1) -> #NAME? | E23: CLOUD VPS(AMD) | F23: OSM | G23: RIKI | H23: 18000000 | I23: DESEMBER | L23: 2026
C24: PS-030-00 | D24: =_xlfn.XLOOKUP(C24,'KODE PROJECT BARU'!$C$5:$C$98,'KODE PROJECT BARU'!$E$5:$E$98,"N/A",0,1) -> #NAME? | E24: MRC MEI | F24: OSM | G24: RIKI | H24: 367250000 | I24: JULI | J24: PT. BERCA HARDAYAPRAKARSA | L24: 2026
C25: PS-030-00 | D25: =_xlfn.XLOOKUP(C25,'KODE PROJECT BARU'!$C$5:$C$98,'KODE PROJECT BARU'!$E$5:$E$98,"N/A",0,1) -> #NAME? | E25: MRC JUNI | F25: OSM | G25: RIKI | H25: 367250000 | I25: AGUSTUS | L25: 2026
C26: PS-030-00 | D26: =_xlfn.XLOOKUP(C26,'KODE PROJECT BARU'!$C$5:$C$98,'KODE PROJECT BARU'!$E$5:$E$98,"N/A",0,1) -> #NAME? | E26: MRC JULI | F26: OSM | G26: RIKI | H26: 367250000 | I26: SEPTEMBER | L26: 2026
C27: PS-030-00 | D27: =_xlfn.XLOOKUP(C27,'KODE PROJECT BARU'!$C$5:$C$98,'KODE PROJECT BARU'!$E$5:$E$98,"N/A",0,1) -> #NAME? | E27: MRC AGUSTUS | F27: OSM | G27: RIKI | H27: 367250000 | I27: OKTOBER | L27: 2026
C28: PS-030-00 | D28: =_xlfn.XLOOKUP(C28,'KODE PROJECT BARU'!$C$5:$C$98,'KODE PROJECT BARU'!$E$5:$E$98,"N/A",0,1) -> #NAME? | E28: MRC SEPTEMBER | F28: OSM | G28: RIKI | H28: 367250000 | I28: NOVEMBER | L28: 2026
C29: PS-030-00 | D29: =_xlfn.XLOOKUP(C29,'KODE PROJECT BARU'!$C$5:$C$98,'KODE PROJECT BARU'!$E$5:$E$98,"N/A",0,1) -> #NAME? | E29: MRC OKTOBER | F29: OSM | G29: RIKI | H29: 367250000 | I29: DESEMBER | L29: 2026
C30: PS-030-00 | D30: =_xlfn.XLOOKUP(C30,'KODE PROJECT BARU'!$C$5:$C$98,'KODE PROJECT BARU'!$E$5:$E$98,"N/A",0,1) -> #NAME? | E30: MRC NOVEMBER | F30: OSM | G30: RIKI | H30: 367250000 | I30: DESEMBER | L30: 2026
C31: PS-030-00 | D31: =_xlfn.XLOOKUP(C31,'KODE PROJECT BARU'!$C$5:$C$98,'KODE PROJECT BARU'!$E$5:$E$98,"N/A",0,1) -> #NAME? | E31: MRC DESEMBER | F31: OSM | G31: RIKI | H31: 367250000 | I31: DESEMBER | L31: 2026
C32: PS-030-00 | D32: =_xlfn.XLOOKUP(C32,'KODE PROJECT BARU'!$C$5:$C$98,'KODE PROJECT BARU'!$E$5:$E$98,"N/A",0,1) -> #NAME? | E32: AMD JASA INSTALASI RAM | F32: OSM | G32: RIKI | H32: 57000000 | I32: JULI | L32: 2026
C33: PS-030-00 | D33: =_xlfn.XLOOKUP(C33,'KODE PROJECT BARU'!$C$5:$C$98,'KODE PROJECT BARU'!$E$5:$E$98,"N/A",0,1) -> #NAME? | E33: ADD POWER DCI 3KVA | F33: OSM | G33: RIKI | H33: 216000000 | I33: DESEMBER | J33: PT. DCI | K33: SO 626 | L33: 2026
C34: PS-018-00 | D34: =_xlfn.XLOOKUP(C34,'KODE PROJECT BARU'!$C$5:$C$98,'KODE PROJECT BARU'!$E$5:$E$98,"N/A",0,1) -> #NAME? | E34: Biaya Pekerja | F34: DMO | G34: CHYNTIA | H34: =9959571+28053000+338125868 -> 376138439 | I34: JULI | J34: PT PERSONEL ALIH DAYA | L34: 2026
C35: PS-018-00 | D35: =_xlfn.XLOOKUP(C35,'KODE PROJECT BARU'!$C$5:$C$98,'KODE PROJECT BARU'!$E$5:$E$98,"N/A",0,1) -> #NAME? | E35: Biaya Pekerja | F35: DMO | G35: CHYNTIA | H35: =9959571+338125868 -> 348085439 | I35: AGUSTUS | J35: PT PERSONEL ALIH DAYA | L35: 2026
C36: PS-018-00 | D36: =_xlfn.XLOOKUP(C36,'KODE PROJECT BARU'!$C$5:$C$98,'KODE PROJECT BARU'!$E$5:$E$98,"N/A",0,1) -> #NAME? | E36: Biaya Pekerja | F36: DMO | G36: CHYNTIA | H36: =9959571+338125868 -> 348085439 | I36: SEPTEMBER | J36: PT PERSONEL ALIH DAYA | L36: 2026
C37: PS-018-00 | D37: =_xlfn.XLOOKUP(C37,'KODE PROJECT BARU'!$C$5:$C$98,'KODE PROJECT BARU'!$E$5:$E$98,"N/A",0,1) -> #NAME? | E37: Biaya Pekerja | F37: DMO | G37: CHYNTIA | H37: =9959571+28053000+338125868 -> 376138439 | I37: OKTOBER | J37: PT PERSONEL ALIH DAYA | L37: 2026
C38: PS-018-00 | D38: =_xlfn.XLOOKUP(C38,'KODE PROJECT BARU'!$C$5:$C$98,'KODE PROJECT BARU'!$E$5:$E$98,"N/A",0,1) -> #NAME? | E38: Biaya Pekerja | F38: DMO | G38: CHYNTIA | H38: =9959571+338125868 -> 348085439 | I38: NOVEMBER | J38: PT PERSONEL ALIH DAYA | L38: 2026
C39: PS-018-00 | D39: =_xlfn.XLOOKUP(C39,'KODE PROJECT BARU'!$C$5:$C$98,'KODE PROJECT BARU'!$E$5:$E$98,"N/A",0,1) -> #NAME? | E39: Biaya Pekerja | F39: DMO | G39: CHYNTIA | H39: =9959571+28053000+338125868+5452613+31923800+295739679+255116431+37579894 -> 1001950856 | I39: DESEMBER | J39: PT PERSONEL ALIH DAYA | L39: 2026
C54: PS-023-00 | D54: =_xlfn.XLOOKUP(C54,'KODE PROJECT BARU'!$C$5:$C$98,'KODE PROJECT BARU'!$E$5:$E$98,"N/A",0,1) -> #NAME? | E54: PARKIR | F54: DMO | G54: CHYNTIA | H54: 822888 | I54: JULI | J54: PT PERSONEL ALIH DAYA | L54: 2026
C55: PS-023-00 | D55: =_xlfn.XLOOKUP(C55,'KODE PROJECT BARU'!$C$5:$C$98,'KODE PROJECT BARU'!$E$5:$E$98,"N/A",0,1) -> #NAME? | E55: PARKIR | F55: DMO | G55: CHYNTIA | H55: 822888 | I55: AGUSTUS | J55: PT PERSONEL ALIH DAYA | L55: 2026
C56: PS-023-00 | D56: =_xlfn.XLOOKUP(C56,'KODE PROJECT BARU'!$C$5:$C$98,'KODE PROJECT BARU'!$E$5:$E$98,"N/A",0,1) -> #NAME? | E56: PARKIR | F56: DMO | G56: CHYNTIA | H56: 822888 | I56: SEPTEMBER | J56: PT PERSONEL ALIH DAYA | L56: 2026
C57: PS-023-00 | D57: =_xlfn.XLOOKUP(C57,'KODE PROJECT BARU'!$C$5:$C$98,'KODE PROJECT BARU'!$E$5:$E$98,"N/A",0,1) -> #NAME? | E57: PARKIR | F57: DMO | G57: CHYNTIA | H57: 822888 | I57: OKTOBER | J57: PT PERSONEL ALIH DAYA | L57: 2026
C58: PS-023-00 | D58: =_xlfn.XLOOKUP(C58,'KODE PROJECT BARU'!$C$5:$C$98,'KODE PROJECT BARU'!$E$5:$E$98,"N/A",0,1) -> #NAME? | E58: PARKIR | F58: DMO | G58: CHYNTIA | H58: 822888 | I58: NOVEMBER | J58: PT PERSONEL ALIH DAYA | L58: 2026
C59: PS-023-00 | D59: =_xlfn.XLOOKUP(C59,'KODE PROJECT BARU'!$C$5:$C$98,'KODE PROJECT BARU'!$E$5:$E$98,"N/A",0,1) -> #NAME? | E59: PARKIR | F59: DMO | G59: CHYNTIA | H59: 822888 | I59: DESEMBER | J59: PT PERSONEL ALIH DAYA | L59: 2026
C60: PS-023-00 | D60: =_xlfn.XLOOKUP(C60,'KODE PROJECT BARU'!$C$5:$C$98,'KODE PROJECT BARU'!$E$5:$E$98,"N/A",0,1) -> #NAME? | E60: SPPD | F60: DMO | G60: CHYNTIA | H60: 67295703 | I60: JULI | J60: PT PERSONEL ALIH DAYA | L60: 2026
C61: PS-023-00 | D61: =_xlfn.XLOOKUP(C61,'KODE PROJECT BARU'!$C$5:$C$98,'KODE PROJECT BARU'!$E$5:$E$98,"N/A",0,1) -> #NAME? | E61: SPPD | F61: DMO | G61: CHYNTIA | H61: 67295703 | I61: AGUSTUS | J61: PT PERSONEL ALIH DAYA | L61: 2026
C62: PS-023-00 | D62: =_xlfn.XLOOKUP(C62,'KODE PROJECT BARU'!$C$5:$C$98,'KODE PROJECT BARU'!$E$5:$E$98,"N/A",0,1) -> #NAME? | E62: SPPD | F62: DMO | G62: CHYNTIA | H62: 67295703 | I62: SEPTEMBER | J62: PT PERSONEL ALIH DAYA | L62: 2026
C63: PS-023-00 | D63: =_xlfn.XLOOKUP(C63,'KODE PROJECT BARU'!$C$5:$C$98,'KODE PROJECT BARU'!$E$5:$E$98,"N/A",0,1) -> #NAME? | E63: SPPD | F63: DMO | G63: CHYNTIA | H63: 67295703 | I63: OKTOBER | J63: PT PERSONEL ALIH DAYA | L63: 2026
C64: PS-023-00 | D64: =_xlfn.XLOOKUP(C64,'KODE PROJECT BARU'!$C$5:$C$98,'KODE PROJECT BARU'!$E$5:$E$98,"N/A",0,1) -> #NAME? | E64: SPPD | F64: DMO | G64: CHYNTIA | H64: 67295703 | I64: NOVEMBER | J64: PT PERSONEL ALIH DAYA | L64: 2026
C65: PS-023-00 | D65: =_xlfn.XLOOKUP(C65,'KODE PROJECT BARU'!$C$5:$C$98,'KODE PROJECT BARU'!$E$5:$E$98,"N/A",0,1) -> #NAME? | E65: SPPD | F65: DMO | G65: CHYNTIA | H65: 67295703 | I65: DESEMBER | J65: PT PERSONEL ALIH DAYA | L65: 2026
... C78: PS-023-00 | D78: =_xlfn.XLOOKUP(C78,'KODE PROJECT BARU'!$C$5:$C$98,'KODE PROJECT BARU'!$E$5:$E$98,"N/A",0,1) -> #NAME? | E78: KOMPENSASI | F78: DMO | G78: CHYNTIA | H78: 468431932 | I78: DESEMBER | J78: PT PERSONEL ALIH DAYA | L78: 2026
C79: PS-004-00 | D79: =_xlfn.XLOOKUP(C79,'KODE PROJECT BARU'!$C$5:$C$98,'KODE PROJECT BARU'!$E$5:$E$98,"N/A",0,1) -> #NAME? | E79: Biaya Pekerja | F79: DMO | G79: CHYNTIA | H79: =45176460+10545850+634181698+12494268 -> 702398276 | I79: JULI | J79: PT PERSONEL ALIH DAYA | L79: 2026
C80: PS-004-00 | D80: =_xlfn.XLOOKUP(C80,'KODE PROJECT BARU'!$C$5:$C$98,'KODE PROJECT BARU'!$E$5:$E$98,"N/A",0,1) -> #NAME? | E80: Biaya Pekerja | F80: DMO | G80: CHYNTIA | H80: =45176460+10545850+634181698 -> 689904008 | I80: AGUSTUS | J80: PT PERSONEL ALIH DAYA | L80: 2026
C81: PS-004-00 | D81: =_xlfn.XLOOKUP(C81,'KODE PROJECT BARU'!$C$5:$C$98,'KODE PROJECT BARU'!$E$5:$E$98,"N/A",0,1) -> #NAME? | E81: Biaya Pekerja | F81: DMO | G81: CHYNTIA | H81: =45176460+10545850+634181698 -> 689904008 | I81: SEPTEMBER | J81: PT PERSONEL ALIH DAYA | L81: 2026
C82: PS-004-00 | D82: =_xlfn.XLOOKUP(C82,'KODE PROJECT BARU'!$C$5:$C$98,'KODE PROJECT BARU'!$E$5:$E$98,"N/A",0,1) -> #NAME? | E82: Biaya Pekerja | F82: DMO | G82: CHYNTIA | H82: =45176460+10545850+634181698 -> 689904008 | I82: OKTOBER | J82: PT PERSONEL ALIH DAYA | L82: 2026
C83: PS-004-00 | D83: =_xlfn.XLOOKUP(C83,'KODE PROJECT BARU'!$C$5:$C$98,'KODE PROJECT BARU'!$E$5:$E$98,"N/A",0,1) -> #NAME? | E83: Biaya Pekerja | F83: DMO | G83: CHYNTIA | H83: =45176460+10545850+634181698 -> 689904008 | I83: NOVEMBER | J83: PT PERSONEL ALIH DAYA | L83: 2026
C84: PS-004-00 | D84: =_xlfn.XLOOKUP(C84,'KODE PROJECT BARU'!$C$5:$C$98,'KODE PROJECT BARU'!$E$5:$E$98,"N/A",0,1) -> #NAME? | E84: Biaya Pekerja | F84: DMO | G84: CHYNTIA | H84: =45176460+10545850+634181698+(7090000*6)+571828533+75278442+72745072+22231116 -> 1474527171 | I84: DESEMBER | J84: PT PERSONEL ALIH DAYA | L84: 2026
C108: PS-046-00 | D108: =_xlfn.XLOOKUP(C108,'KODE PROJECT BARU'!$C$5:$C$98,'KODE PROJECT BARU'!$E$5:$E$98,"N/A",0,1) -> #NAME? | E108: UPAH | F108: DMO | G108: CHYNTIA | H108: 8051854 | I108: JULI | J108: PT PERSONEL ALIH DAYA | L108: 2026
C109: PS-046-00 | D109: =_xlfn.XLOOKUP(C109,'KODE PROJECT BARU'!$C$5:$C$98,'KODE PROJECT BARU'!$E$5:$E$98,"N/A",0,1) -> #NAME? | E109: UPAH | F109: DMO | G109: CHYNTIA | H109: 8051854 | I109: AGUSTUS | J109: PT PERSONEL ALIH DAYA | L109: 2026
C110: PS-046-00 | D110: =_xlfn.XLOOKUP(C110,'KODE PROJECT BARU'!$C$5:$C$98,'KODE PROJECT BARU'!$E$5:$E$98,"N/A",0,1) -> #NAME? | E110: UPAH | F110: DMO | G110: CHYNTIA | H110: 8051854 | I110: SEPTEMBER | J110: PT PERSONEL ALIH DAYA | L110: 2026
C111: PS-046-00 | D111: =_xlfn.XLOOKUP(C111,'KODE PROJECT BARU'!$C$5:$C$98,'KODE PROJECT BARU'!$E$5:$E$98,"N/A",0,1) -> #NAME? | E111: UPAH | F111: DMO | G111: CHYNTIA | H111: 8051854 | I111: OKTOBER | J111: PT PERSONEL ALIH DAYA | L111: 2026
C112: PS-046-00 | D112: =_xlfn.XLOOKUP(C112,'KODE PROJECT BARU'!$C$5:$C$98,'KODE PROJECT BARU'!$E$5:$E$98,"N/A",0,1) -> #NAME? | E112: UPAH | F112: DMO | G112: CHYNTIA | H112: 8051854 | I112: NOVEMBER | J112: PT PERSONEL ALIH DAYA | L112: 2026
C113: PS-046-00 | D113: =_xlfn.XLOOKUP(C113,'KODE PROJECT BARU'!$C$5:$C$98,'KODE PROJECT BARU'!$E$5:$E$98,"N/A",0,1) -> #NAME? | E113: UPAH | F113: DMO | G113: CHYNTIA | H113: 8051854 | I113: DESEMBER | J113: PT PERSONEL ALIH DAYA | L113: 2026
C114: PS-046-00 | D114: =_xlfn.XLOOKUP(C114,'KODE PROJECT BARU'!$C$5:$C$98,'KODE PROJECT BARU'!$E$5:$E$98,"N/A",0,1) -> #NAME? | E114: KOMPENSASI | F114: DMO | G114: CHYNTIA | H114: 6213220 | I114: DESEMBER | J114: PT PERSONEL ALIH DAYA | L114: 2026
C115: PS-046-00 | D115: =_xlfn.XLOOKUP(C115,'KODE PROJECT BARU'!$C$5:$C$98,'KODE PROJECT BARU'!$E$5:$E$98,"N/A",0,1) -> #NAME? | E115: SPPD | F115: DMO | G115: CHYNTIA | H115: 12860742 | I115: AGUSTUS | J115: PT PERSONEL ALIH DAYA | L115: 2026
C116: PS-046-00 | D116: =_xlfn.XLOOKUP(C116,'KODE PROJECT BARU'!$C$5:$C$98,'KODE PROJECT BARU'!$E$5:$E$98,"N/A",0,1) -> #NAME? | E116: SPPD | F116: DMO | G116: CHYNTIA | H116: =H115 -> 12860742 | I116: DESEMBER | J116: PT PERSONEL ALIH DAYA | L116: 2026
C117: PS-047-00 | D117: =_xlfn.XLOOKUP(C117,'KODE PROJECT BARU'!$C$5:$C$98,'KODE PROJECT BARU'!$E$5:$E$98,"N/A",0,1) -> #NAME? | E117: UPAH | F117: DMO | G117: CHYNTIA | H117: 178204573 | I117: JULI | J117: PT PERSONEL ALIH DAYA | L117: 2026
C118: PS-047-00 | D118: =_xlfn.XLOOKUP(C118,'KODE PROJECT BARU'!$C$5:$C$98,'KODE PROJECT BARU'!$E$5:$E$98,"N/A",0,1) -> #NAME? | E118: UPAH | F118: DMO | G118: CHYNTIA | H118: 178204573 | I118: AGUSTUS | J118: PT PERSONEL ALIH DAYA | L118: 2026
C119: PS-047-00 | D119: =_xlfn.XLOOKUP(C119,'KODE PROJECT BARU'!$C$5:$C$98,'KODE PROJECT BARU'!$E$5:$E$98,"N/A",0,1) -> #NAME? | E119: UPAH | F119: DMO | G119: CHYNTIA | H119: 178204573 | I119: SEPTEMBER | J119: PT PERSONEL ALIH DAYA | L119: 2026
C120: PS-047-00 | D120: =_xlfn.XLOOKUP(C120,'KODE PROJECT BARU'!$C$5:$C$98,'KODE PROJECT BARU'!$E$5:$E$98,"N/A",0,1) -> #NAME? | E120: UPAH | F120: DMO | G120: CHYNTIA | H120: 178204573 | I120: OKTOBER | J120: PT PERSONEL ALIH DAYA | L120: 2026
C121: PS-047-00 | D121: =_xlfn.XLOOKUP(C121,'KODE PROJECT BARU'!$C$5:$C$98,'KODE PROJECT BARU'!$E$5:$E$98,"N/A",0,1) -> #NAME? | E121: UPAH | F121: DMO | G121: CHYNTIA | H121: 178204573 | I121: NOVEMBER | J121: PT PERSONEL ALIH DAYA | L121: 2026
C122: PS-047-00 | D122: =_xlfn.XLOOKUP(C122,'KODE PROJECT BARU'!$C$5:$C$98,'KODE PROJECT BARU'!$E$5:$E$98,"N/A",0,1) -> #NAME? | E122: UPAH | F122: DMO | G122: CHYNTIA | H122: 178204573 | I122: DESEMBER | J122: PT PERSONEL ALIH DAYA | L122: 2026
C123: PS-047-00 | D123: =_xlfn.XLOOKUP(C123,'KODE PROJECT BARU'!$C$5:$C$98,'KODE PROJECT BARU'!$E$5:$E$98,"N/A",0,1) -> #NAME? | E123: TUNJANGAN OFFSHORE | F123: DMO | G123: CHYNTIA | H123: 51601935 | I123: JULI | J123: PT PERSONEL ALIH DAYA | L123: 2026
C124: PS-047-00 | D124: =_xlfn.XLOOKUP(C124,'KODE PROJECT BARU'!$C$5:$C$98,'KODE PROJECT BARU'!$E$5:$E$98,"N/A",0,1) -> #NAME? | E124: TUNJANGAN OFFSHORE | F124: DMO | G124: CHYNTIA | H124: 51601935 | I124: AGUSTUS | J124: PT PERSONEL ALIH DAYA | L124: 2026
C125: PS-047-00 | D125: =_xlfn.XLOOKUP(C125,'KODE PROJECT BARU'!$C$5:$C$98,'KODE PROJECT BARU'!$E$5:$E$98,"N/A",0,1) -> #NAME? | E125: TUNJANGAN OFFSHORE | F125: DMO | G125: CHYNTIA | H125: 51601935 | I125: SEPTEMBER | J125: PT PERSONEL ALIH DAYA | L125: 2026
C126: PS-047-00 | D126: =_xlfn.XLOOKUP(C126,'KODE PROJECT BARU'!$C$5:$C$98,'KODE PROJECT BARU'!$E$5:$E$98,"N/A",0,1) -> #NAME? | E126: TUNJANGAN OFFSHORE | F126: DMO | G126: CHYNTIA | H126: 51601935 | I126: OKTOBER | J126: PT PERSONEL ALIH DAYA | L126: 2026
C127: PS-047-00 | D127: =_xlfn.XLOOKUP(C127,'KODE PROJECT BARU'!$C$5:$C$98,'KODE PROJECT BARU'!$E$5:$E$98,"N/A",0,1) -> #NAME? | E127: TUNJANGAN OFFSHORE | F127: DMO | G127: CHYNTIA | H127: 51601935 | I127: NOVEMBER | J127: PT PERSONEL ALIH DAYA | L127: 2026
C128: PS-047-00 | D128: =_xlfn.XLOOKUP(C128,'KODE PROJECT BARU'!$C$5:$C$98,'KODE PROJECT BARU'!$E$5:$E$98,"N/A",0,1) -> #NAME? | E128: TUNJANGAN OFFSHORE | F128: DMO | G128: CHYNTIA | H128: 51601935 | I128: DESEMBER | J128: PT PERSONEL ALIH DAYA | L128: 2026
... C207: PS-028-00 | D207: =_xlfn.XLOOKUP(C207,'KODE PROJECT BARU'!$C$5:$C$98,'KODE PROJECT BARU'!$E$5:$E$98,"N/A",0,1) -> #NAME? | E207: UPAH | F207: DMO | G207: CHYNTIA | H207: 21177184 | I207: DESEMBER | J207: PT PERSONEL ALIH DAYA | L207: 2026
C208: PS-028-00 | D208: =_xlfn.XLOOKUP(C208,'KODE PROJECT BARU'!$C$5:$C$98,'KODE PROJECT BARU'!$E$5:$E$98,"N/A",0,1) -> #NAME? | E208: KOMPENSASI | F208: DMO | G208: CHYNTIA | H208: =14545600*1.039 -> 15112878 | I208: DESEMBER | J208: PT PERSONEL ALIH DAYA | L208: 2026
C209: PS-028-00 | D209: =_xlfn.XLOOKUP(C209,'KODE PROJECT BARU'!$C$5:$C$98,'KODE PROJECT BARU'!$E$5:$E$98,"N/A",0,1) -> #NAME? | E209: TRAINING | F209: DMO | G209: CHYNTIA | H209: 7826480 | I209: DESEMBER | J209: PT PERSONEL ALIH DAYA | L209: 2026
C210: PS-028-00 | D210: =_xlfn.XLOOKUP(C210,'KODE PROJECT BARU'!$C$5:$C$98,'KODE PROJECT BARU'!$E$5:$E$98,"N/A",0,1) -> #NAME? | E210: PIKET NATARU | F210: DMO | G210: CHYNTIA | H210: 3117000 | I210: DESEMBER | J210: PT PERSONEL ALIH DAYA | L210: 2026
C211: PS-008-00 | D211: =_xlfn.XLOOKUP(C211,'KODE PROJECT BARU'!$C$5:$C$98,'KODE PROJECT BARU'!$E$5:$E$98,"N/A",0,1) -> #NAME? | E211: Biaya Pekerja | F211: DMO | G211: CHYNTIA | H211: =1558500+8544536 -> 10103036 | I211: JULI | J211: PT PERSONEL ALIH DAYA | L211: 2026
C212: PS-008-00 | D212: =_xlfn.XLOOKUP(C212,'KODE PROJECT BARU'!$C$5:$C$98,'KODE PROJECT BARU'!$E$5:$E$98,"N/A",0,1) -> #NAME? | E212: Biaya Pekerja | F212: DMO | G212: CHYNTIA | H212: =1558500+8544536 -> 10103036 | I212: OKTOBER | J212: PT PERSONEL ALIH DAYA | L212: 2026
C213: PS-008-00 | D213: =_xlfn.XLOOKUP(C213,'KODE PROJECT BARU'!$C$5:$C$98,'KODE PROJECT BARU'!$E$5:$E$98,"N/A",0,1) -> #NAME? | E213: Biaya Pekerja | F213: DMO | G213: CHYNTIA | H213: =1558500+8544536+6638281 -> 16741317 | I213: DESEMBER | J213: PT PERSONEL ALIH DAYA | L213: 2026
C215: PS-008-00 | D215: =_xlfn.XLOOKUP(C215,'KODE PROJECT BARU'!$C$5:$C$98,'KODE PROJECT BARU'!$E$5:$E$98,"N/A",0,1) -> #NAME? | E215: Biaya Pekerja | F215: DMO | G215: CHYNTIA | H215: 8544536 | I215: AGUSTUS | J215: PT PERSONEL ALIH DAYA | L215: 2026
C216: PS-008-00 | D216: =_xlfn.XLOOKUP(C216,'KODE PROJECT BARU'!$C$5:$C$98,'KODE PROJECT BARU'!$E$5:$E$98,"N/A",0,1) -> #NAME? | E216: Biaya Pekerja | F216: DMO | G216: CHYNTIA | H216: 8544536 | I216: SEPTEMBER | J216: PT PERSONEL ALIH DAYA | L216: 2026
C218: PS-008-00 | D218: =_xlfn.XLOOKUP(C218,'KODE PROJECT BARU'!$C$5:$C$98,'KODE PROJECT BARU'!$E$5:$E$98,"N/A",0,1) -> #NAME? | E218: Biaya Pekerja | F218: DMO | G218: CHYNTIA | H218: 8544536 | I218: NOVEMBER | J218: PT PERSONEL ALIH DAYA | L218: 2026
C221: PS-027-00 | D221: =_xlfn.XLOOKUP(C221,'KODE PROJECT BARU'!$C$5:$C$98,'KODE PROJECT BARU'!$E$5:$E$98,"N/A",0,1) -> #NAME? | E221: BIAYA BUFFER | F221: DMO | G221: CHYNTIA | H221: 1558500 | I221: JULI | J221: PT PERSONEL ALIH DAYA | L221: 2026
C222: PS-027-00 | D222: =_xlfn.XLOOKUP(C222,'KODE PROJECT BARU'!$C$5:$C$98,'KODE PROJECT BARU'!$E$5:$E$98,"N/A",0,1) -> #NAME? | E222: BIAYA BUFFER | F222: DMO | G222: CHYNTIA | H222: 1558500 | I222: OKTOBER | J222: PT PERSONEL ALIH DAYA | L222: 2026
C223: PS-027-00 | D223: =_xlfn.XLOOKUP(C223,'KODE PROJECT BARU'!$C$5:$C$98,'KODE PROJECT BARU'!$E$5:$E$98,"N/A",0,1) -> #NAME? | E223: UPAH | F223: DMO | G223: CHYNTIA | H223: 11548402 | I223: JULI | J223: PT PERSONEL ALIH DAYA | L223: 2026
C224: PS-027-00 | D224: =_xlfn.XLOOKUP(C224,'KODE PROJECT BARU'!$C$5:$C$98,'KODE PROJECT BARU'!$E$5:$E$98,"N/A",0,1) -> #NAME? | E224: UPAH | F224: DMO | G224: CHYNTIA | H224: 11548402 | I224: AGUSTUS | J224: PT PERSONEL ALIH DAYA | L224: 2026
C225: PS-027-00 | D225: =_xlfn.XLOOKUP(C225,'KODE PROJECT BARU'!$C$5:$C$98,'KODE PROJECT BARU'!$E$5:$E$98,"N/A",0,1) -> #NAME? | E225: UPAH | F225: DMO | G225: CHYNTIA | H225: 11548402 | I225: SEPTEMBER | J225: PT PERSONEL ALIH DAYA | L225: 2026
C226: PS-027-00 | D226: =_xlfn.XLOOKUP(C226,'KODE PROJECT BARU'!$C$5:$C$98,'KODE PROJECT BARU'!$E$5:$E$98,"N/A",0,1) -> #NAME? | E226: UPAH | F226: DMO | G226: CHYNTIA | H226: 11548402 | I226: OKTOBER | J226: PT PERSONEL ALIH DAYA | L226: 2026
C227: PS-027-00 | D227: =_xlfn.XLOOKUP(C227,'KODE PROJECT BARU'!$C$5:$C$98,'KODE PROJECT BARU'!$E$5:$E$98,"N/A",0,1) -> #NAME? | E227: UPAH | F227: DMO | G227: CHYNTIA | H227: 11548402 | I227: NOVEMBER | J227: PT PERSONEL ALIH DAYA | L227: 2026
C228: PS-027-00 | D228: =_xlfn.XLOOKUP(C228,'KODE PROJECT BARU'!$C$5:$C$98,'KODE PROJECT BARU'!$E$5:$E$98,"N/A",0,1) -> #NAME? | E228: UPAH | F228: DMO | G228: CHYNTIA | H228: 11548402 | I228: DESEMBER | J228: PT PERSONEL ALIH DAYA | L228: 2026
C229: PS-027-00 | D229: =_xlfn.XLOOKUP(C229,'KODE PROJECT BARU'!$C$5:$C$98,'KODE PROJECT BARU'!$E$5:$E$98,"N/A",0,1) -> #NAME? | E229: KOMPENSASI | F229: DMO | G229: CHYNTIA | H229: 8312000 | I229: DESEMBER | J229: PT PERSONEL ALIH DAYA | L229: 2026
... C256: PS-031-00 | D256: =_xlfn.XLOOKUP(C256,'KODE PROJECT BARU'!$C$5:$C$98,'KODE PROJECT BARU'!$E$5:$E$98,"N/A",0,1) -> #NAME? | E256: UPAH | F256: DMO | G256: CHYNTIA | H256: 23239484 | I256: DESEMBER | J256: PT PERSONEL ALIH DAYA | L256: 2026
C257: PS-031-00 | D257: =_xlfn.XLOOKUP(C257,'KODE PROJECT BARU'!$C$5:$C$98,'KODE PROJECT BARU'!$E$5:$E$98,"N/A",0,1) -> #NAME? | E257: KOMPENSASI | F257: DMO | G257: CHYNTIA | H257: =16120000*1.039 -> 16748680 | I257: DESEMBER | J257: PT PERSONEL ALIH DAYA | L257: 2026
C258: PS-056-00 | D258: =_xlfn.XLOOKUP(C258,'KODE PROJECT BARU'!$C$5:$C$98,'KODE PROJECT BARU'!$E$5:$E$98,"N/A",0,1) -> #NAME? | E258: UPAH | F258: DMO | G258: CHYNTIA | H258: 416356937 | I258: JULI | J258: PT PERSONEL ALIH DAYA | L258: 2026
C259: PS-056-00 | D259: =_xlfn.XLOOKUP(C259,'KODE PROJECT BARU'!$C$5:$C$98,'KODE PROJECT BARU'!$E$5:$E$98,"N/A",0,1) -> #NAME? | E259: UPAH | F259: DMO | G259: CHYNTIA | H259: 416356937 | I259: AGUSTUS | J259: PT PERSONEL ALIH DAYA | L259: 2026
C260: PS-056-00 | D260: =_xlfn.XLOOKUP(C260,'KODE PROJECT BARU'!$C$5:$C$98,'KODE PROJECT BARU'!$E$5:$E$98,"N/A",0,1) -> #NAME? | E260: UPAH | F260: DMO | G260: CHYNTIA | H260: 416356937 | I260: SEPTEMBER | J260: PT PERSONEL ALIH DAYA | L260: 2026
C261: PS-056-00 | D261: =_xlfn.XLOOKUP(C261,'KODE PROJECT BARU'!$C$5:$C$98,'KODE PROJECT BARU'!$E$5:$E$98,"N/A",0,1) -> #NAME? | E261: UPAH | F261: DMO | G261: CHYNTIA | H261: 416356937 | I261: OKTOBER | J261: PT PERSONEL ALIH DAYA | L261: 2026
C262: PS-056-00 | D262: =_xlfn.XLOOKUP(C262,'KODE PROJECT BARU'!$C$5:$C$98,'KODE PROJECT BARU'!$E$5:$E$98,"N/A",0,1) -> #NAME? | E262: UPAH | F262: DMO | G262: CHYNTIA | H262: 416356937 | I262: NOVEMBER | J262: PT PERSONEL ALIH DAYA | L262: 2026
...

Sheet APLIKASI
A2: No | B2: Kontrak Induk | C2: Kontrak Turunan | D2: Client | E2: Sales | F2: Area | G2: End of contract | H2: Nilai
A3: 1 | B3: kontrak tunggal | C3: Pekerjaan Penyediaan Aplikasi Performance And Competency Management Competency Management | D3: PT Gagas Energi Indonesia | E3: Hona | F3: HO | G3: 46023
A4: 2 | B4: kontrak tunggal | C4: Pekerjaan Jasa Developing Dashboard PSAIMS dan HSSE Forntliner System | D4: PT Perusahaan Gas Negara | E4: Kelvin | F4: HO | G4: 46022
A5: 3 | B5: kontrak tunggal | C5: Tindak Lanjut Pekerjaan Pengadaan Jasa Tekninal Asistensi Sistem Management Informasi Legal | D5: PT Perusahaan Gas Negara | E5: Kelvin | F5: HO | G5: 46288
A6: 4 | B6: kontrak tunggal | C6: Pengadaan Jasa Manage Service E-KYC | D6: PT Perusahaan Gas Negara | E6: Junita | F6: HO | G6: 46387
A7: 5 | B7: kontrak tunggal | C7: Layanan Customer Relationship Management Billing Retail (end mei 2024) | D7: PT Telemedia Dinamika Sarana | E7: Ega | F7: HO | G7: 45443
A8: 6 | B8: kontrak tunggal | C8: Pengadaan Pembangunan SIPGAS EM Fungsi Monitoring Komunikasi CRM Tahun 2024 | D8: PT Perusahaan Gas Negara | E8: Kelvin | F8: HO | G8: 45657
A9: 7 | B9: kontrak tunggal | C9: Perpanjangan Layanan Delivery Pekerjaan Pengadaan Sewa Aplikasi Point of Sales untuk Pemberdayaan Aset 2026 | D9: PT Perusahaan Gas Negara | E9: Nisa | F9: HO | G9: 46022
A10: 8 | B10: kontrak tunggal | C10: Managed Service Aplikasi Pengelolaan Piutang (Modul Restrukturisasi Piutang & Pengendalian {Pemakaian Gas) | D10: PT Perusahaan Gas Negara | E10: Junita | F10: HO | G10: 46022
A11: 9 | B11: kontrak tunggal | C11: Delivery Jasa Pemeliharaan APlikasi HSSE Online System and Indicator Performance Center | D11: PT Perusahaan Gas Negara | E11: Kelvin | F11: HO | G11: 46022
A12: 10 | C12: Smart meter | D12: PT Perusahaan Gas Negara | E12: Erdika | F12: HO
A13: 11 | B13: kontrak tunggal | C13: Geospatial Update Licensing Information System | D13: PT Perusahaan Gas Negara | E13: Mumtaz | F13: RO Bekasi | G13: 46022
A14: 12 | B14: kontrak tunggal | C14: Jasa Pembuatan Sistem Data Kinerja PGN SOR III | D14: PT Perusahaan Gas Negara | E14: Rosiana | F14: RO Jabatim | G14: 45994
A15: 13 | B15: kontrak tunggal | C15: Pengembangan dan Peningkatan Kapabilitas Aplikasi ENERGY (Enterprise Revenue Generation System) | D15: PT Perusahaan Gas Negara | E15: Alifa | F15: RO Jakarta | G15: 46022
A16: 14 | B16: LPASI 2025 | C16: LPASI : Pembuatan Dashboard ELO Procurement | D16: PT Perusahaan Gas Negara | E16: Alifa | F16: RO Jakarta | G16: 46022
A17: 15 | B17: LPASI 2025 | C17: LPASI : Implementasi DAMARA & ELO ECM Suite | D17: PT Perusahaan Gas Negara | E17: Alifa | F17: RO Jakarta | G17: 46022
A18: 16 | B18: LPASI 2025 | C18: Jasa Pengembangan Aplikasi Gas Up (Coaching & Mentoring) | D18: PT Perusahaan Gas Negara | E18: Alifa | F18: RO Jakarta | G18: 46022
A19: 17 | B19: LPASI 2025 | C19: Pekerjaan Pengembangan Aplikasi PGN E-Lease Tahun 2025 | D19: PT Perusahaan Gas Negara | E19: Alifa | F19: RO Jakarta | G19: 46022
A20: 18 | C20: Website PGN | D20: PT Perusahaan Gas Negara | E20: Alifa | F20: RO Jakarta
A21: 19 | B21: LPASI 2025 | C21: Pengembangan Aplikasi Digitalisasi Berlangganan Gas Pelanggan Komersial Industri | D21: PT Perusahaan Gas Negara | E21: Alifa | F21: RO Jakarta | G21: 46022
A22: 20 | B22: kontrak tunggal | C22: Penyediaan Lisensi Piranti Lunak dan Annual Technical Support | D22: PT Perusahaan Gas Negara | E22: Alifa | F22: RO Jakarta | G22: 46357
A23: 21 | C23: PGN Register | D23: PT Perusahaan Gas Negara
A25: No | B25: Kontrak induk | C25: Kontrak Turunan | D25: Client | E25: Tanggal WO | F25: Nilai
A26: 1 | B26: MSAIS 2026 | C26: Jasa enhancement E-SMS | D26: PT Perusahaan Gas negara | E26: 46125 | F26: 140552312
A27: 2 | B27: MSAIS 2026 | C27: Pekerjaan Enhancement 16 KB Page File (Android), Multifactor Authentification (MFA) (Android & IOS) Serta Implementasi Progressive Web App (PWA) | D27: PT Perusahaan Gas negara | E27: 46181 | F27: 687369348
A28: 3 | B28: MSAIS 2026 | C28: Pekerjaan Pengelolaan & Dukungan Aplikasi Kepelangganan PGN Tahun 2026 | D28: PT Perusahaan Gas negara | E28: 46192 | F28: 695673676

Sheet DOKUMEN
A2: Project_ID | B2: Project_client | C2: Project Name | D2: Kontrak | E2: KAK | F2: Cost based | G2: Kertas kerja PSM | H2: TKDN | I2: Amandemen | J2: Keterangan | K2: Link
A3: BS-005 | B3: SAKA | C3: Pengadaan Sewa Aplikasi Absensi Online (Bimasakti) | D3: TRUE | E3: FALSE | F3: FALSE | G3: FALSE | H3: FALSE | I3: FALSE | K3: https://pgascom.sharepoint.com/:f:/s/DMO2-PCRM/IgBASDLQqhD3TLSMMW09hzt5AZ6yD-GxIDBIVVGSnRUi-WA?e=0baeY9
A4: MS-016 | B4: GGS | C4: Pengadaan Sewa Aplikasi Absensi Online (Bimasakti) | D4: TRUE | E4: FALSE | F4: FALSE | G4: FALSE | H4: FALSE | I4: FALSE | K4: https://pgascom.sharepoint.com/:f:/s/DMO2-PCRM/IgCMkAFcp6tbSrzK0fiK3O1FAToaLtKHG0Jp_uSopvBO2mE?e=7SitxB
A5: MS-019 | B5: PLI | C5: Jasa Pemeliharaan Sistem Kontrol dan Telekomunikasi Offtake Station (OTS) & Onshore Receiving Facilities (ORF) 2025-2026 | D5: TRUE | E5: TRUE | F5: FALSE | G5: FALSE | H5: TRUE | I5: FALSE | K5: https://pgascom.sharepoint.com/:f:/s/DMO2-PCRM/IgCywEI3sHKjQ7UX_9UywmDXAaqB1wp8xEfw-IzqdI74Kmc?e=tCe7Ip
A6: MS-020 | B6: NR | C6: Jasa Layanan Radio Komunikasi - Trunking | D6: TRUE | E6: FALSE | F6: FALSE | G6: FALSE | H6: FALSE | I6: TRUE | K6: https://pgascom.sharepoint.com/:f:/s/DMO2-PCRM/IgCn20bxH7GpRZson8QIVMSgAWJSvX86pexvHi8-mqtmd2Q?e=NtQ2av
A7: MS-044 | B7: PTM | C7: Penyediaan Layanan Platform Pilot Aplikasi Modern | D7: TRUE | E7: FALSE | F7: TRUE | G7: FALSE | H7: TRUE | I7: TRUE | K7: https://pgascom.sharepoint.com/:f:/s/DMO2-PCRM/IgCFYHqtUXTHTo8HLHl6nYTAAZwpnqoEvTj3nthjQ-rZZy4?e=KnxBIv
A8: MS-047 | B8: PGN | C8: Layanan Pengelolaan Aplikasi dan Solusi Integrasi Tahun 2025 | D8: TRUE | E8: TRUE | F8: FALSE | G8: FALSE | H8: TRUE | I8: FALSE | K8: https://pgascom.sharepoint.com/:f:/s/DMO2-PCRM/IgCn_ZZavLhuSbixBUVYsWz9AQ6xn-0iLYqeHx1TInNic5I?e=KBHcgb
A9: MS-081 | B9: PPN | C9: Pekerjaan Sewa Router Untuk Layanan Dual Link SPBU | D9: TRUE | E9: FALSE | F9: FALSE | G9: FALSE | H9: FALSE | I9: FALSE | K9: https://pgascom.sharepoint.com/:f:/s/DMO2-PCRM/IgDu9fQmkhFDR4aKpnKmxkpSAf1Mje4D9Iho9C_WrQp-zi4?e=atnQ1H
A10: MS-115 | B10: PPN | C10: Pekerjaan Maintenance CCTV & Infrastruktur PPN MOR1 FT Labuhan Deli | D10: TRUE | E10: FALSE | F10: TRUE | G10: TRUE | H10: FALSE | I10: FALSE | K10: https://pgascom.sharepoint.com/:f:/s/DMO2-PCRM/IgAAx5aYb-UjSrkWQQ1DzdzjAc51jV-QSMO3eRMsA25B57E?e=H8iNeU
A11: MS-117 | B11: SEML | C11: Provision of Document Management System ATS Muara Laboh | D11: TRUE | E11: FALSE | F11: FALSE | G11: FALSE | H11: TRUE | I11: FALSE
A12: MS-118 | B12: SERD | C12: Provision of Document Management System ATS Rantau Dedap | D12: TRUE | E12: FALSE | F12: FALSE | G12: FALSE | H12: TRUE | I12: FALSE
A13: MS-121 | B13: KPI | C13: Jasa Pendampingan Surveillance Sertifikasi ISO/IEC 27001:2022 di PT KPI | D13: TRUE | E13: TRUE | F13: TRUE | G13: TRUE | H13: TRUE | I13: FALSE | K13: https://pgascom.sharepoint.com/:f:/s/DMO2-PCRM/IgBHJcBF_-mWR6SFv7vCup3PAXpgcSgcI99DPIZgXlHE6kc?e=zmhNqe
A14: PS-000-00 | B14: PLI | C14: Pengadaan CCTV PT PGN LNG | D14: TRUE | E14: FALSE | F14: TRUE | G14: FALSE | H14: FALSE | I14: FALSE | K14: https://pgascom.sharepoint.com/:f:/s/DMO2-PCRM/IgAMhve6sr4RRKYNx_iv4nq3Afz7tqY1VwEeZn0qwTTu8qo?e=Z1DjWM
A15: PS-001-00 | B15: PTG | C15: Manage Service Layanan Printer, Scanner, Multimedia dan UPS System di PT Pertamina Gas | D15: TRUE | E15: TRUE | F15: TRUE | G15: FALSE | H15: FALSE | I15: TRUE | K15: https://pgascom.sharepoint.com/:f:/s/DMO2-PCRM/IgATDttzxz9aQZeHsGLAnwDZATEP3xSUAZSSWF2MJwjqvBA?e=0Bmlfo
A16: PS-003-00 | B16: WDR | C16: Pengadaan Sewa Aplikasi Absensi Online (Bimasakti) | D16: TRUE | E16: FALSE | F16: FALSE | G16: FALSE | H16: FALSE | I16: TRUE | K16: https://pgascom.sharepoint.com/:f:/s/DMO2-PCRM/IgCLqcYrWlmdS7dgHsvojo1nAft7SIc1P30G5fT1CS1xW3M?e=X2Asq1
A17: PS-004-00 | B17: PTM | C17: Pengelolaan & Pengembangan Servicedesk Shared Services Pertamina | D17: TRUE | E17: FALSE | F17: FALSE | G17: TRUE | H17: FALSE | I17: FALSE | K17: https://pgascom.sharepoint.com/:f:/s/DMO2-PCRM/IgBf4Pizf2GxSJfWj2kn-4JFASKNk8GNy4PLJdBaZGTRHs8?e=n23lr9
A18: PS-005-00 | B18: KJG | C18: Pengadaan Jasa penyediaan Perangkat Sistem Informasi | D18: TRUE | E18: TRUE | F18: TRUE | G18: FALSE | H18: FALSE | I18: TRUE | K18: https://pgascom.sharepoint.com/:f:/s/DMO2-PCRM/IgD0bK_uZP_TTJ5gAu1Xg4_WAQagLxaEkx9PGrJOoIOPeIE?e=AbzD1v
A19: PS-006-00 | B19: PSOL | C19: Implementasi Vulnerability Assessment & Penetration Test (VAPT) dan Technical Service Cyber Security | D19: TRUE | E19: TRUE | F19: TRUE | G19: FALSE | H19: FALSE | I19: FALSE | K19: https://pgascom.sharepoint.com/:f:/s/DMO2-PCRM/IgAyh4QjuxWsS5tJAeTBfdo3AQXqzRwCMUSe0xbCQ1ar7OE?e=8SBfTl
A20: PS-007-00 | B20: PGN | C20: Pekerjaan Penyediaan Layanan Sewa Server YKPP PGN | D20: TRUE | E20: FALSE | F20: FALSE | G20: FALSE | H20: FALSE | I20: FALSE | K20: https://pgascom.sharepoint.com/:f:/s/DMO2-PCRM/IgCMYLbsZNeVT6dRcsK4TKRmAZc-Dh3TsHc9RaCU0QRIP-w?e=BMzu0c
A21: PS-008-00 | B21: PGN | C21: Jasa Teknikal Asistensi Sistem Manajemen Informasi Legal (SMILE) 2024 | D21: TRUE | E21: FALSE | F21: FALSE | G21: FALSE | H21: FALSE | I21: TRUE | K21: https://pgascom.sharepoint.com/:f:/s/DMO2-PCRM/IgDMBBn0H-3wQbNZJJgN7t2qAcQC85UMrQQEabX5-LENHlI?e=orzmib
A22: PS-009-00 | B22: NR | C22: Jasa Implementasi Security Information Event Management (SIEM) dan Security Operation Center (SOC) | D22: TRUE | E22: TRUE | F22: TRUE | G22: FALSE | H22: FALSE | I22: FALSE | K22: https://pgascom.sharepoint.com/:f:/s/DMO2-PCRM/IgC_AZMGMaAmRI7jwYWmK3w-AX2BsfXSa6ZO324MXWJSnJk?e=erhcY6
A23: PS-010-00 | B23: PTM | C23: Penyediaan Jasa Dukungan Operasional Fungsi Shared Services ICT Tahun 2025-2026 | D23: TRUE | E23: FALSE | F23: TRUE | G23: FALSE | H23: FALSE | I23: FALSE | K23: https://pgascom.sharepoint.com/:f:/s/DMO2-PCRM/IgBaofmynKRRTKCWwr7jh_SyAXmKyaVz9E07YGtlpNLY0oE?e=pXRO9l
A24: PS-011-00 | B24: PGN | C24: Penyediaan Lisensi Piranti Lunak dan Annual Technical Support | D24: FALSE | E24: FALSE | F24: FALSE | G24: FALSE | H24: FALSE | I24: FALSE
A25: PS-012-00 | B25: PTM | C25: Pengadaan Jasa Penyediaan Endpoint Security 2026-2027 | D25: TRUE | E25: FALSE | F25: TRUE | G25: FALSE | H25: TRUE | I25: FALSE | K25: https://pgascom.sharepoint.com/:f:/s/DMO2-PCRM/IgDRM-4yXdlPTpqB1FVE65J0AVRTEzEzX9HhakiexEtxEFc?e=T4PzVy
A26: PS-013-00 | B26: PTM | C26: Pengadaan Sewa Perangkat Storage san NTP Server Pertamina | D26: TRUE | E26: TRUE | F26: TRUE | G26: FALSE | H26: TRUE | I26: TRUE | K26: https://pgascom.sharepoint.com/:f:/s/DMO2-PCRM/IgCBB8gzprowQ6SOv9SA-qzBAarzaSFyTBjkYXgZeSTMvv0?e=VhHdGP
A27: PS-014-00 | B27: PTM | C27: Penyediaan Jasa Layanan Offline Backup AWS Phase 1 | D27: TRUE | E27: FALSE | F27: FALSE | G27: FALSE | H27: TRUE | I27: FALSE | K27: https://pgascom.sharepoint.com/:f:/s/DMO2-PCRM/IgAwpxfCI-h0Raklv4LGDvQnATQcd0KLQcdKkOsEOW4B5ZY?e=LctLWX
A28: PS-015-00 | B28: PTM | C28: Tindak Lanjut Pekerjaan Jasa Managed Service Security Assessment (MSSA) | D28: TRUE | E28: TRUE | F28: TRUE | G28: FALSE | H28: TRUE | I28: FALSE | K28: https://pgascom.sharepoint.com/:f:/s/DMO2-PCRM/IgCZNoNtBVFxRLEaLnoH06RtAWk2WWZFuu3McPGzv5a2N08?e=mvvhhI
A29: PS-016-00 | B29: PGN | C29: Jasa Managed Service Pengelolaan Layanan Pelanggan Melalui Contact Center 2025-2027 | D29: TRUE | E29: TRUE | F29: TRUE | G29: TRUE | H29: TRUE | I29: FALSE | K29: https://pgascom.sharepoint.com/:f:/s/DMO2-PCRM/IgBlYpRzviokR5NEJLwcitJiAcM3n63l-8eJr6w6pcvfGJ8?e=E6gXhq
A30: PS-017-00 | B30: PGN | C30: Jasa Penyediaan Perangkat Multimedia dan Peralatan Pendukung Ruang Integrated Monitoring Center (IMOC) | D30: TRUE | E30: FALSE | F30: TRUE | G30: FALSE | H30: FALSE | I30: FALSE | K30: https://pgascom.sharepoint.com/:f:/s/DMO2-PCRM/IgAIXPUMtHU6QYLG8SqFF2hqAWjcRBN25TZWAYQm7eex9jI?e=CpgalX
A31: PS-018-00 | B31: PGN | C31: Managed Service Aplication Integration Solutions (MSAIS) Tahun 2026 | D31: TRUE | E31: TRUE | F31: TRUE | G31: TRUE | H31: TRUE | I31: FALSE | K31: https://pgascom.sharepoint.com/:f:/s/DMO2-PCRM/IgAg-LwPCp9uT5JuKsrMvg0sAeR75PhJGWTM5Ie2WDdFYWI?e=tOO9aA
A32: PS-019-00 | B32: PGN | C32: Managed Service Backup Management (Vinchin) | D32: TRUE | E32: TRUE | F32: FALSE | G32: TRUE | H32: TRUE | I32: FALSE | K32: https://pgascom.sharepoint.com/:f:/s/DMO2-PCRM/IgCWt-04uHYWSZX44lNsSCfMATbuBCw45Q3e4LH5vABrchA?e=iXS2M2
A33: PS-020-00 | B33: PGN | C33: Managed Service Cyber Security (MSCS) Tahun 2026 | D33: TRUE | E33: TRUE | F33: TRUE | G33: FALSE | H33: TRUE | I33: FALSE | K33: https://pgascom.sharepoint.com/:f:/s/DMO2-PCRM/IgA2DrHZ4QH2Qpkn3DfEN37mAcVXRaAYWi1eLZwKQadKIgg?e=GO7Qht
A34: PS-021-00 | B34: PGN | C34: Managed Service OT Security (MSOT) Tahun 2026 - 2028 | D34: TRUE | E34: TRUE | F34: TRUE | G34: TRUE | H34: TRUE | I34: FALSE | K34: https://pgascom.sharepoint.com/:f:/s/DMO2-PCRM/IgDBZzzozJyATIV0zPFXNh9wAV6qyjKnXEBkqkFw9_3lG_k?e=dWLn5O
A35: PS-022-00 | B35: PGN | C35: Managed Service Sewa Infrastruktur Data Center (Aletra) | D35: TRUE | E35: TRUE | F35: TRUE | G35: FALSE | H35: FALSE | I35: FALSE | K35: https://pgascom.sharepoint.com/:f:/s/DMO2-PCRM/IgCTK0e_rgt1RL2fIkGiu1l2AXpDEiyNm9VOcnriTKyYn6M?e=OyXaHQ
A36: PS-023-00 | B36: PGN | C36: Managed Service Teknologi Informasi (MSTI) 2025 | D36: TRUE | E36: TRUE | F36: FALSE | G36: FALSE | H36: FALSE | I36: FALSE | K36: https://pgascom.sharepoint.com/:f:/s/DMO2-PCRM/IgBgihMLdWI5ToCPTTCFywLAAcMI9VkAhI20woHPnHEXeHk?e=BXz8wB
... A44: PS-030-00 | B44: PGN | C44: Sewa Perangkat Infrastruktur Teknologi Informasi (Sangfor) | D44: TRUE | E44: TRUE | F44: TRUE | G44: FALSE | H44: FALSE | I44: TRUE | K44: https://pgascom.sharepoint.com/:f:/s/DMO2-PCRM/IgB9WQGFSm8PQ7zJz4lU80CNAYy-YpYvdqb5JBdjAgGVlhw?e=uDtFCJ
A45: PS-031-00 | B45: PGN | C45: Penyediaan Personil Tenaga Alih Daya (TAD) di PT Perusahaan Gas Negara (PGN) HSSE Untuk Rencana Pekerjaan PGN Digital HSSE Campaign Tahun 2026 | D45: FALSE | E45: FALSE | F45: FALSE | G45: FALSE | H45: FALSE | I45: FALSE
A46: PS-032-00 | B46: PGN | C46: Penyediaan Aplikasi Point of Sales untuk Pemberdayaan Aset | D46: TRUE | E46: TRUE | F46: TRUE | G46: FALSE | H46: TRUE | I46: FALSE | K46: https://pgascom.sharepoint.com/:f:/s/DMO2-PCRM/IgAruXOx_eIDRqpPLfXCDInEAYG7a-YSFaWzVZDIlflQ8nU?e=40V6kH
A47: PS-033-00 | B47: PGN | C47: Managed Service Cyber Security Awareness 2026 | D47: FALSE | E47: TRUE | F47: TRUE | G47: FALSE | H47: TRUE | I47: FALSE | K47: https://pgascom.sharepoint.com/:f:/s/DMO2-PCRM/IgAb5S6-_gmyRrqQ0lEcwlozAS5AH2yHsLjFXARzDzSArpY?e=FNNVfh
A48: PS-034-00 | B48: PLI | C48: Jasa Pemeliharaan Sistem Kontrol dan Telekomunikasi Offtake Station (OTS) & Onshore Receiving Facilities (ORF) 2026-2027 | D48: FALSE | E48: FALSE | F48: TRUE | G48: TRUE | H48: FALSE | I48: FALSE | K48: https://pgascom.sharepoint.com/:f:/s/DMO2-PCRM/IgAQQ4Gu1ds-QLAqfliMziBlAeq6s8-FcvWplmxPSpD14vQ?e=ZVQ9fu
A49: PS-035-00 | B49: PTG | C49: Layanan Sewa Perangkat Server dan Network Teknologi Informasi dan Layanan Sewa Perangkat Infrastruktur Teknologi Informasi SPO Nusantara | D49: TRUE | E49: TRUE | F49: TRUE | G49: TRUE | H49: FALSE | I49: FALSE | K49: https://pgascom.sharepoint.com/:f:/s/DMO2-PCRM/IgDznFUBaJq7SpST_IBIQk3NAdO0DHt6fYJKN5zNmIwNLjo?e=Nha86s
A50: PS-036-00 | B50: PTG | C50: Manage Service Layanan Perangkat Command Crisis Center PT Pertamina Gas | D50: TRUE | E50: TRUE | F50: TRUE | G50: FALSE | H50: TRUE | I50: FALSE | K50: https://pgascom.sharepoint.com/:f:/s/DMO2-PCRM/IgBmJcwGP1sVRJl0oZzKqKxUAZg3L7uE-_cR0PQ2ANYtDS8?e=aBbFty
A51: PS-037-00 | B51: PLI | C51: Managed Service Access Point dan Switch | D51: TRUE | E51: FALSE | F51: TRUE | G51: FALSE | H51: FALSE | I51: FALSE | K51: https://pgascom.sharepoint.com/:f:/s/DMO2-PCRM/IgCeJf-gNf7DTKNLUYuQN8SmAec_Gw9WiMqY3-NyKZNY7tc?e=RVwpSW
A52: PS-038-00 | B52: PLI | C52: Managed Service SD-WAN | D52: TRUE | E52: FALSE | F52: FALSE | G52: FALSE | H52: FALSE | I52: FALSE | K52: https://pgascom.sharepoint.com/:f:/s/DMO2-PCRM/IgCGxGeybmbqS4Jq9wb_mj7ZAd9Vcrkj1gShQ28v_tyfuxU?e=X3CKDb
A53: PS-039-00 | B53: PTG | C53: Managed Service Sewa layanan IP Phone System | D53: TRUE | E53: TRUE | F53: TRUE | G53: FALSE | H53: TRUE | I53: FALSE | K53: https://pgascom.sharepoint.com/:f:/s/DMO2-PCRM/IgCrHP80zRtHTJ8QZ5rWSQXsAeBZhEZy58NbdOT1w4CK8hA?e=S7W765
A54: PS-040-00 | B54: PLI | C54: Pekerjaan Layanan Cloud (dan VAPT) | D54: TRUE | E54: TRUE | F54: TRUE | G54: FALSE | H54: FALSE | I54: FALSE | K54: https://pgascom.sharepoint.com/:f:/s/DMO2-PCRM/IgB1jyikSbdRTL88Qk9sfM2FAQP5R_XVC45vmOec-hDJ3hU?e=dt1iuy
A55: PS-042-00 | B55: SAKA | C55: Pengadaan Sewa Aplikasi Absensi Online (Bimasakti) | D55: TRUE | E55: FALSE | F55: FALSE | G55: FALSE | H55: FALSE | I55: FALSE | K55: https://pgascom.sharepoint.com/:f:/s/DMO2-PCRM/IgBoL7rS7L_eSKnHW-xG1apvATBUkDVIk1ey2j_nCqTWNjA?e=UAjhYR
A56: PS-043-00 | B56: PTG | C56: Pengelolaan Integrasi Data dan Pemeliharaan Sistem Data Acquisition Transportasi Minyak & Gas Bumi | D56: TRUE | E56: FALSE | F56: TRUE | G56: FALSE | H56: FALSE | I56: FALSE | K56: https://pgascom.sharepoint.com/:f:/s/DMO2-PCRM/IgA5T26GlR6DRbPxnYV50Zj6AfhNoPj5SXPufRQ5iPJx5Xs?e=ccYSOh
A57: PS-044-00 | B57: PPN | C57: Pengadaan Implementasi Security Operation Center (SOC) di Kantor Pusat Wisma Tugu II | D57: TRUE | E57: FALSE | F57: TRUE | G57: FALSE | H57: TRUE | I57: FALSE | K57: https://pgascom.sharepoint.com/:f:/s/DMO2-PCRM/IgBqNnnA2XdUQJdf4Y6xMLFzAbDKUxBG8M0g8PkPcLWt9FU?e=cgu6HV
... A66: PS-053-00 | B66: YKP | C66: Penetration Testing All Care System | D66: FALSE | E66: TRUE | F66: TRUE | G66: TRUE | H66: FALSE | I66: FALSE | K66: https://pgascom.sharepoint.com/:f:/s/DMO2-PCRM/IgAhzvFm2hYQQpspNlMePuRRAaVdXDG5TQrE9nYAShNlxog?e=VWirPf
A67: PS-055-00 | B67: PPN | C67: Jasa Keamanan Operasi Cyber Security PT Kilang Pertamina Internasional | D67: FALSE | E67: TRUE | F67: TRUE | G67: TRUE | H67: TRUE | I67: FALSE | J67: SP3MK | K67: https://pgascom.sharepoint.com/:f:/s/DMO2-PCRM/IgBCrOlR3_CBR6OpdjRi_mQfAcKi841zHBZzqEDDgd4v4AY?e=zcp6wj
A68: PS-056-00 | B68: PPN | C68: Pengadaan Jasa Pengembangan & Pemeliharaan Aplikasi Pendukung IT Project Pertamina Patra Niaga | D68: FALSE | E68: FALSE | F68: TRUE | G68: FALSE | H68: TRUE | I68: FALSE | J68: SP3MK | K68: 2026 - Pekerjaan Pengadaan Jasa Pengembangan dan Pemeliharaan Aplikasi Pendukung IT Project Pertamina Patra Niaga
A69: PS-057-00 | B69: KPI | C69: Pengadaan Jasa Implementasi Data Governance Di PT Kilang Pertamina Internasional | D69: TRUE | E69: TRUE | F69: TRUE | G69: TRUE | H69: TRUE | I69: FALSE | K69: https://pgascom.sharepoint.com/:f:/s/DMO2-PCRM/IgCGwtepp6gyTrqXb48W7QfHAbrw4fk9hq01yBqa6-ANlrI?e=4ZgJw2
A70: PS-058-00 | B70: PGN | C70: Penyediaan Perangkat Network System Refreshment | D70: TRUE | E70: TRUE | F70: TRUE | G70: TRUE | H70: FALSE | I70: FALSE | K70: https://pgascom.sharepoint.com/:f:/s/DMO2-PCRM/IgCytRyrgIivTK13KvPH2JhQAaHwDisr1S5Xs0lw8ugdwCc?e=EHmJWM
A71: PS-059-00 | B71: PTM | C71: Penyediaan Jasa Klasifikasi Keamanan Informasi | D71: TRUE | E71: FALSE | F71: TRUE | G71: FALSE | H71: FALSE | I71: FALSE | K71: https://pgascom.sharepoint.com/:f:/s/DMO2-PCRM/IgA1mwXUlWGPSJ5YqwEY-pjrAV5-sXHJU0m3wu-3RlHy4Jc?e=eDBWcj
A72: PS-060-00 | B72: PGN | C72: Enhancement Aplikasi System Integrasi Datamart & Tools Monitoring Dashboard Management Kinerja Niaga | D72: FALSE | E72: FALSE | F72: FALSE | G72: FALSE | H72: FALSE | I72: FALSE | K72: 2026 - Enhancement Aplikasi System Integrasi Datamart & Tools Monitoring Dashboard Management Kinerja Niaga
A73: PS-061-00 | B73: PGN | C73: Pengadaan Monitor PGN GCG & Compliance | D73: TRUE | E73: FALSE | F73: TRUE | G73: FALSE | H73: FALSE | I73: FALSE | K73: 2026 - Pengadaan Monitor GCG dan Compliance
A74: PS-062-00 | B74: PTG | C74: Security Awareness-Cyber Security BSSN forum untuk AP/JV | D74: FALSE | E74: FALSE | F74: TRUE | G74: FALSE | H74: FALSE | I74: FALSE | K74: 2026 - Security Awareness-Cyber Security BSSN Forum untuk AP-JV
D75: FALSE | E75: FALSE | F75: FALSE | G75: FALSE | H75: FALSE | I75: FALSE
D76: FALSE | E76: FALSE | F76: FALSE | G76: FALSE | H76: FALSE | I76: FALSE
D77: FALSE | E77: FALSE | F77: FALSE | G77: FALSE | H77: FALSE | I77: FALSE

Sheet PIC
A2: Project_ID | B2: Project_client | C2: Project Name | D2: Account Manager | E2: Pre-Sales | F2: Project Manager | G2: Service Manager
A3: BS-005 | B3: SAKA | C3: Pengadaan Sewa Aplikasi Absensi Online (Bimasakti)
A4: MS-016 | B4: GGS | C4: Pengadaan Sewa Aplikasi Absensi Online (Bimasakti)
A5: MS-019 | B5: PLI | C5: Jasa Pemeliharaan Sistem Kontrol dan Telekomunikasi Offtake Station (OTS) & Onshore Receiving Facilities (ORF)
A6: MS-020 | B6: NR | C6: Jasa Layanan Radio Komunikasi - Trunking
A7: MS-044 | B7: PTM | C7: Penyediaan Layanan Platform Pilot Aplikasi Modern
A8: MS-081 | B8: PPN | C8: Pekerjaan Sewa Router Untuk Layanan Dual Link SPBU
A9: PS-000-00 | B9: PLI | C9: Pengadaan CCTV PT PGN LNG
A10: PS-001-00 | B10: PTG | C10: Manage Service Layanan Printer, Scanner, Multimedia dan UPS System di PT Pertamina Gas
A11: PS-003-00 | B11: WDR | C11: Pengadaan Sewa Aplikasi Absensi Online (Bimasakti)
A12: PS-004-00 | B12: PTM | C12: Pengelolaan & Pengembangan Servicedesk Shared Services Pertamina
A13: PS-005-00 | B13: KJG | C13: Pengadaan Jasa penyediaan Perangkat Sistem Informasi
A14: PS-006-00 | B14: PSOL | C14: Implementasi Vulnerability Assessment & Penetration Test (VAPT) dan Technical Service Cyber Security
... A61: PS-055-00 | B61: PPN | C61: Jasa Keamanan Operasi Cyber Security PT Kilang Pertamina Internasional
A62: MS-115
A63: MS-116
A64: MS-117
A65: MS-118
A66: MS-119
A67: MS-120

Sheet TKDN
C1: =SUBTOTAL(3,C3:C50) -> 46 | F1: 2026 | R1: 2027 | AD1: 2028 | AP1: 2029
A2: ID | B2: Client | C2: Project Name | D2: TKDN | E2: Description | F2: Jan-26 | G2: Feb-26 | H2: Mar-26 | I2: Apr-26 | J2: Mei-26 | K2: Jun-26 | L2: Jul-26 | M2: Agu-26 | N2: Sep-26 | O2: Okt-26 | P2: Nov-26 | Q2: Des-26 | R2: Jan-27 | S2: Feb-27 | T2: Mar-27 | U2: Apr-27 | V2: Mei-27 | W2: Jun-27 | X2: Jul-27 | Y2: Agu-27 | Z2: Sep-27 | AA2: Okt-27 | AB2: Nov-27 | AC2: Des-27 | AD2: Jan-28 | AE2: Feb-28 | AF2: Mar-28 | AG2: Apr-28 | AH2: Mei-28 | AI2: Jun-28 | AJ2: Jul-28 | AK2: Agu-28 | AL2: Sep-28 | AM2: Okt-28 | AN2: Nov-28 | AO2: Des-28 | AP2: Jan-29 | AQ2: Feb-29 | AR2: Mar-29 | AS2: Apr-29 | AT2: Mei-29 | AU2: Jun-29 | AV2: Jul-29 | AW2: Agu-29 | AX2: Sep-29 | AY2: Okt-29 | AZ2: Nov-29 | BA2: Des-29
A3: MS-019 | B3: PLI | C3: Jasa Pemeliharaan Sistem Kontrol dan Telekomunikasi Offtake Station (OTS) & Onshore Receiving Facilities (ORF) | D3: 0.79 | G3: VERIFIKASI
A4: PS-004-00 | B4: PTM | C4: Pengelolaan & Pengembangan Servicedesk Shared Services Pertamina | D4: 89,60% | E4: dokumen komitmen
A5: PS-005-00 | B5: KJG | C5: Pengadaan Jasa penyediaan Perangkat Sistem Informasi | D5: 0.4 | E5: dokumen komitmen
A6: PS-006-00 | B6: PSOL | C6: Implementasi Vulnerability Assessment & Penetration Test (VAPT) dan Technical Service Cyber Security | D6: 0.8923 | M6: VERIFIKASI
A7: PS-008-00 | B7: PGN | C7: Jasa Teknikal Asistensi Sistem Manajemen Informasi Legal (SMILE) | D7: 0.9547 | E7: dokumen komitmen
A8: PS-009-00 | B8: NR | C8: Jasa Implementasi Security Information Event Management (SIEM) dan Security Operation Center (SOC) | D8: 0.7386 | E8: dokumen komitmen
A9: PS-011-00 | B9: PGN | C9: Penyediaan Lisensi Piranti Lunak dan Annual Technical Support | D9: 33,77%
A10: PS-012-00 | B10: PTM | C10: Pengadaan Jasa Penyediaan Endpoint Security 2026-2027 | D10: 0.0111 | T10: VERIFIKASI
A11: PS-013-00 | B11: PTM | C11: Pengadaan Sewa Perangkat Storage san NTP Server Pertamina | D11: 0.7119 | L11: MONITORING | Q11: MONITORING | X11: MONITORING | AC11: MONITORING | AJ11: VERIFIKASI
A12: PS-014-00 | B12: PTM | C12: Penyediaan Jasa Layanan Offline Backup AWS Phase 1 | D12: 0.3478 | H12: MONITORING | N12: VERIFIKASI
A13: PS-015-00 | B13: PTM | C13: Tindak Lanjut Pekerjaan Jasa Managed Service Security Assessment (MSSA) | D13: 0.3546 | I13: MONITORING | O13: VERIFIKASI
A14: PS-016-00 | B14: PGN | C14: Jasa Managed Service Pengelolaan Layanan Pelanggan Melalui Contact Center 2025-2027 | D14: 89,20% | N14: MONITORING | Z14: VERIFIKASI
A15: PS-017-00 | B15: PGN | C15: Jasa Penyediaan Perangkat Multimedia dan Peralatan Pendukung Ruang Integrated Monitoring Center (IMOC) | D15: 0.8513 | E15: dokumen komitmen | AK15: VERIFIKASI
A16: PS-018-00 | B16: PGN | C16: Managed Service Aplication Integration Solutions (MSAIS) Tahun 2026 | D16: 84,45% | Q16: VERIFIKASI
A17: PS-019-00 | B17: PGN | C17: Managed Service Backup Management (Vinchin) | D17: 0.5031 | K17: MONITORING | Q17: MONITORING | W17: MONITORING | AC17: VERIFIKASI
A18: PS-020-00 | B18: PGN | C18: Managed Service Cyber Security (MSCS) Tahun 2026 | D18: 0.6632 | F18: MONITORING | G18: MONITORING | H18: MONITORING | I18: MONITORING | J18: MONITORING | K18: MONITORING | L18: MONITORING | M18: MONITORING | N18: MONITORING | O18: MONITORING | P18: MONITORING | Q18: VERIFIKASI
A19: PS-021-00 | B19: PGN | C19: Managed Service OT Security (MSOT) Tahun 2026 - 2028 | D19: 30,44% | K19: MONITORING | Q19: MONITORING | W19: MONITORING | AC19: MONITORING | AI19: MONITORING | AO19: VERIFIKASI
A20: PS-022-00 | B20: PGN | C20: Managed Service Sewa Infrastruktur Data Center (Aletra) | D20: 0.66 | E20: dokumen komitmen | AC20: VERIFIKASI
A21: PS-023-00 | B21: PGN | C21: Managed Service Teknologi Informasi (MSTI) 2026 | D21: 0.643 | Q21: VERIFIKASI
A22: PS-024-00 | B22: PGN | C22: Pekerjaan Jasa Operasi dan Pemeliharaan Terintegrasi Gas Management System (PJOPTGMS) | D22: 0.5918 | G22: MONITORING | S22: MONITORING | AE22: VERIFIKASI
A23: PS-025-00 | B23: PGN | C23: Pekerjaan Jasa Sewa Penyediaan Collocation Master Data Center dan Backup data Center | D23: 0.7741 | E23: dokumen komitmen | Q23: VERIFIKASI
A24: PS-026-00 | B24: PGN | C24: Pengadaan Jasa Managed Service E-KYC | D24: 58,56% | F24: MONITORING | I24: MONITORING | L24: MONITORING | O24: MONITORING | Q24: VERIFIKASI
A25: PS-027-00 | B25: PGN | C25: Penyediaan Jasa Layanan Notifikasi SMS Penagihan Piutang Pelanggan Tahun 2026 | D25: 0.9635 | J25: MONITORING | M25: MONITORING | Q25: VERIFIKASI
A26: PS-028-00 | B26: PGN | C26: Penyediaan Layanan Sistem Radio Komunikasi 2025-2027 | D26: 75,57% | E26: dokumen komitmen | AC26: VERIFIKASI
A27: PS-029-00 | B27: PGN | C27: Penyediaan Lisensi Piranti Lunak Periode IV (Google Maps) | D27: 0.0757 | L27: MONITORING | Q27: MONITORING | X27: MONITORING | AC27: MONITORING | AJ27: MONITORING | AO27: VERIFIKASI
A28: PS-030-00 | B28: PGN | C28: Sewa Perangkat Infrastruktur Teknologi Informasi (Sangfor) | D28: 0.4692 | E28: dokumen komitmen | AP28: VERIFIKASI
A29: PS-031-00 | B29: PGN | C29: Penyediaan Personil Tenaga Alih Daya (TAD) di PT Perusahaan Gas Negara (PGN) HSSE Untuk Rencana Pekerjaan PGN Digital HSSE Campaign Tahun 2026 | D29: TBC | E29: dokumen komitmen
A30: PS-032-00 | B30: PGN | C30: Penyediaan Aplikasi Point of Sales untuk Pemberdayaan Aset | D30: 0.8661 | K30: MONITORING | N30: MONITORING | Q30: VERIFIKASI
A31: PS-033-00 | B31: PGN | C31: Managed Service Cyber Security Awareness | D31: 0.5702 | F31: MONITORING | G31: MONITORING | H31: MONITORING | I31: MONITORING | J31: MONITORING | K31: MONITORING | L31: MONITORING | M31: MONITORING | N31: MONITORING | O31: MONITORING | P31: MONITORING | Q31: VERIFIKASI
A32: PS-034-00 | B32: PLI | C32: Jasa Pemeliharaan Sistem Kontrol dan Telekomunikasi Offtake Station (OTS) & Onshore Receiving Facilities (ORF) | D32: 0.79 | E32: dokumen komitmen | J32: MONITORING | M32: MONITORING | P32: MONITORING | S32: VERIFIKASI
A33: PS-035-00 | B33: PTG | C33: Layanan Sewa Perangkat Server dan Network Teknologi Informasi dan Layanan Sewa Perangkat Infrastruktur Teknologi Informasi SPO Nusantara | D33: TBC | E33: dokumen komitmen
A34: PS-036-00 | B34: PTG | C34: Manage Service Layanan Perangkat Command Crisis Center PT Pertamina Gas | D34: 0.71 | E34: dokumen komitmen
A35: PS-039-00 | B35: PTG | C35: Managed Service Sewa layanan IP Phone System | D35: 0.5646 | E35: dokumen komitmen
A36: PS-040-00 | B36: PLI | C36: Pekerjaan Layanan Cloud (dan VAPT) | D36: 0.75 | E36: dokumen komitmen | AC36: VERIFIKASI
A37: PS-043-00 | B37: PTG | C37: Pengelolaan Integrasi Data dan Pemeliharaan Sistem Data Acquisition Transportasi Minyak & Gas Bumi | D37: 0.9702 | E37: dokumen komitmen | V37: VERIFIKASI
A38: PS-044-00 | B38: PPN | C38: Pengadaan Implementasi Security Operation Center (SOC) di Kantor Pusat Wisma Tugu II | D38: 0.3577 | J38: MONITORING | P38: MONITORING | V38: MONITORING | AB38: MONITORING | AH38: MONITORING | AN38: VERIFIKASI
A39: PS-045-00 | B39: PIS | C39: Penyediaan Perangkat Multimedia Ballroom dan Mini Galery | D39: 0.7519 | E39: dokumen komitmen | AY39: VERIFIKASI
A40: PS-046-00 | B40: PET | C40: Sewa Perangkat Radio Komunikasi di TLPG Tanjung Sekong, IT Tanjung Uban, FT Pulau Sambu, FT Kotabaru dan FT Baubau | D40: 0.7674 | E40: dokumen komitmen | AM40: VERIFIKASI
A41: PS-047-00 | B41: PHE | C41: Layanan Telekomunikasi Site | D41: 0.936 | E41: dokumen komitmen | R41: VERIFIKASI
A42: PS-048-00 | B42: PIS | C42: Pekerjaan Jasa Pengelolaan Modul Smartship dan Pemeliharaan Sensor Kapal | D42: 0.592 | K42: MONITORING | Q42: MONITORING | W42: MONITORING | AC42: VERIFIKASI
A43: PS-050-00 | B43: PAS | C43: Pengadaan SOC (Security Operation Center), PAM (Priviledge Access Management) dan Layanan Managed Service Security | D43: TBC | E43: dokumen komitmen
A44: PS-051-00 | B44: PTPN | C44: Penyediaan Layanan Managed Services Security Operation Center (SOC) PTPN HOLING | D44: 0.3577 | E44: dokumen komitmen
A45: PS-055-00 | B45: PPN | C45: Jasa Keamanan Operasi Cyber Security | D45: 0.9001 | E45: TBC
A46: PS-056-00 | B46: PPN | C46: Pengadaan Jasa Pengembangan & Pemeliharaan Aplikasi Pendukung IT Project Pertamina Patra Niaga | D46: 0.5506
A47: PS-058-00 | B47: PGN | C47: Penyediaan Perangkat Network System Refreshment | D47: 0.4746
A48: PS-073-00 | B48: PTM | C48: Penyediaan ATS & Lisensi SIEM | D48: 0.0001

Sheet REALISASI 2026
B2: PROJECT NAME | C2: All Project
B3: CUSTOMER | C3: ALL CUSTOMER
B4: PERIODE | C4: 2026
B6: NO | C6: KODE PROJECT | D6: NAMA PROJECT | E6: ITEM BIAYA | F6: SATUAN KERJA | G6: PIC | H6: PERIODE | I6: REALISASI BIAYA | J6: STATUS | K6: VENDOR | L6: SIFAT | M6: LINK EVIDENCE | N6: Tahun | O6: Kolom1
K7: 0 | M7: https://pgascom.sharepoint.com/:f:/s/DMO2-PCRM/IgAtXwuElMa_S4ltRuIZ2mJTAeEOdK2ZKM055kdpTEpNhk8?e=KE5ciu | N7: 2026
C8: PS-024-00 | D8: {=_xlfn.XLOOKUP(Tabel2[[#This Row],[KODE PROJECT]], _xlfn.VSTACK('KODE PROJECT BARU'!$B$5:$B$98, 'KODE PROJECT BARU'!$C$5:$C$98), _xlfn.VSTACK('KODE PROJECT BARU'!$E$5:$E$98, 'KODE PROJECT BARU'!$E$5:$E$98), "Tidak Ditemukan", 0, 1)} -> #NAME? | E8: UPAH | F8: DMO | G8: Ulfa | H8: JANUARI | I8: =851433857+12333257 -> 863767114 | J8: PAID | K8: PERSADA | L8: MONTHLY | N8: 2026
C9: PS-024-00 | D9: {=_xlfn.XLOOKUP(Tabel2[[#This Row],[KODE PROJECT]], _xlfn.VSTACK('KODE PROJECT BARU'!$B$5:$B$98, 'KODE PROJECT BARU'!$C$5:$C$98), _xlfn.VSTACK('KODE PROJECT BARU'!$E$5:$E$98, 'KODE PROJECT BARU'!$E$5:$E$98), "Tidak Ditemukan", 0, 1)} -> #NAME? | E9: UPAH | F9: DMO | G9: Ulfa | H9: FEBRUARI | I9: =862153641+11055476 -> 873209117 | J9: PAID | K9: PERSADA | L9: MONTHLY | N9: 2026
C10: PS-024-00 | D10: {=_xlfn.XLOOKUP(Tabel2[[#This Row],[KODE PROJECT]], _xlfn.VSTACK('KODE PROJECT BARU'!$B$5:$B$98, 'KODE PROJECT BARU'!$C$5:$C$98), _xlfn.VSTACK('KODE PROJECT BARU'!$E$5:$E$98, 'KODE PROJECT BARU'!$E$5:$E$98), "Tidak Ditemukan", 0, 1)} -> #NAME? | E10: UPAH | F10: DMO | G10: Ulfa | H10: MARET | I10: =869057456-10926705 -> 858130751 | J10: PAID | K10: PERSADA | L10: MONTHLY | N10: 2026
C11: PS-024-00 | D11: {=_xlfn.XLOOKUP(Tabel2[[#This Row],[KODE PROJECT]], _xlfn.VSTACK('KODE PROJECT BARU'!$B$5:$B$98, 'KODE PROJECT BARU'!$C$5:$C$98), _xlfn.VSTACK('KODE PROJECT BARU'!$E$5:$E$98, 'KODE PROJECT BARU'!$E$5:$E$98), "Tidak Ditemukan", 0, 1)} -> #NAME? | E11: TALI KASIH | F11: DMO | G11: Ulfa | H11: MARET | I11: 115194767 | J11: PAID | K11: PERSADA | L11: OTC | N11: 2026
C12: PS-024-00 | D12: {=_xlfn.XLOOKUP(Tabel2[[#This Row],[KODE PROJECT]], _xlfn.VSTACK('KODE PROJECT BARU'!$B$5:$B$98, 'KODE PROJECT BARU'!$C$5:$C$98), _xlfn.VSTACK('KODE PROJECT BARU'!$E$5:$E$98, 'KODE PROJECT BARU'!$E$5:$E$98), "Tidak Ditemukan", 0, 1)} -> #NAME? | E12: THRK | F12: DMO | G12: Ulfa | H12: MARET | I12: 592126292 | J12: PAID | K12: PERSADA | L12: OTC | N12: 2026
C13: PS-024-00 | D13: {=_xlfn.XLOOKUP(Tabel2[[#This Row],[KODE PROJECT]], _xlfn.VSTACK('KODE PROJECT BARU'!$B$5:$B$98, 'KODE PROJECT BARU'!$C$5:$C$98), _xlfn.VSTACK('KODE PROJECT BARU'!$E$5:$E$98, 'KODE PROJECT BARU'!$E$5:$E$98), "Tidak Ditemukan", 0, 1)} -> #NAME? | E13: SPPD | F13: DMO | G13: Ulfa | H13: JANUARI | I13: 46479352 | J13: PAID | K13: PERSADA | L13: OTC | N13: 2026
C14: PS-024-00 | D14: {=_xlfn.XLOOKUP(Tabel2[[#This Row],[KODE PROJECT]], _xlfn.VSTACK('KODE PROJECT BARU'!$B$5:$B$98, 'KODE PROJECT BARU'!$C$5:$C$98), _xlfn.VSTACK('KODE PROJECT BARU'!$E$5:$E$98, 'KODE PROJECT BARU'!$E$5:$E$98), "Tidak Ditemukan", 0, 1)} -> #NAME? | E14: SPPD | F14: DMO | G14: Ulfa | H14: FEBRUARI | I14: 105094644 | J14: PAID | K14: PERSADA | L14: OTC | N14: 2026
C15: PS-024-00 | D15: {=_xlfn.XLOOKUP(Tabel2[[#This Row],[KODE PROJECT]], _xlfn.VSTACK('KODE PROJECT BARU'!$B$5:$B$98, 'KODE PROJECT BARU'!$C$5:$C$98), _xlfn.VSTACK('KODE PROJECT BARU'!$E$5:$E$98, 'KODE PROJECT BARU'!$E$5:$E$98), "Tidak Ditemukan", 0, 1)} -> #NAME? | E15: SPPD | F15: DMO | G15: Ulfa | H15: MARET | I15: 54037546 | J15: PAID | K15: PERSADA | L15: OTC | N15: 2026
C16: PS-028-00 | D16: {=_xlfn.XLOOKUP(Tabel2[[#This Row],[KODE PROJECT]], _xlfn.VSTACK('KODE PROJECT BARU'!$B$5:$B$98, 'KODE PROJECT BARU'!$C$5:$C$98), _xlfn.VSTACK('KODE PROJECT BARU'!$E$5:$E$98, 'KODE PROJECT BARU'!$E$5:$E$98), "Tidak Ditemukan", 0, 1)} -> #NAME? | E16: UPAH | F16: DMO | G16: Ulfa | H16: JANUARI | I16: =20280832+289712 -> 20570544 | J16: PAID | K16: PERSADA | L16: MONTHLY | N16: 2026
C17: PS-028-00 | D17: {=_xlfn.XLOOKUP(Tabel2[[#This Row],[KODE PROJECT]], _xlfn.VSTACK('KODE PROJECT BARU'!$B$5:$B$98, 'KODE PROJECT BARU'!$C$5:$C$98), _xlfn.VSTACK('KODE PROJECT BARU'!$E$5:$E$98, 'KODE PROJECT BARU'!$E$5:$E$98), "Tidak Ditemukan", 0, 1)} -> #NAME? | E17: UPAH | F17: DMO | G17: Ulfa | H17: FEBRUARI | I17: =16470110+12240515 -> 28710625 | J17: PAID | K17: PERSADA | L17: MONTHLY | N17: 2026
C18: PS-028-00 | D18: {=_xlfn.XLOOKUP(Tabel2[[#This Row],[KODE PROJECT]], _xlfn.VSTACK('KODE PROJECT BARU'!$B$5:$B$98, 'KODE PROJECT BARU'!$C$5:$C$98), _xlfn.VSTACK('KODE PROJECT BARU'!$E$5:$E$98, 'KODE PROJECT BARU'!$E$5:$E$98), "Tidak Ditemukan", 0, 1)} -> #NAME? | E18: UPAH | F18: DMO | G18: Ulfa | H18: MARET | I18: =10575923-1154462 -> 9421461 | J18: PAID | K18: PERSADA | L18: MONTHLY | N18: 2026
C19: PS-028-00 | D19: {=_xlfn.XLOOKUP(Tabel2[[#This Row],[KODE PROJECT]], _xlfn.VSTACK('KODE PROJECT BARU'!$B$5:$B$98, 'KODE PROJECT BARU'!$C$5:$C$98), _xlfn.VSTACK('KODE PROJECT BARU'!$E$5:$E$98, 'KODE PROJECT BARU'!$E$5:$E$98), "Tidak Ditemukan", 0, 1)} -> #NAME? | E19: TALI KASIH | F19: DMO | G19: Ulfa | H19: MARET | I19: 1500000 | J19: PAID | K19: PERSADA | L19: OTC | N19: 2026
C20: PS-028-00 | D20: {=_xlfn.XLOOKUP(Tabel2[[#This Row],[KODE PROJECT]], _xlfn.VSTACK('KODE PROJECT BARU'!$B$5:$B$98, 'KODE PROJECT BARU'!$C$5:$C$98), _xlfn.VSTACK('KODE PROJECT BARU'!$E$5:$E$98, 'KODE PROJECT BARU'!$E$5:$E$98), "Tidak Ditemukan", 0, 1)} -> #NAME? | E20: THRK | F20: DMO | G20: Ulfa | H20: MARET | I20: 7584700 | J20: PAID | K20: PERSADA | L20: OTC | N20: 2026
C21: PS-028-00 | D21: {=_xlfn.XLOOKUP(Tabel2[[#This Row],[KODE PROJECT]], _xlfn.VSTACK('KODE PROJECT BARU'!$B$5:$B$98, 'KODE PROJECT BARU'!$C$5:$C$98), _xlfn.VSTACK('KODE PROJECT BARU'!$E$5:$E$98, 'KODE PROJECT BARU'!$E$5:$E$98), "Tidak Ditemukan", 0, 1)} -> #NAME? | E21: SPPD | F21: DMO | G21: Ulfa | H21: FEBRUARI | I21: 6088574 | J21: PAID | K21: PERSADA | L21: OTC | N21: 2026
C22: MS-019 | D22: {=_xlfn.XLOOKUP(Tabel2[[#This Row],[KODE PROJECT]], _xlfn.VSTACK('KODE PROJECT BARU'!$B$5:$B$98, 'KODE PROJECT BARU'!$C$5:$C$98), _xlfn.VSTACK('KODE PROJECT BARU'!$E$5:$E$98, 'KODE PROJECT BARU'!$E$5:$E$98), "Tidak Ditemukan", 0, 1)} -> #NAME? | E22: UPAH | F22: DMO | G22: Ulfa | H22: JANUARI | I22: =29356172-1314774 -> 28041398 | J22: PAID | K22: PERSADA | L22: MONTHLY | N22: 2026
C23: MS-019 | D23: {=_xlfn.XLOOKUP(Tabel2[[#This Row],[KODE PROJECT]], _xlfn.VSTACK('KODE PROJECT BARU'!$B$5:$B$98, 'KODE PROJECT BARU'!$C$5:$C$98), _xlfn.VSTACK('KODE PROJECT BARU'!$E$5:$E$98, 'KODE PROJECT BARU'!$E$5:$E$98), "Tidak Ditemukan", 0, 1)} -> #NAME? | E23: UPAH | F23: DMO | G23: Ulfa | H23: FEBRUARI | I23: =29356172-394114 -> 28962058 | J23: PAID | K23: PERSADA | L23: MONTHLY | N23: 2026
C24: MS-019 | D24: {=_xlfn.XLOOKUP(Tabel2[[#This Row],[KODE PROJECT]], _xlfn.VSTACK('KODE PROJECT BARU'!$B$5:$B$98, 'KODE PROJECT BARU'!$C$5:$C$98), _xlfn.VSTACK('KODE PROJECT BARU'!$E$5:$E$98, 'KODE PROJECT BARU'!$E$5:$E$98), "Tidak Ditemukan", 0, 1)} -> #NAME? | E24: UPAH | F24: DMO | G24: Ulfa | H24: MARET | I24: =29356172+2477355 -> 31833527 | J24: PAID | K24: PERSADA | L24: MONTHLY | N24: 2026
C25: MS-019 | D25: {=_xlfn.XLOOKUP(Tabel2[[#This Row],[KODE PROJECT]], _xlfn.VSTACK('KODE PROJECT BARU'!$B$5:$B$98, 'KODE PROJECT BARU'!$C$5:$C$98), _xlfn.VSTACK('KODE PROJECT BARU'!$E$5:$E$98, 'KODE PROJECT BARU'!$E$5:$E$98), "Tidak Ditemukan", 0, 1)} -> #NAME? | E25: TALI KASIH | F25: DMO | G25: Ulfa | H25: MARET | I25: 4500000 | J25: PAID | K25: PERSADA | L25: OTC | N25: 2026
C26: MS-019 | D26: {=_xlfn.XLOOKUP(Tabel2[[#This Row],[KODE PROJECT]], _xlfn.VSTACK('KODE PROJECT BARU'!$B$5:$B$98, 'KODE PROJECT BARU'!$C$5:$C$98), _xlfn.VSTACK('KODE PROJECT BARU'!$E$5:$E$98, 'KODE PROJECT BARU'!$E$5:$E$98), "Tidak Ditemukan", 0, 1)} -> #NAME? | E26: THRK | F26: DMO | G26: Ulfa | H26: MARET | I26: 20807845 | J26: PAID | K26: PERSADA | L26: OTC | N26: 2026
C27: MS-019 | D27: {=_xlfn.XLOOKUP(Tabel2[[#This Row],[KODE PROJECT]], _xlfn.VSTACK('KODE PROJECT BARU'!$B$5:$B$98, 'KODE PROJECT BARU'!$C$5:$C$98), _xlfn.VSTACK('KODE PROJECT BARU'!$E$5:$E$98, 'KODE PROJECT BARU'!$E$5:$E$98), "Tidak Ditemukan", 0, 1)} -> #NAME? | E27: SPPD | F27: DMO | G27: Ulfa | H27: JANUARI | I27: 1983761 | J27: PAID | K27: PERSADA | L27: OTC | N27: 2026
C28: MS-019 | D28: {=_xlfn.XLOOKUP(Tabel2[[#This Row],[KODE PROJECT]], _xlfn.VSTACK('KODE PROJECT BARU'!$B$5:$B$98, 'KODE PROJECT BARU'!$C$5:$C$98), _xlfn.VSTACK('KODE PROJECT BARU'!$E$5:$E$98, 'KODE PROJECT BARU'!$E$5:$E$98), "Tidak Ditemukan", 0, 1)} -> #NAME? | E28: SPPD | F28: DMO | G28: Ulfa | H28: FEBRUARI | I28: 7686569 | J28: PAID | K28: PERSADA | L28: OTC | N28: 2026
C29: PS-046-00 | D29: {=_xlfn.XLOOKUP(Tabel2[[#This Row],[KODE PROJECT]], _xlfn.VSTACK('KODE PROJECT BARU'!$B$5:$B$98, 'KODE PROJECT BARU'!$C$5:$C$98), _xlfn.VSTACK('KODE PROJECT BARU'!$E$5:$E$98, 'KODE PROJECT BARU'!$E$5:$E$98), "Tidak Ditemukan", 0, 1)} -> #NAME? | E29: UPAH | F29: DMO | G29: Ulfa | H29: JANUARI | I29: 7607974 | J29: PAID | K29: PERSADA | L29: MONTHLY | N29: 2026
C30: PS-046-00 | D30: {=_xlfn.XLOOKUP(Tabel2[[#This Row],[KODE PROJECT]], _xlfn.VSTACK('KODE PROJECT BARU'!$B$5:$B$98, 'KODE PROJECT BARU'!$C$5:$C$98), _xlfn.VSTACK('KODE PROJECT BARU'!$E$5:$E$98, 'KODE PROJECT BARU'!$E$5:$E$98), "Tidak Ditemukan", 0, 1)} -> #NAME? | E30: UPAH | F30: DMO | G30: Ulfa | H30: FEBRUARI | I30: 7607974 | J30: PAID | K30: PERSADA | L30: MONTHLY | N30: 2026
C31: PS-046-00 | D31: {=_xlfn.XLOOKUP(Tabel2[[#This Row],[KODE PROJECT]], _xlfn.VSTACK('KODE PROJECT BARU'!$B$5:$B$98, 'KODE PROJECT BARU'!$C$5:$C$98), _xlfn.VSTACK('KODE PROJECT BARU'!$E$5:$E$98, 'KODE PROJECT BARU'!$E$5:$E$98), "Tidak Ditemukan", 0, 1)} -> #NAME? | E31: UPAH | F31: DMO | G31: Ulfa | H31: MARET | I31: 7607974 | J31: PAID | K31: PERSADA | L31: MONTHLY | N31: 2026
C32: PS-046-00 | D32: {=_xlfn.XLOOKUP(Tabel2[[#This Row],[KODE PROJECT]], _xlfn.VSTACK('KODE PROJECT BARU'!$B$5:$B$98, 'KODE PROJECT BARU'!$C$5:$C$98), _xlfn.VSTACK('KODE PROJECT BARU'!$E$5:$E$98, 'KODE PROJECT BARU'!$E$5:$E$98), "Tidak Ditemukan", 0, 1)} -> #NAME? | E32: THRK | F32: DMO | G32: Ulfa | H32: MARET | I32: 5870350 | J32: PAID | K32: PERSADA | L32: OTC | N32: 2026
C33: PS-004-00 | D33: {=_xlfn.XLOOKUP(Tabel2[[#This Row],[KODE PROJECT]], _xlfn.VSTACK('KODE PROJECT BARU'!$B$5:$B$98, 'KODE PROJECT BARU'!$C$5:$C$98), _xlfn.VSTACK('KODE PROJECT BARU'!$E$5:$E$98, 'KODE PROJECT BARU'!$E$5:$E$98), "Tidak Ditemukan", 0, 1)} -> #NAME? | E33: UPAH | F33: DMO | G33: Ulfa | H33: JANUARI | I33: 618542477 | J33: PAID | K33: PERSADA | L33: MONTHLY | N33: 2026
C34: PS-004-00 | D34: {=_xlfn.XLOOKUP(Tabel2[[#This Row],[KODE PROJECT]], _xlfn.VSTACK('KODE PROJECT BARU'!$B$5:$B$98, 'KODE PROJECT BARU'!$C$5:$C$98), _xlfn.VSTACK('KODE PROJECT BARU'!$E$5:$E$98, 'KODE PROJECT BARU'!$E$5:$E$98), "Tidak Ditemukan", 0, 1)} -> #NAME? | E34: UPAH | F34: DMO | G34: Ulfa | H34: FEBRUARI | I34: 630360579 | J34: PAID | K34: PERSADA | L34: MONTHLY | N34: 2026
C35: PS-004-00 | D35: {=_xlfn.XLOOKUP(Tabel2[[#This Row],[KODE PROJECT]], _xlfn.VSTACK('KODE PROJECT BARU'!$B$5:$B$98, 'KODE PROJECT BARU'!$C$5:$C$98), _xlfn.VSTACK('KODE PROJECT BARU'!$E$5:$E$98, 'KODE PROJECT BARU'!$E$5:$E$98), "Tidak Ditemukan", 0, 1)} -> #NAME? | E35: UPAH | F35: DMO | G35: Ulfa | H35: MARET | I35: 631560786 | J35: PAID | K35: PERSADA | L35: MONTHLY | N35: 2026
C36: PS-004-00 | D36: {=_xlfn.XLOOKUP(Tabel2[[#This Row],[KODE PROJECT]], _xlfn.VSTACK('KODE PROJECT BARU'!$B$5:$B$98, 'KODE PROJECT BARU'!$C$5:$C$98), _xlfn.VSTACK('KODE PROJECT BARU'!$E$5:$E$98, 'KODE PROJECT BARU'!$E$5:$E$98), "Tidak Ditemukan", 0, 1)} -> #NAME? | E36: TUNJANGAN TIDAK TETAP | F36: DMO | G36: Ulfa | H36: JANUARI | I36: 11273150 | J36: PAID | K36: PERSADA | L36: OTC | N36: 2026
... C50: PS-008-00 | D50: {=_xlfn.XLOOKUP(Tabel2[[#This Row],[KODE PROJECT]], _xlfn.VSTACK('KODE PROJECT BARU'!$B$5:$B$98, 'KODE PROJECT BARU'!$C$5:$C$98), _xlfn.VSTACK('KODE PROJECT BARU'!$E$5:$E$98, 'KODE PROJECT BARU'!$E$5:$E$98), "Tidak Ditemukan", 0, 1)} -> #NAME? | E50: THRK | F50: DMO | G50: Ulfa | H50: MARET | I50: 6337046 | J50: PAID | K50: PERSADA | L50: OTC | N50: 2026
C51: PS-023-00 | D51: {=_xlfn.XLOOKUP(Tabel2[[#This Row],[KODE PROJECT]], _xlfn.VSTACK('KODE PROJECT BARU'!$B$5:$B$98, 'KODE PROJECT BARU'!$C$5:$C$98), _xlfn.VSTACK('KODE PROJECT BARU'!$E$5:$E$98, 'KODE PROJECT BARU'!$E$5:$E$98), "Tidak Ditemukan", 0, 1)} -> #NAME? | E51: UPAH | F51: DMO | G51: Ulfa | H51: JANUARI | I51: =652725791-4995298 -> 647730493 | J51: PAID | K51: PERSADA | L51: MONTHLY | N51: 2026
C52: PS-023-00 | D52: {=_xlfn.XLOOKUP(Tabel2[[#This Row],[KODE PROJECT]], _xlfn.VSTACK('KODE PROJECT BARU'!$B$5:$B$98, 'KODE PROJECT BARU'!$C$5:$C$98), _xlfn.VSTACK('KODE PROJECT BARU'!$E$5:$E$98, 'KODE PROJECT BARU'!$E$5:$E$98), "Tidak Ditemukan", 0, 1)} -> #NAME? | E52: UPAH | F52: DMO | G52: Ulfa | H52: FEBRUARI | I52: =652725791-7936357 -> 644789434 | J52: PAID | K52: PERSADA | L52: MONTHLY | N52: 2026
C53: PS-023-00 | D53: {=_xlfn.XLOOKUP(Tabel2[[#This Row],[KODE PROJECT]], _xlfn.VSTACK('KODE PROJECT BARU'!$B$5:$B$98, 'KODE PROJECT BARU'!$C$5:$C$98), _xlfn.VSTACK('KODE PROJECT BARU'!$E$5:$E$98, 'KODE PROJECT BARU'!$E$5:$E$98), "Tidak Ditemukan", 0, 1)} -> #NAME? | E53: UPAH | F53: DMO | G53: Ulfa | H53: MARET | I53: =652725791-26885241 -> 625840550 | J53: PAID | K53: PERSADA | L53: MONTHLY | N53: 2026
C54: PS-023-00 | D54: {=_xlfn.XLOOKUP(Tabel2[[#This Row],[KODE PROJECT]], _xlfn.VSTACK('KODE PROJECT BARU'!$B$5:$B$98, 'KODE PROJECT BARU'!$C$5:$C$98), _xlfn.VSTACK('KODE PROJECT BARU'!$E$5:$E$98, 'KODE PROJECT BARU'!$E$5:$E$98), "Tidak Ditemukan", 0, 1)} -> #NAME? | E54: PARKIR | F54: DMO | G54: Ulfa | H54: JANUARI | I54: 937178 | J54: PAID | K54: PERSADA | L54: OTC | N54: 2026
C55: PS-023-00 | D55: {=_xlfn.XLOOKUP(Tabel2[[#This Row],[KODE PROJECT]], _xlfn.VSTACK('KODE PROJECT BARU'!$B$5:$B$98, 'KODE PROJECT BARU'!$C$5:$C$98), _xlfn.VSTACK('KODE PROJECT BARU'!$E$5:$E$98, 'KODE PROJECT BARU'!$E$5:$E$98), "Tidak Ditemukan", 0, 1)} -> #NAME? | E55: PARKIR | F55: DMO | G55: Ulfa | H55: FEBRUARI | I55: 822888 | J55: PAID | K55: PERSADA | L55: OTC | N55: 2026
C56: PS-023-00 | D56: {=_xlfn.XLOOKUP(Tabel2[[#This Row],[KODE PROJECT]], _xlfn.VSTACK('KODE PROJECT BARU'!$B$5:$B$98, 'KODE PROJECT BARU'!$C$5:$C$98), _xlfn.VSTACK('KODE PROJECT BARU'!$E$5:$E$98, 'KODE PROJECT BARU'!$E$5:$E$98), "Tidak Ditemukan", 0, 1)} -> #NAME? | E56: PARKIR | F56: DMO | G56: Ulfa | H56: MARET | I56: 822888 | J56: PAID | K56: PERSADA | L56: OTC | N56: 2026
C57: PS-023-00 | D57: {=_xlfn.XLOOKUP(Tabel2[[#This Row],[KODE PROJECT]], _xlfn.VSTACK('KODE PROJECT BARU'!$B$5:$B$98, 'KODE PROJECT BARU'!$C$5:$C$98), _xlfn.VSTACK('KODE PROJECT BARU'!$E$5:$E$98, 'KODE PROJECT BARU'!$E$5:$E$98), "Tidak Ditemukan", 0, 1)} -> #NAME? | E57: PARKIR | F57: DMO | G57: Ulfa | H57: APRIL | I57: 822888 | J57: PAID | K57: PERSADA | L57: OTC | N57: 2026
C58: PS-023-00 | D58: {=_xlfn.XLOOKUP(Tabel2[[#This Row],[KODE PROJECT]], _xlfn.VSTACK('KODE PROJECT BARU'!$B$5:$B$98, 'KODE PROJECT BARU'!$C$5:$C$98), _xlfn.VSTACK('KODE PROJECT BARU'!$E$5:$E$98, 'KODE PROJECT BARU'!$E$5:$E$98), "Tidak Ditemukan", 0, 1)} -> #NAME? | E58: TALI KASIH | F58: DMO | G58: Ulfa | H58: MARET | I58: 94377907 | J58: PAID | K58: PERSADA | L58: OTC | N58: 2026
C59: PS-023-00 | D59: {=_xlfn.XLOOKUP(Tabel2[[#This Row],[KODE PROJECT]], _xlfn.VSTACK('KODE PROJECT BARU'!$B$5:$B$98, 'KODE PROJECT BARU'!$C$5:$C$98), _xlfn.VSTACK('KODE PROJECT BARU'!$E$5:$E$98, 'KODE PROJECT BARU'!$E$5:$E$98), "Tidak Ditemukan", 0, 1)} -> #NAME? | E59: THRK | F59: DMO | G59: Ulfa | H59: MARET | I59: 455189858 | J59: PAID | K59: PERSADA | L59: OTC | N59: 2026
C60: PS-023-00 | D60: {=_xlfn.XLOOKUP(Tabel2[[#This Row],[KODE PROJECT]], _xlfn.VSTACK('KODE PROJECT BARU'!$B$5:$B$98, 'KODE PROJECT BARU'!$C$5:$C$98), _xlfn.VSTACK('KODE PROJECT BARU'!$E$5:$E$98, 'KODE PROJECT BARU'!$E$5:$E$98), "Tidak Ditemukan", 0, 1)} -> #NAME? | E60: SPPD | F60: DMO | G60: Ulfa | H60: JANUARI | I60: 14753263 | J60: PAID | K60: PERSADA | L60: OTC | N60: 2026
C61: PS-023-00 | D61: {=_xlfn.XLOOKUP(Tabel2[[#This Row],[KODE PROJECT]], _xlfn.VSTACK('KODE PROJECT BARU'!$B$5:$B$98, 'KODE PROJECT BARU'!$C$5:$C$98), _xlfn.VSTACK('KODE PROJECT BARU'!$E$5:$E$98, 'KODE PROJECT BARU'!$E$5:$E$98), "Tidak Ditemukan", 0, 1)} -> #NAME? | E61: SPPD | F61: DMO | G61: Ulfa | H61: FEBRUARI | I61: 5654253 | J61: PAID | K61: PERSADA | L61: OTC | N61: 2026
C62: PS-018-00 | D62: {=_xlfn.XLOOKUP(Tabel2[[#This Row],[KODE PROJECT]], _xlfn.VSTACK('KODE PROJECT BARU'!$B$5:$B$98, 'KODE PROJECT BARU'!$C$5:$C$98), _xlfn.VSTACK('KODE PROJECT BARU'!$E$5:$E$98, 'KODE PROJECT BARU'!$E$5:$E$98), "Tidak Ditemukan", 0, 1)} -> #NAME? | E62: UPAH | F62: DMO | G62: Ulfa | H62: JANUARI | I62: =304331903-14136191 -> 290195712 | J62: PAID | K62: PERSADA | L62: MONTHLY | N62: 2026
C63: PS-018-00 | D63: {=_xlfn.XLOOKUP(Tabel2[[#This Row],[KODE PROJECT]], _xlfn.VSTACK('KODE PROJECT BARU'!$B$5:$B$98, 'KODE PROJECT BARU'!$C$5:$C$98), _xlfn.VSTACK('KODE PROJECT BARU'!$E$5:$E$98, 'KODE PROJECT BARU'!$E$5:$E$98), "Tidak Ditemukan", 0, 1)} -> #NAME? | E63: UPAH | F63: DMO | G63: Ulfa | H63: FEBRUARI | I63: =323720226-17000000 -> 306720226 | J63: PAID | K63: PERSADA | L63: MONTHLY | N63: 2026
C64: PS-018-00 | D64: {=_xlfn.XLOOKUP(Tabel2[[#This Row],[KODE PROJECT]], _xlfn.VSTACK('KODE PROJECT BARU'!$B$5:$B$98, 'KODE PROJECT BARU'!$C$5:$C$98), _xlfn.VSTACK('KODE PROJECT BARU'!$E$5:$E$98, 'KODE PROJECT BARU'!$E$5:$E$98), "Tidak Ditemukan", 0, 1)} -> #NAME? | E64: UPAH | F64: DMO | G64: Ulfa | H64: MARET | I64: =325758212-16641599 -> 309116613 | J64: PAID | K64: PERSADA | L64: MONTHLY | N64: 2026
C65: PS-018-00 | D65: {=_xlfn.XLOOKUP(Tabel2[[#This Row],[KODE PROJECT]], _xlfn.VSTACK('KODE PROJECT BARU'!$B$5:$B$98, 'KODE PROJECT BARU'!$C$5:$C$98), _xlfn.VSTACK('KODE PROJECT BARU'!$E$5:$E$98, 'KODE PROJECT BARU'!$E$5:$E$98), "Tidak Ditemukan", 0, 1)} -> #NAME? | E65: TALI KASIH | F65: DMO | G65: Ulfa | H65: MARET | I65: 20079942 | J65: PAID | K65: PERSADA | L65: OTC | N65: 2026
C66: PS-018-00 | D66: {=_xlfn.XLOOKUP(Tabel2[[#This Row],[KODE PROJECT]], _xlfn.VSTACK('KODE PROJECT BARU'!$B$5:$B$98, 'KODE PROJECT BARU'!$C$5:$C$98), _xlfn.VSTACK('KODE PROJECT BARU'!$E$5:$E$98, 'KODE PROJECT BARU'!$E$5:$E$98), "Tidak Ditemukan", 0, 1)} -> #NAME? | E66: THRK | F66: DMO | G66: Ulfa | H66: MARET | I66: 230300551 | J66: PAID | K66: PERSADA | L66: OTC | N66: 2026
C67: PS-018-00 | D67: {=_xlfn.XLOOKUP(Tabel2[[#This Row],[KODE PROJECT]], _xlfn.VSTACK('KODE PROJECT BARU'!$B$5:$B$98, 'KODE PROJECT BARU'!$C$5:$C$98), _xlfn.VSTACK('KODE PROJECT BARU'!$E$5:$E$98, 'KODE PROJECT BARU'!$E$5:$E$98), "Tidak Ditemukan", 0, 1)} -> #NAME? | E67: SPPD | F67: DMO | G67: Ulfa | H67: JANUARI | I67: 2311775 | J67: PAID | K67: PERSADA | L67: OTC | N67: 2026
C68: PS-020-00 | D68: {=_xlfn.XLOOKUP(Tabel2[[#This Row],[KODE PROJECT]], _xlfn.VSTACK('KODE PROJECT BARU'!$B$5:$B$98, 'KODE PROJECT BARU'!$C$5:$C$98), _xlfn.VSTACK('KODE PROJECT BARU'!$E$5:$E$98, 'KODE PROJECT BARU'!$E$5:$E$98), "Tidak Ditemukan", 0, 1)} -> #NAME? | E68: UPAH | F68: DMO | G68: Ulfa | H68: JANUARI | I68: =171528180+4429499 -> 175957679 | J68: PAID | K68: PERSADA | L68: MONTHLY | N68: 2026
C69: PS-020-00 | D69: {=_xlfn.XLOOKUP(Tabel2[[#This Row],[KODE PROJECT]], _xlfn.VSTACK('KODE PROJECT BARU'!$B$5:$B$98, 'KODE PROJECT BARU'!$C$5:$C$98), _xlfn.VSTACK('KODE PROJECT BARU'!$E$5:$E$98, 'KODE PROJECT BARU'!$E$5:$E$98), "Tidak Ditemukan", 0, 1)} -> #NAME? | E69: UPAH | F69: DMO | G69: Ulfa | H69: FEBRUARI | I69: =176326553+7094115 -> 183420668 | J69: PAID | K69: PERSADA | L69: MONTHLY | N69: 2026
C70: PS-020-00 | D70: {=_xlfn.XLOOKUP(Tabel2[[#This Row],[KODE PROJECT]], _xlfn.VSTACK('KODE PROJECT BARU'!$B$5:$B$98, 'KODE PROJECT BARU'!$C$5:$C$98), _xlfn.VSTACK('KODE PROJECT BARU'!$E$5:$E$98, 'KODE PROJECT BARU'!$E$5:$E$98), "Tidak Ditemukan", 0, 1)} -> #NAME? | E70: UPAH | F70: DMO | G70: Ulfa | H70: MARET | I70: =179575753+8265672 -> 187841425 | J70: PAID | K70: PERSADA | L70: MONTHLY | N70: 2026
C71: PS-020-00 | D71: {=_xlfn.XLOOKUP(Tabel2[[#This Row],[KODE PROJECT]], _xlfn.VSTACK('KODE PROJECT BARU'!$B$5:$B$98, 'KODE PROJECT BARU'!$C$5:$C$98), _xlfn.VSTACK('KODE PROJECT BARU'!$E$5:$E$98, 'KODE PROJECT BARU'!$E$5:$E$98), "Tidak Ditemukan", 0, 1)} -> #NAME? | E71: TALI KASIH | F71: DMO | G71: Ulfa | H71: MARET | I71: 15968023 | J71: PAID | K71: PERSADA | L71: OTC | N71: 2026
C72: PS-020-00 | D72: {=_xlfn.XLOOKUP(Tabel2[[#This Row],[KODE PROJECT]], _xlfn.VSTACK('KODE PROJECT BARU'!$B$5:$B$98, 'KODE PROJECT BARU'!$C$5:$C$98), _xlfn.VSTACK('KODE PROJECT BARU'!$E$5:$E$98, 'KODE PROJECT BARU'!$E$5:$E$98), "Tidak Ditemukan", 0, 1)} -> #NAME? | E72: THRK | F72: DMO | G72: Ulfa | H72: MARET | I72: 102347632 | J72: PAID | K72: PERSADA | L72: OTC | N72: 2026
C73: PS-020-00 | D73: {=_xlfn.XLOOKUP(Tabel2[[#This Row],[KODE PROJECT]], _xlfn.VSTACK('KODE PROJECT BARU'!$B$5:$B$98, 'KODE PROJECT BARU'!$C$5:$C$98), _xlfn.VSTACK('KODE PROJECT BARU'!$E$5:$E$98, 'KODE PROJECT BARU'!$E$5:$E$98), "Tidak Ditemukan", 0, 1)} -> #NAME? | E73: EXAM | F73: DMO | G73: Ulfa | H73: FEBRUARI | I73: 51820125 | J73: PAID | K73: PERSADA | L73: OTC | N73: 2026
C74: PS-019-00 | D74: {=_xlfn.XLOOKUP(Tabel2[[#This Row],[KODE PROJECT]], _xlfn.VSTACK('KODE PROJECT BARU'!$B$5:$B$98, 'KODE PROJECT BARU'!$C$5:$C$98), _xlfn.VSTACK('KODE PROJECT BARU'!$E$5:$E$98, 'KODE PROJECT BARU'!$E$5:$E$98), "Tidak Ditemukan", 0, 1)} -> #NAME? | E74: UPAH | F74: DMO | G74: Ulfa | H74: JANUARI | I74: =26829832-2000000 -> 24829832 | J74: PAID | K74: PERSADA | L74: MONTHLY | N74: 2026
C75: PS-019-00 | D75: {=_xlfn.XLOOKUP(Tabel2[[#This Row],[KODE PROJECT]], _xlfn.VSTACK('KODE PROJECT BARU'!$B$5:$B$98, 'KODE PROJECT BARU'!$C$5:$C$98), _xlfn.VSTACK('KODE PROJECT BARU'!$E$5:$E$98, 'KODE PROJECT BARU'!$E$5:$E$98), "Tidak Ditemukan", 0, 1)} -> #NAME? | E75: UPAH | F75: DMO | G75: Ulfa | H75: FEBRUARI | I75: =26829832-2000000 -> 24829832 | J75: PAID | K75: PERSADA | L75: MONTHLY | N75: 2026
C76: PS-019-00 | D76: {=_xlfn.XLOOKUP(Tabel2[[#This Row],[KODE PROJECT]], _xlfn.VSTACK('KODE PROJECT BARU'!$B$5:$B$98, 'KODE PROJECT BARU'!$C$5:$C$98), _xlfn.VSTACK('KODE PROJECT BARU'!$E$5:$E$98, 'KODE PROJECT BARU'!$E$5:$E$98), "Tidak Ditemukan", 0, 1)} -> #NAME? | E76: UPAH | F76: DMO | G76: Ulfa | H76: MARET | I76: =26829832-1602110 -> 25227722 | J76: PAID | K76: PERSADA | L76: MONTHLY | N76: 2026
C77: PS-019-00 | D77: {=_xlfn.XLOOKUP(Tabel2[[#This Row],[KODE PROJECT]], _xlfn.VSTACK('KODE PROJECT BARU'!$B$5:$B$98, 'KODE PROJECT BARU'!$C$5:$C$98), _xlfn.VSTACK('KODE PROJECT BARU'!$E$5:$E$98, 'KODE PROJECT BARU'!$E$5:$E$98), "Tidak Ditemukan", 0, 1)} -> #NAME? | E77: TALI KASIH | F77: DMO | G77: Ulfa | H77: MARET | I77: 3000000 | J77: PAID | K77: PERSADA | L77: OTC | N77: 2026
C78: PS-019-00 | D78: {=_xlfn.XLOOKUP(Tabel2[[#This Row],[KODE PROJECT]], _xlfn.VSTACK('KODE PROJECT BARU'!$B$5:$B$98, 'KODE PROJECT BARU'!$C$5:$C$98), _xlfn.VSTACK('KODE PROJECT BARU'!$E$5:$E$98, 'KODE PROJECT BARU'!$E$5:$E$98), "Tidak Ditemukan", 0, 1)} -> #NAME? | E78: THRK | F78: DMO | G78: Ulfa | H78: MARET | I78: 19866724 | J78: PAID | K78: PERSADA | L78: OTC | N78: 2026
C79: PS-047-00 | D79: {=_xlfn.XLOOKUP(Tabel2[[#This Row],[KODE PROJECT]], _xlfn.VSTACK('KODE PROJECT BARU'!$B$5:$B$98, 'KODE PROJECT BARU'!$C$5:$C$98), _xlfn.VSTACK('KODE PROJECT BARU'!$E$5:$E$98, 'KODE PROJECT BARU'!$E$5:$E$98), "Tidak Ditemukan", 0, 1)} -> #NAME? | E79: UPAH | F79: DMO | G79: Ulfa | H79: JANUARI | I79: =167365613+289712 -> 167655325 | J79: PAID | K79: PERSADA | L79: MONTHLY | N79: 2026
C80: PS-047-00 | D80: {=_xlfn.XLOOKUP(Tabel2[[#This Row],[KODE PROJECT]], _xlfn.VSTACK('KODE PROJECT BARU'!$B$5:$B$98, 'KODE PROJECT BARU'!$C$5:$C$98), _xlfn.VSTACK('KODE PROJECT BARU'!$E$5:$E$98, 'KODE PROJECT BARU'!$E$5:$E$98), "Tidak Ditemukan", 0, 1)} -> #NAME? | E80: UPAH | F80: DMO | G80: Ulfa | H80: FEBRUARI | I80: =167365613+12240515 -> 179606128 | J80: PAID | K80: PERSADA | L80: MONTHLY | N80: 2026
C81: PS-047-00 | D81: {=_xlfn.XLOOKUP(Tabel2[[#This Row],[KODE PROJECT]], _xlfn.VSTACK('KODE PROJECT BARU'!$B$5:$B$98, 'KODE PROJECT BARU'!$C$5:$C$98), _xlfn.VSTACK('KODE PROJECT BARU'!$E$5:$E$98, 'KODE PROJECT BARU'!$E$5:$E$98), "Tidak Ditemukan", 0, 1)} -> #NAME? | E81: UPAH | F81: DMO | G81: Ulfa | H81: MARET | I81: =170912613-1154462 -> 169758151 | J81: PAID | K81: PERSADA | L81: MONTHLY | N81: 2026
C82: PS-047-00 | D82: {=_xlfn.XLOOKUP(Tabel2[[#This Row],[KODE PROJECT]], _xlfn.VSTACK('KODE PROJECT BARU'!$B$5:$B$98, 'KODE PROJECT BARU'!$C$5:$C$98), _xlfn.VSTACK('KODE PROJECT BARU'!$E$5:$E$98, 'KODE PROJECT BARU'!$E$5:$E$98), "Tidak Ditemukan", 0, 1)} -> #NAME? | E82: TUNJANGAN OFFSHORE | F82: DMO | G82: Ulfa | H82: JANUARI | I82: 53389015 | J82: PAID | K82: PERSADA | L82: OTC | N82: 2026
C83: PS-047-00 | D83: {=_xlfn.XLOOKUP(Tabel2[[#This Row],[KODE PROJECT]], _xlfn.VSTACK('KODE PROJECT BARU'!$B$5:$B$98, 'KODE PROJECT BARU'!$C$5:$C$98), _xlfn.VSTACK('KODE PROJECT BARU'!$E$5:$E$98, 'KODE PROJECT BARU'!$E$5:$E$98), "Tidak Ditemukan", 0, 1)} -> #NAME? | E83: TUNJANGAN OFFSHORE | F83: DMO | G83: Ulfa | H83: FEBRUARI | I83: 46910850 | J83: PAID | K83: PERSADA | L83: OTC | N83: 2026
C84: PS-047-00 | D84: {=_xlfn.XLOOKUP(Tabel2[[#This Row],[KODE PROJECT]], _xlfn.VSTACK('KODE PROJECT BARU'!$B$5:$B$98, 'KODE PROJECT BARU'!$C$5:$C$98), _xlfn.VSTACK('KODE PROJECT BARU'!$E$5:$E$98, 'KODE PROJECT BARU'!$E$5:$E$98), "Tidak Ditemukan", 0, 1)} -> #NAME? | E84: TUNJANGAN OFFSHORE | F84: DMO | G84: Ulfa | H84: MARET | I84: 51825320 | J84: PAID | K84: PERSADA | L84: OTC | N84: 2026
C85: PS-047-00 | D85: {=_xlfn.XLOOKUP(Tabel2[[#This Row],[KODE PROJECT]], _xlfn.VSTACK('KODE PROJECT BARU'!$B$5:$B$98, 'KODE PROJECT BARU'!$C$5:$C$98), _xlfn.VSTACK('KODE PROJECT BARU'!$E$5:$E$98, 'KODE PROJECT BARU'!$E$5:$E$98), "Tidak Ditemukan", 0, 1)} -> #NAME? | E85: TRAINING | F85: DMO | G85: Ulfa | H85: JANUARI | I85: 1039000 | J85: PAID | K85: PERSADA | L85: OTC | N85: 2026
C86: PS-047-00 | D86: {=_xlfn.XLOOKUP(Tabel2[[#This Row],[KODE PROJECT]], _xlfn.VSTACK('KODE PROJECT BARU'!$B$5:$B$98, 'KODE PROJECT BARU'!$C$5:$C$98), _xlfn.VSTACK('KODE PROJECT BARU'!$E$5:$E$98, 'KODE PROJECT BARU'!$E$5:$E$98), "Tidak Ditemukan", 0, 1)} -> #NAME? | E86: THRK | F86: DMO | G86: Ulfa | H86: MARET | I86: 121962055 | J86: PAID | K86: PERSADA | L86: OTC | N86: 2026
C87: PS-060-00 | D87: {=_xlfn.XLOOKUP(Tabel2[[#This Row],[KODE PROJECT]], _xlfn.VSTACK('KODE PROJECT BARU'!$B$5:$B$98, 'KODE PROJECT BARU'!$C$5:$C$98), _xlfn.VSTACK('KODE PROJECT BARU'!$E$5:$E$98, 'KODE PROJECT BARU'!$E$5:$E$98), "Tidak Ditemukan", 0, 1)} -> #NAME? | E87: UPAH | F87: DMO | G87: Ulfa | H87: JANUARI | I87: 17182612 | J87: PAID | K87: PERSADA | L87: MONTHLY | N87: 2026
C88: PS-060-00 | D88: {=_xlfn.XLOOKUP(Tabel2[[#This Row],[KODE PROJECT]], _xlfn.VSTACK('KODE PROJECT BARU'!$B$5:$B$98, 'KODE PROJECT BARU'!$C$5:$C$98), _xlfn.VSTACK('KODE PROJECT BARU'!$E$5:$E$98, 'KODE PROJECT BARU'!$E$5:$E$98), "Tidak Ditemukan", 0, 1)} -> #NAME? | E88: UPAH | F88: DMO | G88: Ulfa | H88: FEBRUARI | I88: 17182612 | J88: PAID | K88: PERSADA | L88: MONTHLY | N88: 2026
C89: PS-060-00 | D89: {=_xlfn.XLOOKUP(Tabel2[[#This Row],[KODE PROJECT]], _xlfn.VSTACK('KODE PROJECT BARU'!$B$5:$B$98, 'KODE PROJECT BARU'!$C$5:$C$98), _xlfn.VSTACK('KODE PROJECT BARU'!$E$5:$E$98, 'KODE PROJECT BARU'!$E$5:$E$98), "Tidak Ditemukan", 0, 1)} -> #NAME? | E89: UPAH | F89: DMO | G89: Ulfa | H89: MARET | I89: 17182612 | J89: PAID | K89: PERSADA | L89: MONTHLY | N89: 2026
C90: PS-060-00 | D90: {=_xlfn.XLOOKUP(Tabel2[[#This Row],[KODE PROJECT]], _xlfn.VSTACK('KODE PROJECT BARU'!$B$5:$B$98, 'KODE PROJECT BARU'!$C$5:$C$98), _xlfn.VSTACK('KODE PROJECT BARU'!$E$5:$E$98, 'KODE PROJECT BARU'!$E$5:$E$98), "Tidak Ditemukan", 0, 1)} -> #NAME? | E90: TALI KASIH | F90: DMO | G90: Ulfa | H90: MARET | I90: 2760174 | J90: PAID | K90: PERSADA | L90: OTC | N90: 2026
C91: PS-060-00 | D91: {=_xlfn.XLOOKUP(Tabel2[[#This Row],[KODE PROJECT]], _xlfn.VSTACK('KODE PROJECT BARU'!$B$5:$B$98, 'KODE PROJECT BARU'!$C$5:$C$98), _xlfn.VSTACK('KODE PROJECT BARU'!$E$5:$E$98, 'KODE PROJECT BARU'!$E$5:$E$98), "Tidak Ditemukan", 0, 1)} -> #NAME? | E91: THRK | F91: DMO | G91: Ulfa | H91: MARET | I91: 12807729 | J91: PAID | K91: PERSADA | L91: OTC | N91: 2026
C92: PS-027-00 | D92: {=_xlfn.XLOOKUP(Tabel2[[#This Row],[KODE PROJECT]], _xlfn.VSTACK('KODE PROJECT BARU'!$B$5:$B$98, 'KODE PROJECT BARU'!$C$5:$C$98), _xlfn.VSTACK('KODE PROJECT BARU'!$E$5:$E$98, 'KODE PROJECT BARU'!$E$5:$E$98), "Tidak Ditemukan", 0, 1)} -> #NAME? | E92: UPAH | F92: DMO | G92: Ulfa | H92: MARET | I92: 11498860 | J92: PAID | K92: PERSADA | L92: MONTHLY | N92: 2026
C93: PS-027-00 | D93: {=_xlfn.XLOOKUP(Tabel2[[#This Row],[KODE PROJECT]], _xlfn.VSTACK('KODE PROJECT BARU'!$B$5:$B$98, 'KODE PROJECT BARU'!$C$5:$C$98), _xlfn.VSTACK('KODE PROJECT BARU'!$E$5:$E$98, 'KODE PROJECT BARU'!$E$5:$E$98), "Tidak Ditemukan", 0, 1)} -> #NAME? | E93: THRK | F93: DMO | G93: Ulfa | H93: MARET | I93: 8312000 | J93: PAID | K93: PERSADA | L93: OTC | N93: 2026
... C98: PS-023-00 | D98: {=_xlfn.XLOOKUP(Tabel2[[#This Row],[KODE PROJECT]], _xlfn.VSTACK('KODE PROJECT BARU'!$B$5:$B$98, 'KODE PROJECT BARU'!$C$5:$C$98), _xlfn.VSTACK('KODE PROJECT BARU'!$E$5:$E$98, 'KODE PROJECT BARU'!$E$5:$E$98), "Tidak Ditemukan", 0, 1)} -> #NAME? | E98: SPPD | F98: DMO | G98: Ulfa | H98: APRIL | I98: 5311026 | J98: POPAY | K98: PERSADA | L98: OTC | N98: 2026
C99: PS-018-00 | D99: {=_xlfn.XLOOKUP(Tabel2[[#This Row],[KODE PROJECT]], _xlfn.VSTACK('KODE PROJECT BARU'!$B$5:$B$98, 'KODE PROJECT BARU'!$C$5:$C$98), _xlfn.VSTACK('KODE PROJECT BARU'!$E$5:$E$98, 'KODE PROJECT BARU'!$E$5:$E$98), "Tidak Ditemukan", 0, 1)} -> #NAME? | E99: SPPD | F99: DMO | G99: Ulfa | H99: APRIL | I99: =575000*1039 -> 597425000 | J99: POPAY | K99: PERSADA | L99: OTC | N99: 2026
C100: PS-034-00 | D100: {=_xlfn.XLOOKUP(Tabel2[[#This Row],[KODE PROJECT]], _xlfn.VSTACK('KODE PROJECT BARU'!$B$5:$B$98, 'KODE PROJECT BARU'!$C$5:$C$98), _xlfn.VSTACK('KODE PROJECT BARU'!$E$5:$E$98, 'KODE PROJECT BARU'!$E$5:$E$98), "Tidak Ditemukan", 0, 1)} -> #NAME? | E100: SPPD | F100: DMO | G100: Ulfa | H100: APRIL | I100: 2073586 | J100: POPAY | K100: PERSADA | L100: OTC | N100: 2026
C101: PS-024-00 | D101: {=_xlfn.XLOOKUP(Tabel2[[#This Row],[KODE PROJECT]], _xlfn.VSTACK('KODE PROJECT BARU'!$B$5:$B$98, 'KODE PROJECT BARU'!$C$5:$C$98), _xlfn.VSTACK('KODE PROJECT BARU'!$E$5:$E$98, 'KODE PROJECT BARU'!$E$5:$E$98), "Tidak Ditemukan", 0, 1)} -> #NAME? | E101: UPAH | F101: DMO | G101: Ulfa | H101: APRIL | I101: 872733117 | J101: PAID | K101: PERSADA | L101: MONTHLY | N101: 2026
C102: PS-023-00 | D102: {=_xlfn.XLOOKUP(Tabel2[[#This Row],[KODE PROJECT]], _xlfn.VSTACK('KODE PROJECT BARU'!$B$5:$B$98, 'KODE PROJECT BARU'!$C$5:$C$98), _xlfn.VSTACK('KODE PROJECT BARU'!$E$5:$E$98, 'KODE PROJECT BARU'!$E$5:$E$98), "Tidak Ditemukan", 0, 1)} -> #NAME? | E102: UPAH | F102: DMO | G102: Ulfa | H102: APRIL | I102: 664205364 | J102: PAID | K102: PERSADA | L102: MONTHLY | N102: 2026
C103: PS-047-00 | D103: {=_xlfn.XLOOKUP(Tabel2[[#This Row],[KODE PROJECT]], _xlfn.VSTACK('KODE PROJECT BARU'!$B$5:$B$98, 'KODE PROJECT BARU'!$C$5:$C$98), _xlfn.VSTACK('KODE PROJECT BARU'!$E$5:$E$98, 'KODE PROJECT BARU'!$E$5:$E$98), "Tidak Ditemukan", 0, 1)} -> #NAME? | E103: UPAH | F103: DMO | G103: Ulfa | H103: APRIL | I103: 178204573 | J103: PAID | K103: PERSADA | L103: MONTHLY | N103: 2026
C104: PS-019-00 | D104: {=_xlfn.XLOOKUP(Tabel2[[#This Row],[KODE PROJECT]], _xlfn.VSTACK('KODE PROJECT BARU'!$B$5:$B$98, 'KODE PROJECT BARU'!$C$5:$C$98), _xlfn.VSTACK('KODE PROJECT BARU'!$E$5:$E$98, 'KODE PROJECT BARU'!$E$5:$E$98), "Tidak Ditemukan", 0, 1)} -> #NAME? | E104: UPAH | F104: DMO | G104: Ulfa | H104: APRIL | I104: 27622955 | J104: PAID | K104: PERSADA | L104: MONTHLY | N104: 2026
C105: PS-028-00 | D105: {=_xlfn.XLOOKUP(Tabel2[[#This Row],[KODE PROJECT]], _xlfn.VSTACK('KODE PROJECT BARU'!$B$5:$B$98, 'KODE PROJECT BARU'!$C$5:$C$98), _xlfn.VSTACK('KODE PROJECT BARU'!$E$5:$E$98, 'KODE PROJECT BARU'!$E$5:$E$98), "Tidak Ditemukan", 0, 1)} -> #NAME? | E105: UPAH | F105: DMO | G105: Ulfa | H105: APRIL | I105: 10625465 | J105: PAID | K105: PERSADA | L105: MONTHLY | N105: 2026
C106: PS-034-00 | D106: {=_xlfn.XLOOKUP(Tabel2[[#This Row],[KODE PROJECT]], _xlfn.VSTACK('KODE PROJECT BARU'!$B$5:$B$98, 'KODE PROJECT BARU'!$C$5:$C$98), _xlfn.VSTACK('KODE PROJECT BARU'!$E$5:$E$98, 'KODE PROJECT BARU'!$E$5:$E$98), "Tidak Ditemukan", 0, 1)} -> #NAME? | E106: UPAH | F106: DMO | G106: Ulfa | H106: APRIL | I106: 29492295 | J106: PAID | K106: PERSADA | L106: MONTHLY | N106: 2026
C107: PS-018-00 | D107: {=_xlfn.XLOOKUP(Tabel2[[#This Row],[KODE PROJECT]], _xlfn.VSTACK('KODE PROJECT BARU'!$B$5:$B$98, 'KODE PROJECT BARU'!$C$5:$C$98), _xlfn.VSTACK('KODE PROJECT BARU'!$E$5:$E$98, 'KODE PROJECT BARU'!$E$5:$E$98), "Tidak Ditemukan", 0, 1)} -> #NAME? | E107: UPAH | F107: DMO | G107: Ulfa | H107: APRIL | I107: 332569153 | J107: PAID | K107: PERSADA | L107: MONTHLY | N107: 2026
C108: PS-004-00 | D108: {=_xlfn.XLOOKUP(Tabel2[[#This Row],[KODE PROJECT]], _xlfn.VSTACK('KODE PROJECT BARU'!$B$5:$B$98, 'KODE PROJECT BARU'!$C$5:$C$98), _xlfn.VSTACK('KODE PROJECT BARU'!$E$5:$E$98, 'KODE PROJECT BARU'!$E$5:$E$98), "Tidak Ditemukan", 0, 1)} -> #NAME? | E108: UPAH | F108: DMO | G108: Ulfa | H108: APRIL | I108: 630997314 | J108: PAID | K108: PERSADA | L108: MONTHLY | N108: 2026
C109: PS-004-00 | D109: {=_xlfn.XLOOKUP(Tabel2[[#This Row],[KODE PROJECT]], _xlfn.VSTACK('KODE PROJECT BARU'!$B$5:$B$98, 'KODE PROJECT BARU'!$C$5:$C$98), _xlfn.VSTACK('KODE PROJECT BARU'!$E$5:$E$98, 'KODE PROJECT BARU'!$E$5:$E$98), "Tidak Ditemukan", 0, 1)} -> #NAME? | E109: UPAH | F109: DMO | G109: Ulfa | H109: APRIL | I109: 16698993 | J109: PAID | K109: PERSADA | L109: MONTHLY | N109: 2026
C110: PS-020-00 | D110: {=_xlfn.XLOOKUP(Tabel2[[#This Row],[KODE PROJECT]], _xlfn.VSTACK('KODE PROJECT BARU'!$B$5:$B$98, 'KODE PROJECT BARU'!$C$5:$C$98), _xlfn.VSTACK('KODE PROJECT BARU'!$E$5:$E$98, 'KODE PROJECT BARU'!$E$5:$E$98), "Tidak Ditemukan", 0, 1)} -> #NAME? | E110: UPAH | F110: DMO | G110: Ulfa | H110: APRIL | I110: 184474531 | J110: PAID | K110: PERSADA | L110: MONTHLY | N110: 2026
C111: PS-060-00 | D111: {=_xlfn.XLOOKUP(Tabel2[[#This Row],[KODE PROJECT]], _xlfn.VSTACK('KODE PROJECT BARU'!$B$5:$B$98, 'KODE PROJECT BARU'!$C$5:$C$98), _xlfn.VSTACK('KODE PROJECT BARU'!$E$5:$E$98, 'KODE PROJECT BARU'!$E$5:$E$98), "Tidak Ditemukan", 0, 1)} -> #NAME? | E111: UPAH | F111: DMO | G111: Ulfa | H111: APRIL | I111: 17675779 | J111: PAID | K111: PERSADA | L111: MONTHLY | N111: 2026
... C124: PS-004-00 | D124: {=_xlfn.XLOOKUP(Tabel2[[#This Row],[KODE PROJECT]], _xlfn.VSTACK('KODE PROJECT BARU'!$B$5:$B$98, 'KODE PROJECT BARU'!$C$5:$C$98), _xlfn.VSTACK('KODE PROJECT BARU'!$E$5:$E$98, 'KODE PROJECT BARU'!$E$5:$E$98), "Tidak Ditemukan", 0, 1)} -> #NAME? | E124: SUPLISI | F124: DMO | G124: Ulfa | H124: APRIL | I124: 56451485 | J124: PAID | K124: PERSADA | L124: OTC | N124: 2026
C125: PS-024-00 | D125: {=_xlfn.XLOOKUP(Tabel2[[#This Row],[KODE PROJECT]], _xlfn.VSTACK('KODE PROJECT BARU'!$B$5:$B$98, 'KODE PROJECT BARU'!$C$5:$C$98), _xlfn.VSTACK('KODE PROJECT BARU'!$E$5:$E$98, 'KODE PROJECT BARU'!$E$5:$E$98), "Tidak Ditemukan", 0, 1)} -> #NAME? | E125: UPAH | F125: DMO | G125: Ulfa | H125: MEI | I125: =892197835+42383653 -> 934581488 | J125: PAID | K125: PERSADA | L125: MONTHLY | N125: 2026
C126: PS-023-00 | D126: {=_xlfn.XLOOKUP(Tabel2[[#This Row],[KODE PROJECT]], _xlfn.VSTACK('KODE PROJECT BARU'!$B$5:$B$98, 'KODE PROJECT BARU'!$C$5:$C$98), _xlfn.VSTACK('KODE PROJECT BARU'!$E$5:$E$98, 'KODE PROJECT BARU'!$E$5:$E$98), "Tidak Ditemukan", 0, 1)} -> #NAME? | E126: UPAH | F126: DMO | G126: Ulfa | H126: MEI | I126: =664205364-4853398 -> 659351966 | J126: PAID | K126: PERSADA | L126: MONTHLY | N126: 2026
C127: PS-047-00 | D127: {=_xlfn.XLOOKUP(Tabel2[[#This Row],[KODE PROJECT]], _xlfn.VSTACK('KODE PROJECT BARU'!$B$5:$B$98, 'KODE PROJECT BARU'!$C$5:$C$98), _xlfn.VSTACK('KODE PROJECT BARU'!$E$5:$E$98, 'KODE PROJECT BARU'!$E$5:$E$98), "Tidak Ditemukan", 0, 1)} -> #NAME? | E127: UPAH | F127: DMO | G127: Ulfa | H127: MEI | I127: =178204573+24875160 -> 203079733 | J127: PAID | K127: PERSADA | L127: MONTHLY | N127: 2026
C128: PS-019-00 | D128: {=_xlfn.XLOOKUP(Tabel2[[#This Row],[KODE PROJECT]], _xlfn.VSTACK('KODE PROJECT BARU'!$B$5:$B$98, 'KODE PROJECT BARU'!$C$5:$C$98), _xlfn.VSTACK('KODE PROJECT BARU'!$E$5:$E$98, 'KODE PROJECT BARU'!$E$5:$E$98), "Tidak Ditemukan", 0, 1)} -> #NAME? | E128: UPAH | F128: DMO | G128: Ulfa | H128: MEI | I128: =27622955-1674454 -> 25948501 | J128: PAID | K128: PERSADA | L128: MONTHLY | N128: 2026
C129: PS-028-00 | D129: {=_xlfn.XLOOKUP(Tabel2[[#This Row],[KODE PROJECT]], _xlfn.VSTACK('KODE PROJECT BARU'!$B$5:$B$98, 'KODE PROJECT BARU'!$C$5:$C$98), _xlfn.VSTACK('KODE PROJECT BARU'!$E$5:$E$98, 'KODE PROJECT BARU'!$E$5:$E$98), "Tidak Ditemukan", 0, 1)} -> #NAME? | E129: UPAH | F129: DMO | G129: Ulfa | H129: MEI | I129: =10625465+2890135 -> 13515600 | J129: PAID | K129: PERSADA | L129: MONTHLY | N129: 2026
C130: PS-034-00 | D130: {=_xlfn.XLOOKUP(Tabel2[[#This Row],[KODE PROJECT]], _xlfn.VSTACK('KODE PROJECT BARU'!$B$5:$B$98, 'KODE PROJECT BARU'!$C$5:$C$98), _xlfn.VSTACK('KODE PROJECT BARU'!$E$5:$E$98, 'KODE PROJECT BARU'!$E$5:$E$98), "Tidak Ditemukan", 0, 1)} -> #NAME? | E130: UPAH | F130: DMO | G130: Ulfa | H130: MEI | I130: =29492295-1066216 -> 28426079 | J130: PAID | K130: PERSADA | L130: MONTHLY | N130: 2026
C131: PS-018-00 | D131: {=_xlfn.XLOOKUP(Tabel2[[#This Row],[KODE PROJECT]], _xlfn.VSTACK('KODE PROJECT BARU'!$B$5:$B$98, 'KODE PROJECT BARU'!$C$5:$C$98), _xlfn.VSTACK('KODE PROJECT BARU'!$E$5:$E$98, 'KODE PROJECT BARU'!$E$5:$E$98), "Tidak Ditemukan", 0, 1)} -> #NAME? | E131: UPAH | F131: DMO | G131: Ulfa | H131: MEI | I131: =338125868-16601621 -> 321524247 | J131: PAID | K131: PERSADA | L131: MONTHLY | N131: 2026
...

Sheet Lembar1
B2: Project implementasi, perlu direview
B3: Project_ID | C3: Year | D3: Status | E3: Service Manager | F3: Project_client | G3: Project clasification | H3: Project Name | I3: Contract Number | J3: Category Contract | L3: Date of Contract | M3: Start Date | N3: End Date | O3: Project_Value | P3: Costbased | Q3: Actual Cost konfirmasi | R3: Actual cost (admin) | S3: Persentase | T3: Amandemen | U3: TKDN | V3: Description
C4: TBC | D4: =IF(M4>TODAY(),"FUTURE",IF(N4>TODAY(),"ON GOING","CLOSED")) -> ON GOING | F4: PT Transportasi Gas Indonesia | G4: OTC | H4: Pengadaan Firewall Amandemen Perjanjian Pengadaan Link Metro Ethemet Dan Colocation Data Center Utama PT Transportasi Gas Indonesia | I4: 1SVC-043866 | J4: Kontrak Tunggal | L4: 45196 | M4: 45200 | N4: 46752 | O4: 3981371124 | P4: TBC | T4: Amandemen 1 1SVC-043946; Amandemen II 1SVC-044712 | U4: TBC
H5: Implementasi Identity Provide (IPA) for Server Dalam Lingkup Pekerjaan MSTI PGN Tahun 2026
H6: Jasa Interfacing Data SCADA ke Aplikasi GAS Management System (GMS)
H7: Jasa Pembuatan Sistem Data Kinerja PGN SOR III
H8: Jasa Pemeliharaan Aplikasi HSSE Online System and Indicator Performance Center (HOLISTIC)
H9: Jasa Pengelolaan Dashboard PSAIMS & HSSE Frontliner System
H10: PEKERJAAN INSTALASI RADIO MICROWAVE ADDITIONAL PHE NSO
H11: Pekerjaan Interfacing Data Scada Ke Aplikasi GMS PT Nusantara Regas
H12: Pekerjaan Pengelolaan Limbah B3 Baterai PJOPTGMS – PGN GSOR III
H13: Pengadaan Pembangunan SIPGAS EM Fungsi Monitoring Komunikasi CRM Tahun 2024
H14: Pengembangan dan Peningkatan Kapabilitas Aplikasi ENERGY (Enterprise Revenue Generation System)
H15: Delivery Pekerjaan Jasa Maintenance Perbaikan 5 Unit Perangkat Disk Network Attached Storage (NAS) RU5 Balikpapan KPI
H16: FID Perbaikan dan Relokasi kabel RO Bekasi, Jakarta dan Batam
... H56: Upgrade Metro Ethernet Jakarta-Singapura 2025

Sheet RAW DATA
G1: =SUBTOTAL(3,G3:G239) -> 144
A2: Project_ID | B2: Year | C2: Status | D2: Service Manager | E2: Project_client | F2: Project clasification | G2: Project Name | H2: Contract Number | I2: Category Contract | J2: Skema | K2: Date of Contract | L2: Start Date | M2: End Date | N2: Project_Value | O2: Costbased | P2: Actual Cost konfirmasi | Q2: Actual cost (admin) | R2: Persentase | S2: Amandemen | T2: TKDN | U2: Description | V2: Resource Management
A3: BS-005 | B3: =YEAR(tProjectsMaster212[[#This Row],[End Date]]) -> 2025 | C3: =IF(L3>TODAY(),"FUTURE",IF(M3>TODAY(),"ON GOING","CLOSED")) -> CLOSED | D3: TITA | E3: SAKA | F3: MRC | G3: Pengadaan Sewa Aplikasi Absensi Online (Bimasakti) | H3: 4500615890 | I3: Kontrak Tunggal | J3: Back2Back | K3: 45748 | L3: 45736 | M3: 46022 | N3: =39000000*(9/12) -> 29250000 | O3: 24000000 | P3: 0 | R3: =tProjectsMaster212[[#This Row],[Actual cost (admin)]]/tProjectsMaster212[[#This Row],[Costbased]] -> 0
A4: BS-005 | B4: =YEAR(tProjectsMaster212[[#This Row],[End Date]]) -> 2026 | C4: =IF(L4>TODAY(),"FUTURE",IF(M4>TODAY(),"ON GOING","CLOSED")) -> CLOSED | D4: TITA | E4: SAKA | F4: MRC | G4: Pengadaan Sewa Aplikasi Absensi Online (Bimasakti) | H4: 4500615890 | I4: Kontrak Tunggal | J4: Back2Back | K4: 45748 | L4: 46023 | M4: 46100 | N4: =39000000*(3/12) -> 9750000 | O4: 0 | P4: 24000000 | Q4: =SUMIF('REALISASI 2026'!$C$7:$C$1048576,tProjectsMaster212[[#This Row],[Project_ID]],'REALISASI 2026'!$I$7:$I$1048576) -> 0 | R4: =tProjectsMaster212[[#This Row],[Actual cost (admin)]]/tProjectsMaster212[[#This Row],[Costbased]] -> #DIV/0!
A5: MS-016 | B5: =YEAR(tProjectsMaster212[[#This Row],[End Date]]) -> 2025 | C5: =IF(L5>TODAY(),"FUTURE",IF(M5>TODAY(),"ON GOING","CLOSED")) -> CLOSED | D5: TITA | E5: GGS | F5: MRC | G5: Pengadaan Sewa Aplikasi Absensi Online (Bimasakti) 80 user | H5: 034102.SPK/LG.01/GEI-32/2025 | I5: Kontrak Tunggal | J5: Back2Back | K5: 45933 | L5: 45933 | M5: 46022 | N5: 13056000 | O5: 0 | P5: 0 | R5: =tProjectsMaster212[[#This Row],[Actual cost (admin)]]/tProjectsMaster212[[#This Row],[Costbased]] -> #DIV/0!
A6: MS-016 | B6: =YEAR(tProjectsMaster212[[#This Row],[End Date]]) -> 2026 | C6: =IF(L6>TODAY(),"FUTURE",IF(M6>TODAY(),"ON GOING","CLOSED")) -> ON GOING | D6: TITA | E6: GGS | F6: MRC | G6: Pengadaan Sewa Aplikasi Absensi Online (Bimasakti) 80 user | H6: 034102.SPK/LG.01/GEI-32/2025 | I6: Kontrak Tunggal | J6: Back2Back | K6: 45933 | L6: 46023 | M6: 46387 | N6: 0 | O6: 7680000 | P6: =(4000*80)*24 -> 7680000 | Q6: =SUMIF('REALISASI 2026'!$C$7:$C$1048576,tProjectsMaster212[[#This Row],[Project_ID]],'REALISASI 2026'!$I$7:$I$1048576) -> 0 | R6: =tProjectsMaster212[[#This Row],[Actual cost (admin)]]/tProjectsMaster212[[#This Row],[Costbased]] -> 0
A7: MS-016 | B7: =YEAR(tProjectsMaster212[[#This Row],[End Date]]) -> 2027 | C7: =IF(L7>TODAY(),"FUTURE",IF(M7>TODAY(),"ON GOING","CLOSED")) -> FUTURE | D7: TITA | E7: GGS | F7: MRC | G7: Pengadaan Sewa Aplikasi Absensi Online (Bimasakti) 80 user | H7: 034102.SPK/LG.01/GEI-32/2025 | I7: Kontrak Tunggal | J7: Back2Back | K7: 45933 | L7: 46388 | M7: 46662 | N7: 0 | O7: 0 | P7: 0 | R7: =tProjectsMaster212[[#This Row],[Actual cost (admin)]]/tProjectsMaster212[[#This Row],[Costbased]] -> #DIV/0!
A8: MS-019 | B8: =YEAR(tProjectsMaster212[[#This Row],[End Date]]) -> 2025 | C8: =IF(L8>TODAY(),"FUTURE",IF(M8>TODAY(),"ON GOING","CLOSED")) -> CLOSED | D8: SANDI | E8: PLI | F8: MRC | G8: Jasa Pemeliharaan Sistem Kontrol dan Telekomunikasi Offtake Station (OTS) & Onshore Receiving Facilities (ORF) 2025-2026 | H8: 00500.PKS/HK/PGNCOM/IV/2025 | I8: Kontrak Tunggal | J8: Inhouse | K8: 45719 | L8: 45748 | M8: 46022 | N8: =1820040000*(9/12) -> 1365030000 | O8: =(1096817412/12)*8 -> 731211608 | R8: =tProjectsMaster212[[#This Row],[Actual cost (admin)]]/tProjectsMaster212[[#This Row],[Costbased]] -> 0 | T8: 0.79
A9: MS-019 | B9: =YEAR(tProjectsMaster212[[#This Row],[End Date]]) -> 2026 | C9: =IF(L9>TODAY(),"FUTURE",IF(M9>TODAY(),"ON GOING","CLOSED")) -> CLOSED | D9: SANDI | E9: PLI | F9: MRC | G9: Jasa Pemeliharaan Sistem Kontrol dan Telekomunikasi Offtake Station (OTS) & Onshore Receiving Facilities (ORF) 2025-2026 | H9: 00500.PKS/HK/PGNCOM/IV/2025 | I9: Kontrak Tunggal | J9: Inhouse | K9: 45719 | L9: 46023 | M9: 46112 | N9: =1820040000*(3/12) -> 455010000 | O9: =(1096817412/12)*4 -> 365605804 | Q9: =SUMIF('REALISASI 2026'!$C$7:$C$1048576,tProjectsMaster212[[#This Row],[Project_ID]],'REALISASI 2026'!$I$7:$I$1048576) -> 2.1974252e+08 | R9: =tProjectsMaster212[[#This Row],[Actual cost (admin)]]/tProjectsMaster212[[#This Row],[Costbased]] -> 0.60103674 | T9: 0.79
A10: MS-020 | B10: =YEAR(tProjectsMaster212[[#This Row],[End Date]]) -> 2023 | C10: =IF(L10>TODAY(),"FUTURE",IF(M10>TODAY(),"ON GOING","CLOSED")) -> CLOSED | D10: TAUFAN | E10: NR | F10: MRC | G10: Jasa Layanan Radio Komunikasi - Trunking | H10: 004/NR/B000/P/2023 | I10: Kontrak Tunggal | J10: Inhouse | K10: 45054 | L10: 45017 | M10: 45291 | N10: =9/12*355584000 -> 266688000 | O10: =9/12*296184156 -> 222138117 | R10: =tProjectsMaster212[[#This Row],[Actual cost (admin)]]/tProjectsMaster212[[#This Row],[Costbased]] -> 0 | S10: Adendum I (1 April 2025) | U10: 1. Awal : 355.584.000 2. Perpanjangan-1 : 336.120.000 3. Perpanjangan-2 : 295.440.000
A11: MS-020 | B11: =YEAR(tProjectsMaster212[[#This Row],[End Date]]) -> 2024 | C11: =IF(L11>TODAY(),"FUTURE",IF(M11>TODAY(),"ON GOING","CLOSED")) -> CLOSED | D11: TAUFAN | E11: NR | F11: MRC | G11: Jasa Layanan Radio Komunikasi - Trunking | H11: 004/NR/B000/P/2023 | I11: Kontrak Tunggal | J11: Inhouse | K11: 45054 | L11: 45292 | M11: 45657 | N11: =(3/12*355584000)+(9/12*336120000) -> 340986000 | O11: 296184156 | R11: =tProjectsMaster212[[#This Row],[Actual cost (admin)]]/tProjectsMaster212[[#This Row],[Costbased]] -> 0 | S11: Adendum I (1 April 2025) | U11: 1. Awal : 355.584.000 2. Perpanjangan-1 : 336.120.000 3. Perpanjangan-2 : 295.440.000
A12: MS-020 | B12: =YEAR(tProjectsMaster212[[#This Row],[End Date]]) -> 2025 | C12: =IF(L12>TODAY(),"FUTURE",IF(M12>TODAY(),"ON GOING","CLOSED")) -> CLOSED | D12: TAUFAN | E12: NR | F12: MRC | G12: Jasa Layanan Radio Komunikasi - Trunking | H12: 004/NR/B000/P/2023 | I12: Kontrak Tunggal | J12: Inhouse | K12: 45054 | L12: 45658 | M12: 46022 | N12: =(3/12*336120000)+(9/12*295440000) -> 305610000 | O12: =(3/12*((18*608243)+(22*555320)+(3*505533)))+(9/12*((14*608243)+(22*555320)+(2*505533))) -> 22478134 | R12: =tProjectsMaster212[[#This Row],[Actual cost (admin)]]/tProjectsMaster212[[#This Row],[Costbased]] -> 0 | S12: Adendum I (1 April 2025) | U12: 1. Awal : 355.584.000 2. Perpanjangan-1 : 336.120.000 3. Perpanjangan-2 : 295.440.000
A13: MS-020 | B13: =YEAR(tProjectsMaster212[[#This Row],[End Date]]) -> 2026 | C13: =IF(L13>TODAY(),"FUTURE",IF(M13>TODAY(),"ON GOING","CLOSED")) -> CLOSED | D13: TAUFAN | E13: NR | F13: MRC | G13: Jasa Layanan Radio Komunikasi - Trunking | H13: 004/NR/B000/P/2023 | I13: Kontrak Tunggal | J13: Inhouse | K13: 45054 | L13: 46023 | M13: 46112 | N13: =3/12*295440000 -> 73860000 | O13: =3/12*((14*608243)+(22*555320)+(2*505533)) -> 5435877 | Q13: =SUMIF('REALISASI 2026'!$C$7:$C$1048576,tProjectsMaster212[[#This Row],[Project_ID]],'REALISASI 2026'!$I$7:$I$1048576) -> 33696039 | R13: =tProjectsMaster212[[#This Row],[Actual cost (admin)]]/tProjectsMaster212[[#This Row],[Costbased]] -> 6.1988229 | S13: Adendum I (1 April 2025) | U13: 1. Awal : 355.584.000 2. Perpanjangan-1 : 336.120.000 3. Perpanjangan-2 : 295.440.000
A14: MS-044 | B14: =YEAR(tProjectsMaster212[[#This Row],[End Date]]) -> 2024 | C14: =IF(L14>TODAY(),"FUTURE",IF(M14>TODAY(),"ON GOING","CLOSED")) -> CLOSED | D14: GILANG | E14: PTM | F14: MRC | G14: Penyediaan Layanan Platform Pilot Aplikasi Modern | H14: 3950379274 | I14: Kontrak Tunggal | J14: Back2Back | K14: 45607 | L14: 45607 | M14: 45657 | N14: =2/18*4994758480 -> 5.5497316e+08 | O14: =2/18*4848359566 -> 5.3870662e+08 | R14: =tProjectsMaster212[[#This Row],[Actual cost (admin)]]/tProjectsMaster212[[#This Row],[Costbased]] -> 0 | S14: BA-55/I40520/2025-S0 (Amandemen) 14 Juli 2025 | T14: 0.1119
A15: MS-044 | B15: =YEAR(tProjectsMaster212[[#This Row],[End Date]]) -> 2025 | C15: =IF(L15>TODAY(),"FUTURE",IF(M15>TODAY(),"ON GOING","CLOSED")) -> CLOSED | D15: GILANG | E15: PTM | F15: MRC | G15: Penyediaan Layanan Platform Pilot Aplikasi Modern | H15: 3950379274 | I15: Kontrak Tunggal | J15: Back2Back | K15: 45607 | L15: 45658 | M15: 46022 | N15: =12/18*4994758480 -> 3.329839e+09 | O15: =12/18*4848359566 -> 3.2322397e+09 | R15: =tProjectsMaster212[[#This Row],[Actual cost (admin)]]/tProjectsMaster212[[#This Row],[Costbased]] -> 0 | S15: BA-55/I40520/2025-S0 (Amandemen) 14 Juli 2025 | T15: 0.1119
A16: MS-044 | B16: =YEAR(tProjectsMaster212[[#This Row],[End Date]]) -> 2026 | C16: =IF(L16>TODAY(),"FUTURE",IF(M16>TODAY(),"ON GOING","CLOSED")) -> CLOSED | D16: GILANG | E16: PTM | F16: MRC | G16: Penyediaan Layanan Platform Pilot Aplikasi Modern | H16: 3950379274 | I16: Kontrak Tunggal | J16: Back2Back | K16: 45607 | L16: 46023 | M16: 46153 | N16: =4/18*4994758480 -> 1.1099463e+09 | O16: =4/18*4848359566 -> 1.0774132e+09 | P16: =SUMIF('REALISASI 2026'!$C$7:$C$1048576,tProjectsMaster212[[#This Row],[Project_ID]],'REALISASI 2026'!$I$7:$I$1048576) -> 0 | Q16: =SUMIF('REALISASI 2026'!$C$7:$C$1048576,tProjectsMaster212[[#This Row],[Project_ID]],'REALISASI 2026'!$I$7:$I$1048576) -> 0 | R16: =tProjectsMaster212[[#This Row],[Actual cost (admin)]]/tProjectsMaster212[[#This Row],[Costbased]] -> 0 | S16: BA-55/I40520/2025-S0 (Amandemen) 14 Juli 2025 | T16: 0.1119
A17: MS-047 | B17: =YEAR(tProjectsMaster212[[#This Row],[End Date]]) -> 2025 | C17: =IF(L17>TODAY(),"FUTURE",IF(M17>TODAY(),"ON GOING","CLOSED")) -> CLOSED | E17: PGN | F17: WO | G17: Layanan Pengelolaan Aplikasi dan Solusi Integrasi Tahun 2025 | H17: 004200.PK/LG.01/ICT/ 2025 | I17: kontrak Induk | J17: Inhouse | K17: 45706 | L17: 45658 | M17: 46022 | N17: 8449020551 | O17: 7.790854e+09 | P17: 6.2040173e+09 | R17: =tProjectsMaster212[[#This Row],[Actual cost (admin)]]/tProjectsMaster212[[#This Row],[Costbased]] -> 0 | T17: 72,84%
A18: MS-081 | B18: =YEAR(tProjectsMaster212[[#This Row],[End Date]]) -> 2025 | C18: =IF(L18>TODAY(),"FUTURE",IF(M18>TODAY(),"ON GOING","CLOSED")) -> CLOSED | D18: SANDI | E18: PPN | F18: MRC | G18: Pekerjaan Sewa Router Untuk Layanan Dual Link SPBU | H18: VSO-2025-11-24-118411264/470012416 | I18: Kontrak Tunggal | J18: Back2Back | K18: 45985 | L18: 45992 | M18: 46022 | N18: =190000000*2 -> 380000000 | O18: 0 | P18: 0 | R18: =tProjectsMaster212[[#This Row],[Actual cost (admin)]]/tProjectsMaster212[[#This Row],[Costbased]] -> #DIV/0!
A19: MS-081 | B19: =YEAR(tProjectsMaster212[[#This Row],[End Date]]) -> 2026 | C19: =IF(L19>TODAY(),"FUTURE",IF(M19>TODAY(),"ON GOING","CLOSED")) -> CLOSED | D19: SANDI | E19: PPN | F19: MRC | G19: Pekerjaan Sewa Router Untuk Layanan Dual Link SPBU | H19: VSO-2025-11-24-118411264/470012416 | I19: Kontrak Tunggal | J19: Back2Back | K19: 45985 | L19: 46023 | M19: 46173 | N19: 0 | O19: 336000000 | P19: =SUMIF('REALISASI 2026'!$C$7:$C$1048576,tProjectsMaster212[[#This Row],[Project_ID]],'REALISASI 2026'!$I$7:$I$1048576) -> 0 | Q19: 297000000 | R19: =tProjectsMaster212[[#This Row],[Actual cost (admin)]]/tProjectsMaster212[[#This Row],[Costbased]] -> 0.88392857
A20: MS-115 | B20: =YEAR(tProjectsMaster212[[#This Row],[End Date]]) -> 2026 | C20: =IF(L20>TODAY(),"FUTURE",IF(M20>TODAY(),"ON GOING","CLOSED")) -> CLOSED | E20: PPN | F20: OTC | G20: Pekerjaan Maintenance CCTV & Infrastruktur PPN MOR1 FT Labuhan Deli | H20: VSO-2026-01-08-043538948; VSO-2026-01-08-721977675 | I20: Kontrak Tunggal | J20: Inhouse | K20: 46030 | L20: 46030 | M20: 46073 | N20: =157306838+120715256 -> 278022094 | O20: 228713674 | Q20: =SUMIF('REALISASI 2026'!$C$7:$C$1048576,tProjectsMaster212[[#This Row],[Project_ID]],'REALISASI 2026'!$I$7:$I$1048576) -> 93475716 | R20: =tProjectsMaster212[[#This Row],[Actual cost (admin)]]/tProjectsMaster212[[#This Row],[Costbased]] -> 0.40870191
A21: MS-117 | B21: =YEAR(tProjectsMaster212[[#This Row],[End Date]]) -> 2026 | C21: =IF(L21>TODAY(),"FUTURE",IF(M21>TODAY(),"ON GOING","CLOSED")) -> ON GOING | E21: SEML | F21: OTC | G21: Provision of Document Management System ATS Muara Laboh | H21: 25000226-OS-10101 | I21: Kontrak Tunggal | K21: TBC | L21: 46023 | M21: 46387 | N21: 311400178 | O21: 292835553 | Q21: =SUMIF('REALISASI 2026'!$C$7:$C$1048576,tProjectsMaster212[[#This Row],[Project_ID]],'REALISASI 2026'!$I$7:$I$1048576) -> 478000000 | R21: =tProjectsMaster212[[#This Row],[Actual cost (admin)]]/tProjectsMaster212[[#This Row],[Costbased]] -> 1.6323155 | T21: 0.3119
A22: MS-118 | B22: =YEAR(tProjectsMaster212[[#This Row],[End Date]]) -> 2026 | C22: =IF(L22>TODAY(),"FUTURE",IF(M22>TODAY(),"ON GOING","CLOSED")) -> ON GOING | E22: SERD | F22: OTC | G22: Provision of Document Management System ATS Rantau Dedap | H22: 25000109-OS-10103 | I22: Kontrak Tunggal | K22: TBC | L22: 46023 | M22: 46387 | N22: 2.0675773e+08 | O22: 195054463 | Q22: =SUMIF('REALISASI 2026'!$C$7:$C$1048576,tProjectsMaster212[[#This Row],[Project_ID]],'REALISASI 2026'!$I$7:$I$1048576) -> 0 | R22: =tProjectsMaster212[[#This Row],[Actual cost (admin)]]/tProjectsMaster212[[#This Row],[Costbased]] -> 0 | T22: 0.321
A23: MS-119 | B23: =YEAR(tProjectsMaster212[[#This Row],[End Date]]) -> 2026 | C23: =IF(L23>TODAY(),"FUTURE",IF(M23>TODAY(),"ON GOING","CLOSED")) -> CLOSED | E23: ESA | F23: OTC | G23: Pekerjaan BER Test DC Kemendagri | H23: 080/ESTRADA/WO/IV/2026 | I23: Kontrak Tunggal | J23: Inhouse | K23: 46136 | L23: 46147 | M23: 46149 | N23: 45045045 | O23: 11500000 | Q23: =SUMIF('REALISASI 2026'!$C$7:$C$1048576,tProjectsMaster212[[#This Row],[Project_ID]],'REALISASI 2026'!$I$7:$I$1048576) -> 0 | R23: =tProjectsMaster212[[#This Row],[Actual cost (admin)]]/tProjectsMaster212[[#This Row],[Costbased]] -> 0
A24: MS-121 | B24: =YEAR(tProjectsMaster212[[#This Row],[End Date]]) -> 2026 | C24: =IF(L24>TODAY(),"FUTURE",IF(M24>TODAY(),"ON GOING","CLOSED")) -> CLOSED | E24: KPI | F24: OTC | G24: Jasa Pendampingan Surveillance Sertifikasi ISO/IEC 27001:2022 di PT KPI | H24: SP-02/KPI72200/2025-SO 3950463946 | I24: Kontrak Tunggal | J24: Inhouse | K24: 45985 | L24: 45985 | M24: 46199 | N24: 933118522 | O24: 861775435 | Q24: =SUMIF('REALISASI 2026'!$C$7:$C$1048576,tProjectsMaster212[[#This Row],[Project_ID]],'REALISASI 2026'!$I$7:$I$1048576) -> 420742500 | R24: =tProjectsMaster212[[#This Row],[Actual cost (admin)]]/tProjectsMaster212[[#This Row],[Costbased]] -> 0.48822754
A25: PS-000-00 | B25: =YEAR(tProjectsMaster212[[#This Row],[End Date]]) -> 2026 | C25: =IF(L25>TODAY(),"FUTURE",IF(M25>TODAY(),"ON GOING","CLOSED")) -> CLOSED | D25: RIZKY | E25: PLI | F25: OTC | G25: Pengadaan CCTV PT PGN LNG | H25: - | I25: Kontrak Tunggal | J25: Inhouse | K25: 46112 | L25: 46112 | M25: 46132 | N25: 58000000 | O25: 51875534 | P25: =SUMIF('REALISASI 2026'!$C$7:$C$1048576,tProjectsMaster212[[#This Row],[Project_ID]],'REALISASI 2026'!$I$7:$I$1048576) -> 42402648 | Q25: =SUMIF('REALISASI 2026'!$C$7:$C$1048576,tProjectsMaster212[[#This Row],[Project_ID]],'REALISASI 2026'!$I$7:$I$1048576) -> 42402648 | R25: =tProjectsMaster212[[#This Row],[Actual cost (admin)]]/tProjectsMaster212[[#This Row],[Costbased]] -> 0.81739203 | U25: Tidak ada PO. Pakai Surat penawaran. Beli putus
A26: PS-001-00 | B26: =YEAR(tProjectsMaster212[[#This Row],[End Date]]) -> 2022 | C26: =IF(L26>TODAY(),"FUTURE",IF(M26>TODAY(),"ON GOING","CLOSED")) -> CLOSED | D26: SANDI | E26: PTG | F26: MRC | G26: Manage Service Layanan Printer, Scanner, Multimedia dan UPS System di PT Pertamina Gas | H26: 3900524630 | I26: Kontrak Tunggal | J26: Back2Back | K26: 44866 | L26: 44866 | M26: 44926 | N26: =(419732500+89430000+76481636+641937420)*(2/7) -> 3.5073759e+08 | O26: =(506039000+73387500+75089771+642740600)*(2/7) -> 3.7064482e+08 | R26: =tProjectsMaster212[[#This Row],[Actual cost (admin)]]/tProjectsMaster212[[#This Row],[Costbased]] -> 0
A27: PS-001-00 | B27: =YEAR(tProjectsMaster212[[#This Row],[End Date]]) -> 2023 | C27: =IF(L27>TODAY(),"FUTURE",IF(M27>TODAY(),"ON GOING","CLOSED")) -> CLOSED | D27: SANDI | E27: PTG | F27: MRC | G27: Manage Service Layanan Printer, Scanner, Multimedia dan UPS System di PT Pertamina Gas | H27: 3900524630 | I27: Kontrak Tunggal | J27: Back2Back | K27: 44866 | L27: 44927 | M27: 45291 | N27: =((419732500+89430000+76481636+641937420)*(5/7))+(3971003091*(7/36)) -> 1.6489835e+09 | O27: =((506039000+73387500+75089771+642740600)*(5/7))+((3454954006/36)*7) -> 1.5984087e+09 | P27: =1158222690+425108449 -> 1583331139 | R27: =tProjectsMaster212[[#This Row],[Actual cost (admin)]]/tProjectsMaster212[[#This Row],[Costbased]] -> 0 | S27: Amandemen I No 3900524630 - A1 15 Mei 2023 Amandemen II No 3900524630 - A2 30 November 2023
A28: PS-001-00 | B28: =YEAR(tProjectsMaster212[[#This Row],[End Date]]) -> 2024 | C28: =IF(L28>TODAY(),"FUTURE",IF(M28>TODAY(),"ON GOING","CLOSED")) -> CLOSED | D28: SANDI | E28: PTG | F28: MRC | G28: Manage Service Layanan Printer, Scanner, Multimedia dan UPS System di PT Pertamina Gas | H28: 3900524630 | I28: Kontrak Tunggal | J28: Back2Back | K28: 44866 | L28: 45292 | M28: 45657 | N28: =(3971003091/36)*12 -> 1323667697 | O28: =(3454954006/36)*12 -> 1.1516513e+09 | P28: 1041755827 | R28: =tProjectsMaster212[[#This Row],[Actual cost (admin)]]/tProjectsMaster212[[#This Row],[Costbased]] -> 0 | S28: Amandemen I No 3900524630 - A1 15 Mei 2023 Amandemen II No 3900524630 - A2 30 November 2023
A29: PS-001-00 | B29: =YEAR(tProjectsMaster212[[#This Row],[End Date]]) -> 2025 | C29: =IF(L29>TODAY(),"FUTURE",IF(M29>TODAY(),"ON GOING","CLOSED")) -> CLOSED | D29: SANDI | E29: PTG | F29: MRC | G29: Manage Service Layanan Printer, Scanner, Multimedia dan UPS System di PT Pertamina Gas | H29: 3900524630 | I29: Kontrak Tunggal | J29: Back2Back | K29: 44866 | L29: 45658 | M29: 46022 | N29: =(3971003091/36)*12 -> 1323667697 | O29: =(3454954006/36)*12 -> 1.1516513e+09 | P29: 1078919563 | R29: =tProjectsMaster212[[#This Row],[Actual cost (admin)]]/tProjectsMaster212[[#This Row],[Costbased]] -> 0 | S29: Amandemen I No 3900524630 - A1 15 Mei 2023 Amandemen II No 3900524630 - A2 30 November 2023 Amandemen III 3900524630 - A3 3 September 2024
A30: PS-001-00 | B30: =YEAR(tProjectsMaster212[[#This Row],[End Date]]) -> 2026 | C30: =IF(L30>TODAY(),"FUTURE",IF(M30>TODAY(),"ON GOING","CLOSED")) -> ON GOING | D30: SANDI | E30: PTG | F30: MRC | G30: Manage Service Layanan Printer, Scanner, Multimedia dan UPS System di PT Pertamina Gas | H30: 3900524630 | I30: Kontrak Tunggal | J30: Back2Back | K30: 44866 | L30: 46023 | M30: 46387 | N30: =(3971003091/36)*12 -> 1323667697 | O30: =(3454954006/36)*12 -> 1.1516513e+09 | P30: =SUMIF('REALISASI 2026'!$C$7:$C$1048576,tProjectsMaster212[[#This Row],[Project_ID]],'REALISASI 2026'!$I$7:$I$1048576) -> 465122754 | Q30: =SUMIF('REALISASI 2026'!$C$7:$C$1048576,tProjectsMaster212[[#This Row],[Project_ID]],'REALISASI 2026'!$I$7:$I$1048576) -> 465122754 | R30: =tProjectsMaster212[[#This Row],[Actual cost (admin)]]/tProjectsMaster212[[#This Row],[Costbased]] -> 0.40387463 | S30: Amandemen I No 3900524630 - A1 15 Mei 2023 Amandemen II No 3900524630 - A2 30 November 2023 Amandemen III 3900524630 - A3 3 September 2024
A31: PS-001-00 | B31: =YEAR(tProjectsMaster212[[#This Row],[End Date]]) -> 2027 | C31: =IF(L31>TODAY(),"FUTURE",IF(M31>TODAY(),"ON GOING","CLOSED")) -> FUTURE | E31: PTG | F31: MRC | G31: Manage Service Layanan Printer, Scanner, Multimedia dan UPS System di PT Pertamina Gas | H31: 3900524630 | I31: Kontrak Tunggal | J31: Back2Back | K31: 44866 | L31: 46388 | M31: 46538 | N31: =(3971003091*(5/36)) -> 5.5152821e+08 | O31: =(3454954006/36)*5 -> 4.7985472e+08 | R31: =tProjectsMaster212[[#This Row],[Actual cost (admin)]]/tProjectsMaster212[[#This Row],[Costbased]] -> 0 | S31: Amandemen I No 3900524630 - A1 15 Mei 2023 Amandemen II No 3900524630 - A2 30 November 2023 Amandemen III 3900524630 - A3 3 September 2024 Amandemen IV 3900524630 - A4 8 Juni 2026
A32: PS-003-00 | B32: =YEAR(tProjectsMaster212[[#This Row],[End Date]]) -> 2024 | C32: =IF(L32>TODAY(),"FUTURE",IF(M32>TODAY(),"ON GOING","CLOSED")) -> CLOSED | D32: TITA | E32: WDR | F32: MRC | G32: Pengadaan Sewa Aplikasi Absensi Online (Bimasakti) | H32: 064900.S/LG.01.01/HCGA-WMN/2024 | I32: Kontrak Tunggal | J32: Back2Back | K32: 45454 | L32: 45455 | M32: 45657 | N32: 1788000 | O32: 0 | P32: 0 | Q32: 0 | R32: =tProjectsMaster212[[#This Row],[Actual cost (admin)]]/tProjectsMaster212[[#This Row],[Costbased]] -> #DIV/0! | S32: 068500.SPK/LG.01.01/HCGA-WMN/2024
A33: PS-003-00 | B33: =YEAR(tProjectsMaster212[[#This Row],[End Date]]) -> 2025 | C33: =IF(L33>TODAY(),"FUTURE",IF(M33>TODAY(),"ON GOING","CLOSED")) -> CLOSED | D33: TITA | E33: WDR | F33: MRC | G33: Pengadaan Sewa Aplikasi Absensi Online (Bimasakti) | H33: 064900.S/LG.01.01/HCGA-WMN/2024 | I33: Kontrak Tunggal | J33: Back2Back | K33: 45454 | L33: 45658 | M33: 46022 | N33: 3576000 | O33: 3840000 | P33: =3840000 -> 3840000 | Q33: 0 | R33: =tProjectsMaster212[[#This Row],[Actual cost (admin)]]/tProjectsMaster212[[#This Row],[Costbased]] -> 0 | S33: 068500.SPK/LG.01.01/HCGA-WMN/2024
A34: PS-003-00 | B34: =YEAR(tProjectsMaster212[[#This Row],[End Date]]) -> 2026 | C34: =IF(L34>TODAY(),"FUTURE",IF(M34>TODAY(),"ON GOING","CLOSED")) -> CLOSED | D34: TITA | E34: WDR | F34: MRC | G34: Pengadaan Sewa Aplikasi Absensi Online (Bimasakti) | H34: 064900.S/LG.01.01/HCGA-WMN/2024 | I34: Kontrak Tunggal | J34: Back2Back | K34: 45454 | L34: 46023 | M34: 46234 | N34: =1788000+298000 -> 2086000 | O34: =4000*40 -> 160000 | P34: =SUMIF('REALISASI 2026'!$C$7:$C$1048576,tProjectsMaster212[[#This Row],[Project_ID]],'REALISASI 2026'!$I$7:$I$1048576) -> 2160000 | Q34: =SUMIF('REALISASI 2026'!$C$7:$C$1048576,tProjectsMaster212[[#This Row],[Project_ID]],'REALISASI 2026'!$I$7:$I$1048576) -> 2160000 | R34: =tProjectsMaster212[[#This Row],[Actual cost (admin)]]/tProjectsMaster212[[#This Row],[Costbased]] -> 13.5 | S34: 068500.SPK/LG.01.01/HCGA-WMN/2024
A35: PS-004-00 | B35: =YEAR(tProjectsMaster212[[#This Row],[End Date]]) -> 2023 | C35: =IF(L35>TODAY(),"FUTURE",IF(M35>TODAY(),"ON GOING","CLOSED")) -> CLOSED | E35: PTM | F35: MRC | G35: Pengelolaan & Pengembangan Servicedesk Shared Services Pertamina | H35: 4650002171 | I35: Kontrak Tunggal | J35: Inhouse | K35: 45103 | L35: 45078 | M35: 45291 | N35: =904587350 * 6 -> 5427524100 | O35: =10460864372/12*6 -> 5230432186 | R35: =tProjectsMaster212[[#This Row],[Actual cost (admin)]]/tProjectsMaster212[[#This Row],[Costbased]] -> 0 | T35: 89,60%
A36: PS-004-00 | B36: =YEAR(tProjectsMaster212[[#This Row],[End Date]]) -> 2024 | C36: =IF(L36>TODAY(),"FUTURE",IF(M36>TODAY(),"ON GOING","CLOSED")) -> CLOSED | E36: PTM | F36: MRC | G36: Pengelolaan & Pengembangan Servicedesk Shared Services Pertamina | H36: 4650002171 | I36: Kontrak Tunggal | J36: Inhouse | K36: 45103 | L36: 45292 | M36: 45657 | N36: =904587350 * 12 -> 10855048200 | O36: 10460864372 | R36: =tProjectsMaster212[[#This Row],[Actual cost (admin)]]/tProjectsMaster212[[#This Row],[Costbased]] -> 0 | T36: 89,60%
A37: PS-004-00 | B37: =YEAR(tProjectsMaster212[[#This Row],[End Date]]) -> 2025 | C37: =IF(L37>TODAY(),"FUTURE",IF(M37>TODAY(),"ON GOING","CLOSED")) -> CLOSED | E37: PTM | F37: MRC | G37: Pengelolaan & Pengembangan Servicedesk Shared Services Pertamina | H37: 4650002171 | I37: Kontrak Tunggal | J37: Inhouse | K37: 45103 | L37: 45658 | M37: 46022 | N37: =904587350 * 12 -> 10855048200 | O37: =10460864372 -> 10460864372 | R37: =tProjectsMaster212[[#This Row],[Actual cost (admin)]]/tProjectsMaster212[[#This Row],[Costbased]] -> 0 | T37: 89,60%
A38: PS-004-00 | B38: =YEAR(tProjectsMaster212[[#This Row],[End Date]]) -> 2026 | C38: =IF(L38>TODAY(),"FUTURE",IF(M38>TODAY(),"ON GOING","CLOSED")) -> CLOSED | E38: PTM | F38: MRC | G38: Pengelolaan & Pengembangan Servicedesk Shared Services Pertamina | H38: 4650002171 | I38: Kontrak Tunggal | J38: Inhouse | K38: 45103 | L38: 46023 | M38: 46203 | N38: =904587350 * 6 -> 5427524100 | O38: =10460864372/12*6 -> 5230432186 | P38: =SUMIF('REALISASI 2026'!$C$7:$C$1048576,tProjectsMaster212[[#This Row],[Project_ID]],'REALISASI 2026'!$I$7:$I$1048576) -> 5844708067 | Q38: =SUMIF('REALISASI 2026'!$C$7:$C$1048576,tProjectsMaster212[[#This Row],[Project_ID]],'REALISASI 2026'!$I$7:$I$1048576) -> 5844708067 | R38: =tProjectsMaster212[[#This Row],[Actual cost (admin)]]/tProjectsMaster212[[#This Row],[Costbased]] -> 1.1174427 | T38: 89,60%
A39: PS-005-00 | B39: =YEAR(tProjectsMaster212[[#This Row],[End Date]]) -> 2025 | C39: =IF(L39>TODAY(),"FUTURE",IF(M39>TODAY(),"ON GOING","CLOSED")) -> CLOSED | D39: SANDI | E39: KJG | F39: MRC | G39: Pengadaan Jasa penyediaan Perangkat Sistem Informasi | H39: 00354.SPK-LG.01-KJG-2025 | I39: Kontrak Tunggal | J39: Inhouse | K39: 45729 | L39: 45782 | M39: 46022 | N39: =131992000+14970000 -> 146962000 | O39: =11637000+110062312 -> 121699312 | R39: =tProjectsMaster212[[#This Row],[Actual cost (admin)]]/tProjectsMaster212[[#This Row],[Costbased]] -> 0 | T39: 0.4
A40: PS-005-00 | B40: =YEAR(tProjectsMaster212[[#This Row],[End Date]]) -> 2026 | C40: =IF(L40>TODAY(),"FUTURE",IF(M40>TODAY(),"ON GOING","CLOSED")) -> CLOSED | D40: SANDI | E40: KJG | F40: MRC | G40: Pengadaan Jasa penyediaan Perangkat Sistem Informasi | H40: 00354.SPK-LG.01-KJG-2025 | I40: Kontrak Tunggal | J40: Inhouse | K40: 45729 | L40: 46023 | M40: 46238 | N40: 65996000 | O40: =55031156 -> 55031156 | P40: =SUMIF('REALISASI 2026'!$C$7:$C$1048576,tProjectsMaster212[[#This Row],[Project_ID]],'REALISASI 2026'!$I$7:$I$1048576) -> 30937554 | Q40: =SUMIF('REALISASI 2026'!$C$7:$C$1048576,tProjectsMaster212[[#This Row],[Project_ID]],'REALISASI 2026'!$I$7:$I$1048576) -> 30937554 | R40: =tProjectsMaster212[[#This Row],[Actual cost (admin)]]/tProjectsMaster212[[#This Row],[Costbased]] -> 0.56218252 | T40: 0.4
A41: PS-006-00 | B41: =YEAR(tProjectsMaster212[[#This Row],[End Date]]) -> 2024 | C41: =IF(L41>TODAY(),"FUTURE",IF(M41>TODAY(),"ON GOING","CLOSED")) -> CLOSED | D41: YIYIP | E41: PSOL | F41: WO | G41: Implementasi Vulnerability Assessment & Penetration Test (VAPT) dan Technical Service Cyber Security | H41: 000100.Prn/LG.01/MSB/PGAS/VIII/2024 | I41: Kontrak Induk | J41: Back2Back | K41: 45516 | L41: 45516 | M41: 45657 | N41: =308860000*(1/8) -> 38607500 | O41: =308860000*(1/8) -> 38607500 | P41: =2*16000000 -> 32000000 | R41: =tProjectsMaster212[[#This Row],[Actual cost (admin)]]/tProjectsMaster212[[#This Row],[Costbased]] -> 0 | T41: 0.8923
A42: PS-006-00 | B42: =YEAR(tProjectsMaster212[[#This Row],[End Date]]) -> 2025 | C42: =IF(L42>TODAY(),"FUTURE",IF(M42>TODAY(),"ON GOING","CLOSED")) -> CLOSED | D42: YIYIP | E42: PSOL | F42: WO | G42: Implementasi Vulnerability Assessment & Penetration Test (VAPT) dan Technical Service Cyber Security | H42: 000100.Prn/LG.01/MSB/PGAS/VIII/2024 | I42: Kontrak Induk | J42: Back2Back | K42: 45516 | L42: 45658 | M42: 46022 | N42: =308860000*(4/8) -> 154430000 | O42: =308860000*(4/8) -> 154430000 | P42: =2*16000000 -> 32000000 | R42: =tProjectsMaster212[[#This Row],[Actual cost (admin)]]/tProjectsMaster212[[#This Row],[Costbased]] -> 0 | T42: 0.8923
A43: PS-006-00 | B43: =YEAR(tProjectsMaster212[[#This Row],[End Date]]) -> 2026 | C43: =IF(L43>TODAY(),"FUTURE",IF(M43>TODAY(),"ON GOING","CLOSED")) -> CLOSED | D43: YIYIP | E43: PSOL | F43: WO | G43: Implementasi Vulnerability Assessment & Penetration Test (VAPT) dan Technical Service Cyber Security | H43: 000100.Prn/LG.01/MSB/PGAS/VIII/2024 | I43: Kontrak Induk | J43: Back2Back | K43: 45516 | L43: 46023 | M43: 46245 | N43: =308860000*(3/8) -> 115822500 | O43: =308860000*(3/8) -> 115822500 | P43: =SUMIF('REALISASI 2026'!$C$7:$C$1048576,tProjectsMaster212[[#This Row],[Project_ID]],'REALISASI 2026'!$I$7:$I$1048576) -> 0 | Q43: =SUMIF('REALISASI 2026'!$C$7:$C$1048576,tProjectsMaster212[[#This Row],[Project_ID]],'REALISASI 2026'!$I$7:$I$1048576) -> 0 | R43: =tProjectsMaster212[[#This Row],[Actual cost (admin)]]/tProjectsMaster212[[#This Row],[Costbased]] -> 0 | T43: 0.8923
A44: PS-007-00 | B44: =YEAR(tProjectsMaster212[[#This Row],[End Date]]) -> 2025 | C44: =IF(L44>TODAY(),"FUTURE",IF(M44>TODAY(),"ON GOING","CLOSED")) -> CLOSED | D44: RIKI | E44: PGN | F44: MRC | G44: Pekerjaan Penyediaan Layanan Sewa Server YKPP PGN | H44: 270/VIII/YKPP Gas Negara/2025 | I44: Kontrak Tunggal | J44: Back2Back | K44: 45889 | L44: 45901 | M44: 46022 | N44: =(36288000/12)*4 -> 12096000 | O44: =27189120 -> 27189120 | P44: =(21878400/12)*4 -> 7292800 | R44: =tProjectsMaster212[[#This Row],[Actual cost (admin)]]/tProjectsMaster212[[#This Row],[Costbased]] -> 0
A45: PS-007-00 | B45: =YEAR(tProjectsMaster212[[#This Row],[End Date]]) -> 2026 | C45: =IF(L45>TODAY(),"FUTURE",IF(M45>TODAY(),"ON GOING","CLOSED")) -> ON GOING | D45: RIKI | E45: PGN | F45: MRC | G45: Pekerjaan Penyediaan Layanan Sewa Server YKPP PGN | H45: 270/VIII/YKPP Gas Negara/2025 | I45: Kontrak Tunggal | J45: Back2Back | K45: 45889 | L45: 46023 | M45: 46265 | N45: =(36288000/12)*8 -> 24192000 | O45: 0 | P45: =(21878400/12)*8 -> 14585600 | Q45: =SUMIF('REALISASI 2026'!$C$7:$C$1048576,tProjectsMaster212[[#This Row],[Project_ID]],'REALISASI 2026'!$I$7:$I$1048576) -> 0 | R45: =tProjectsMaster212[[#This Row],[Actual cost (admin)]]/tProjectsMaster212[[#This Row],[Costbased]] -> #DIV/0!
A46: PS-008-00 | B46: =YEAR(tProjectsMaster212[[#This Row],[End Date]]) -> 2025 | C46: =IF(L46>TODAY(),"FUTURE",IF(M46>TODAY(),"ON GOING","CLOSED")) -> CLOSED | D46: JODY | E46: PGN | F46: MRC | G46: Jasa Teknikal Asistensi Sistem Manajemen Informasi Legal (SMILE) | H46: 044300.PK/LG.01/LGL/2025 | I46: Kontrak Tunggal | J46: Inhouse | K46: 45924 | L46: 45924 | M46: 46022 | N46: =359700000*(3/12) -> 89925000 | O46: =323303403*(3/12) -> 80825851 | P46: =SUMIF('REALISASI 2026'!$C$7:$C$1048576,tProjectsMaster212[[#This Row],[Project_ID]],'REALISASI 2026'!$I$7:$I$1048576) -> 61592381 | R46: =tProjectsMaster212[[#This Row],[Actual cost (admin)]]/tProjectsMaster212[[#This Row],[Costbased]] -> 0 | T46: 0.9547
A47: PS-008-00 | B47: =YEAR(tProjectsMaster212[[#This Row],[End Date]]) -> 2026 | C47: =IF(L47>TODAY(),"FUTURE",IF(M47>TODAY(),"ON GOING","CLOSED")) -> ON GOING | D47: JODY | E47: PGN | F47: MRC | G47: Jasa Teknikal Asistensi Sistem Manajemen Informasi Legal (SMILE) | H47: 044300.PK/LG.01/LGL/2025 | I47: Kontrak Tunggal | J47: Inhouse | K47: 45924 | L47: 46023 | M47: 46288 | N47: =359700000*(9/12) -> 269775000 | O47: =323303403*(9/12) -> 2.4247755e+08 | P47: =SUMIF('REALISASI 2026'!$C$7:$C$1048576,tProjectsMaster212[[#This Row],[Project_ID]],'REALISASI 2026'!$I$7:$I$1048576) -> 61592381 | Q47: =SUMIF('REALISASI 2026'!$C$7:$C$1048576,tProjectsMaster212[[#This Row],[Project_ID]],'REALISASI 2026'!$I$7:$I$1048576) -> 61592381 | R47: =tProjectsMaster212[[#This Row],[Actual cost (admin)]]/tProjectsMaster212[[#This Row],[Costbased]] -> 0.25401271 | T47: 0.9547
A48: PS-009-00 | B48: =YEAR(tProjectsMaster212[[#This Row],[End Date]]) -> 2025 | C48: =IF(L48>TODAY(),"FUTURE",IF(M48>TODAY(),"ON GOING","CLOSED")) -> CLOSED | D48: YIYIP | E48: NR | F48: MRC | G48: Jasa Implementasi Security Information Event Management (SIEM) dan Security Operation Center (SOC) | H48: 027/NR/C200/P/2025 | I48: Kontrak Induk | J48: Back2Back | K48: 46021 | L48: 45908 | M48: 46022 | N48: =26300000+(32600000+1152000)*3 -> 127556000 | O48: =380409120/2 -> 190204560 | R48: =tProjectsMaster212[[#This Row],[Actual cost (admin)]]/tProjectsMaster212[[#This Row],[Costbased]] -> 0 | T48: 0.7386
A49: PS-009-00 | B49: =YEAR(tProjectsMaster212[[#This Row],[End Date]]) -> 2026 | C49: =IF(L49>TODAY(),"FUTURE",IF(M49>TODAY(),"ON GOING","CLOSED")) -> ON GOING | D49: YIYIP | E49: NR | F49: MRC | G49: Jasa Implementasi Security Information Event Management (SIEM) dan Security Operation Center (SOC) | H49: 027/NR/C200/P/2025 | I49: Kontrak Induk | J49: Back2Back | K49: 46021 | L49: 46023 | M49: 46292 | N49: =(32600000+1152000)*9 -> 303768000 | O49: =380409120/2 -> 190204560 | P49: =SUMIF('REALISASI 2026'!$C$7:$C$1048576,tProjectsMaster212[[#This Row],[Project_ID]],'REALISASI 2026'!$I$7:$I$1048576) -> 230573 | Q49: =SUMIF('REALISASI 2026'!$C$7:$C$1048576,tProjectsMaster212[[#This Row],[Project_ID]],'REALISASI 2026'!$I$7:$I$1048576) -> 230573 | R49: =tProjectsMaster212[[#This Row],[Actual cost (admin)]]/tProjectsMaster212[[#This Row],[Costbased]] -> 0.001212237 | T49: 0.7386
A50: PS-010-00 | B50: =YEAR(tProjectsMaster212[[#This Row],[End Date]]) -> 2025 | C50: =IF(L50>TODAY(),"FUTURE",IF(M50>TODAY(),"ON GOING","CLOSED")) -> CLOSED | D50: SANDI | E50: PTM | F50: MRC | G50: Penyediaan Jasa Dukungan Operasional Fungsi Shared Services ICT Tahun 2025-2026 | H50: 3950458034 | I50: Kontrak Tunggal | J50: Inhouse | K50: 45993 | L50: 45992 | M50: 46022 | N50: =6863206200/12 -> 571933850 | O50: =6455418228/12 -> 537951519 | R50: =tProjectsMaster212[[#This Row],[Actual cost (admin)]]/tProjectsMaster212[[#This Row],[Costbased]] -> 0 | T50: 0.81
A51: PS-010-00 | B51: =YEAR(tProjectsMaster212[[#This Row],[End Date]]) -> 2026 | C51: =IF(L51>TODAY(),"FUTURE",IF(M51>TODAY(),"ON GOING","CLOSED")) -> ON GOING | D51: SANDI | E51: PTM | F51: MRC | G51: Penyediaan Jasa Dukungan Operasional Fungsi Shared Services ICT Tahun 2025-2026 | H51: 3950458034 | I51: Kontrak Tunggal | J51: Inhouse | K51: 45993 | L51: 46023 | M51: 46356 | N51: =N50*11 -> 6291272350 | O51: =O50*11 -> 5917466709 | P51: =SUMIF('REALISASI 2026'!$C$7:$C$1048576,tProjectsMaster212[[#This Row],[Project_ID]],'REALISASI 2026'!$I$7:$I$1048576) -> 1943532292 | Q51: =SUMIF('REALISASI 2026'!$C$7:$C$1048576,tProjectsMaster212[[#This Row],[Project_ID]],'REALISASI 2026'!$I$7:$I$1048576) -> 1943532292 | R51: =tProjectsMaster212[[#This Row],[Actual cost (admin)]]/tProjectsMaster212[[#This Row],[Costbased]] -> 0.32843992 | T51: 0.81
A52: PS-011-00 | B52: =YEAR(tProjectsMaster212[[#This Row],[End Date]]) -> 2026 | C52: =IF(L52>TODAY(),"FUTURE",IF(M52>TODAY(),"ON GOING","CLOSED")) -> ON GOING | E52: PGN | F52: WO | G52: Penyediaan Lisensi Piranti Lunak dan Annual Technical Support | H52: 032200.PK/LG.01/ICT/2025 | I52: kontrak Induk | J52: Inhouse | K52: 45993 | L52: 45993 | M52: 46357 | N52: 3350000000 | O52: 3.0195815e+09 | P52: =SUMIF('REALISASI 2026'!$C$7:$C$1048576,tProjectsMaster212[[#This Row],[Project_ID]],'REALISASI 2026'!$I$7:$I$1048576) -> 190200000 | Q52: =SUMIF('REALISASI 2026'!$C$7:$C$1048576,tProjectsMaster212[[#This Row],[Project_ID]],'REALISASI 2026'!$I$7:$I$1048576) -> 190200000 | R52: =tProjectsMaster212[[#This Row],[Actual cost (admin)]]/tProjectsMaster212[[#This Row],[Costbased]] -> 0.062988862 | T52: 33,77%
A53: PS-012-00 | B53: =YEAR(tProjectsMaster212[[#This Row],[End Date]]) -> 2026 | C53: =IF(L53>TODAY(),"FUTURE",IF(M53>TODAY(),"ON GOING","CLOSED")) -> ON GOING | D53: YIYIP-RIZKY | E53: PTM | F53: MRC | G53: Pengadaan Jasa Penyediaan Endpoint Security 2026-2027 | H53: 3950486562 | I53: Kontrak Tunggal | J53: Back2Back | K53: TBC | L53: 46099 | M53: 46387 | N53: =13056874050+30846028065+(546750000*(10/12)) -> 44358527115 | O53: =11978791240+28299109280+(1040000000*(10/12)) -> 4.1144567e+10 | P53: =SUMIF('REALISASI 2026'!$C$7:$C$1048576,tProjectsMaster212[[#This Row],[Project_ID]],'REALISASI 2026'!$I$7:$I$1048576) -> 38590702719 | Q53: =SUMIF('REALISASI 2026'!$C$7:$C$1048576,tProjectsMaster212[[#This Row],[Project_ID]],'REALISASI 2026'!$I$7:$I$1048576) -> 38590702719 | R53: =tProjectsMaster212[[#This Row],[Actual cost (admin)]]/tProjectsMaster212[[#This Row],[Costbased]] -> 0.93792949 | T53: 1,11%
A54: PS-012-00 | B54: =YEAR(tProjectsMaster212[[#This Row],[End Date]]) -> 2027 | C54: =IF(L54>TODAY(),"FUTURE",IF(M54>TODAY(),"ON GOING","CLOSED")) -> FUTURE | D54: YIYIP-RIZKY | E54: PTM | F54: MRC | G54: Pengadaan Jasa Penyediaan Endpoint Security 2026-2027 | H54: 3950486562 | I54: Kontrak Tunggal | J54: Back2Back | K54: TBC | L54: 46388 | M54: 46463 | N54: =546750000*(2/12) -> 91125000 | O54: =1040000000*(2/12) -> 1.7333333e+08 | R54: =tProjectsMaster212[[#This Row],[Actual cost (admin)]]/tProjectsMaster212[[#This Row],[Costbased]] -> 0 | T54: 0.0111
A55: PS-013-00 | B55: =YEAR(tProjectsMaster212[[#This Row],[End Date]]) -> 2023 | C55: =IF(L55>TODAY(),"FUTURE",IF(M55>TODAY(),"ON GOING","CLOSED")) -> CLOSED | D55: RIKI | E55: PTM | F55: MRC | G55: Pengadaan Sewa Perangkat Storage san NTP Server Pertamina | H55: 46000000735 | I55: Kontrak Tunggal | J55: Back2Back | K55: 44936 | L55: 44936 | M55: 45291 | N55: =2500000+4000000+(8416667*7)+(6616667*7) -> 111733338 | O55: =2060000+2060000+(6600512*7)+(4060860*7) -> 78749604 | P55: 608550000 | R55: =tProjectsMaster212[[#This Row],[Actual cost (admin)]]/tProjectsMaster212[[#This Row],[Costbased]] -> 0 | S55: 4600000000891 (AMANDEMEN) 15 Oktober 2024 | T55: 0.7119
A56: PS-013-00 | B56: =YEAR(tProjectsMaster212[[#This Row],[End Date]]) -> 2024 | C56: =IF(L56>TODAY(),"FUTURE",IF(M56>TODAY(),"ON GOING","CLOSED")) -> CLOSED | D56: RIKI | E56: PTM | F56: MRC | G56: Pengadaan Sewa Perangkat Storage san NTP Server Pertamina | H56: 46000000735 | I56: Kontrak Tunggal | J56: Back2Back | K56: 44936 | L56: 45292 | M56: 45657 | N56: =(8416667*12)+(6616667*12) -> 180400008 | O56: =(6600512*12)+(4060860*12) -> 127936464 | P56: 0 | R56: =tProjectsMaster212[[#This Row],[Actual cost (admin)]]/tProjectsMaster212[[#This Row],[Costbased]] -> 0 | S56: 4600000000891 (AMANDEMEN) 15 Oktober 2024 | T56: 0.7119
A57: PS-013-00 | B57: =YEAR(tProjectsMaster212[[#This Row],[End Date]]) -> 2025 | C57: =IF(L57>TODAY(),"FUTURE",IF(M57>TODAY(),"ON GOING","CLOSED")) -> CLOSED | D57: RIKI | E57: PTM | F57: MRC | G57: Pengadaan Sewa Perangkat Storage san NTP Server Pertamina | H57: 46000000735 | I57: Kontrak Tunggal | J57: Back2Back | K57: 44936 | L57: 45658 | M57: 46022 | N57: =(8416667*12)+(6616667*12) -> 180400008 | O57: =(6600512*12)+(4060860*12) -> 127936464 | P57: 0 | R57: =tProjectsMaster212[[#This Row],[Actual cost (admin)]]/tProjectsMaster212[[#This Row],[Costbased]] -> 0 | S57: 4600000000891 (AMANDEMEN) 15 Oktober 2024 | T57: 0.7119
A58: PS-013-00 | B58: =YEAR(tProjectsMaster212[[#This Row],[End Date]]) -> 2026 | C58: =IF(L58>TODAY(),"FUTURE",IF(M58>TODAY(),"ON GOING","CLOSED")) -> ON GOING | D58: RIKI | E58: PTM | F58: MRC | G58: Pengadaan Sewa Perangkat Storage san NTP Server Pertamina | H58: 46000000735 | I58: Kontrak Tunggal | J58: Back2Back | K58: 44936 | L58: 46023 | M58: 46387 | N58: =(8416667*12)+(6616667*12) -> 180400008 | O58: =(6600512*12)+(4060860*12) -> 127936464 | P58: 0 | Q58: =SUMIF('REALISASI 2026'!$C$7:$C$1048576,tProjectsMaster212[[#This Row],[Project_ID]],'REALISASI 2026'!$I$7:$I$1048576) -> 0 | R58: =tProjectsMaster212[[#This Row],[Actual cost (admin)]]/tProjectsMaster212[[#This Row],[Costbased]] -> 0 | S58: 4600000000891 (AMANDEMEN) 15 Oktober 2024 | T58: 0.7119
A59: PS-013-00 | B59: =YEAR(tProjectsMaster212[[#This Row],[End Date]]) -> 2027 | C59: =IF(L59>TODAY(),"FUTURE",IF(M59>TODAY(),"ON GOING","CLOSED")) -> FUTURE | D59: RIKI | E59: PTM | F59: MRC | G59: Pengadaan Sewa Perangkat Storage san NTP Server Pertamina | H59: 46000000735 | I59: Kontrak Tunggal | J59: Back2Back | K59: 44936 | L59: 46388 | M59: 46752 | N59: =(8416667*12)+(6616667*12) -> 180400008 | O59: =(6600512*12)+(4060860*12) -> 127936464 | P59: 0 | R59: =tProjectsMaster212[[#This Row],[Actual cost (admin)]]/tProjectsMaster212[[#This Row],[Costbased]] -> 0 | S59: 4600000000891 (AMANDEMEN) 15 Oktober 2024 | T59: 71,19%
A60: PS-013-00 | B60: =YEAR(tProjectsMaster212[[#This Row],[End Date]]) -> 2028 | C60: =IF(L60>TODAY(),"FUTURE",IF(M60>TODAY(),"ON GOING","CLOSED")) -> FUTURE | D60: RIKI | E60: PTM | F60: MRC | G60: Pengadaan Sewa Perangkat Storage san NTP Server Pertamina | H60: 46000000735 | I60: Kontrak Tunggal | J60: Back2Back | K60: 44936 | L60: 46753 | M60: 46913 | N60: =(8416667*5)+(6616667*5)+19000000 -> 94166670 | O60: =(6600512*5)+(4060860*5)+15450000 -> 68756860 | P60: 0 | R60: =tProjectsMaster212[[#This Row],[Actual cost (admin)]]/tProjectsMaster212[[#This Row],[Costbased]] -> 0 | S60: 4600000000891 (AMANDEMEN) 15 Oktober 2024 | T60: 0.7119
A61: PS-014-00 | B61: =YEAR(tProjectsMaster212[[#This Row],[End Date]]) -> 2024 | C61: =IF(L61>TODAY(),"FUTURE",IF(M61>TODAY(),"ON GOING","CLOSED")) -> CLOSED | D61: TAUFAN | E61: PTM | F61: MRC | G61: Penyediaan Jasa Layanan Offline Backup AWS Phase 1 | H61: 3950372558 | I61: Kontrak Tunggal | J61: Back2Back | K61: 45593 | L61: 45558 | M61: 45657 | N61: =3/36*27649420030 -> 2.3041183e+09 | O61: =3/36*26126274249 -> 2.1771895e+09 | R61: =tProjectsMaster212[[#This Row],[Actual cost (admin)]]/tProjectsMaster212[[#This Row],[Costbased]] -> 0 | T61: 0.3478
A62: PS-014-00 | B62: =YEAR(tProjectsMaster212[[#This Row],[End Date]]) -> 2025 | C62: =IF(L62>TODAY(),"FUTURE",IF(M62>TODAY(),"ON GOING","CLOSED")) -> CLOSED | D62: TAUFAN | E62: PTM | F62: MRC | G62: Penyediaan Jasa Layanan Offline Backup AWS Phase 1 | H62: 3950372558 | I62: Kontrak Tunggal | J62: Back2Back | K62: 45593 | L62: 45658 | M62: 46022 | N62: =12/36*27649420030 -> 9.2164733e+09 | O62: =12/36*26126274249 -> 8708758083 | R62: =tProjectsMaster212[[#This Row],[Actual cost (admin)]]/tProjectsMaster212[[#This Row],[Costbased]] -> 0 | T62: 0.3478
A63: PS-014-00 | B63: =YEAR(tProjectsMaster212[[#This Row],[End Date]]) -> 2026 | C63: =IF(L63>TODAY(),"FUTURE",IF(M63>TODAY(),"ON GOING","CLOSED")) -> ON GOING | D63: TAUFAN | E63: PTM | F63: MRC | G63: Penyediaan Jasa Layanan Offline Backup AWS Phase 1 | H63: 3950372558 | I63: Kontrak Tunggal | J63: Back2Back | K63: 45593 | L63: 46023 | M63: 46387 | N63: =12/36*27649420030 -> 9.2164733e+09 | O63: =12/36*26126274249 -> 8708758083 | Q63: =SUMIF('REALISASI 2026'!$C$7:$C$1048576,tProjectsMaster212[[#This Row],[Project_ID]],'REALISASI 2026'!$I$7:$I$1048576) -> 0 | R63: =tProjectsMaster212[[#This Row],[Actual cost (admin)]]/tProjectsMaster212[[#This Row],[Costbased]] -> 0 | T63: 0.3478
A64: PS-014-00 | B64: =YEAR(tProjectsMaster212[[#This Row],[End Date]]) -> 2027 | C64: =IF(L64>TODAY(),"FUTURE",IF(M64>TODAY(),"ON GOING","CLOSED")) -> FUTURE | D64: TAUFAN | E64: PTM | F64: MRC | G64: Penyediaan Jasa Layanan Offline Backup AWS Phase 1 | H64: 3950372558 | I64: Kontrak Tunggal | J64: Back2Back | K64: 45593 | L64: 46388 | M64: 46652 | N64: =9/36*27649420030 -> 6.912355e+09 | O64: =9/36*26126274249 -> 6.5315686e+09 | R64: =tProjectsMaster212[[#This Row],[Actual cost (admin)]]/tProjectsMaster212[[#This Row],[Costbased]] -> 0 | T64: 0.3478
A65: PS-015-00 | B65: =YEAR(tProjectsMaster212[[#This Row],[End Date]]) -> 2024 | C65: =IF(L65>TODAY(),"FUTURE",IF(M65>TODAY(),"ON GOING","CLOSED")) -> CLOSED | D65: YIYIP | E65: PTM | F65: WO | G65: Tindak Lanjut Pekerjaan Jasa Managed Service Security Assessment (MSSA) | H65: 3950380722 | I65: Kontrak Induk | J65: Back2Back | K65: 45603 | L65: 45621 | M65: 45657 | N65: 8952230028 | O65: =(25279905446/25)*1 -> 1.0111962e+09 | P65: =((8076739200/25)*1)+#REF! -> #REF! | R65: =tProjectsMaster212[[#This Row],[Actual cost (admin)]]/tProjectsMaster212[[#This Row],[Costbased]] -> 0 | T65: 0.3546
A66: PS-015-00 | B66: =YEAR(tProjectsMaster212[[#This Row],[End Date]]) -> 2025 | C66: =IF(L66>TODAY(),"FUTURE",IF(M66>TODAY(),"ON GOING","CLOSED")) -> CLOSED | D66: YIYIP | E66: PTM | F66: WO | G66: Tindak Lanjut Pekerjaan Jasa Managed Service Security Assessment (MSSA) | H66: 3950380722 | I66: Kontrak Induk | J66: Back2Back | K66: 45603 | L66: 45658 | M66: 46022 | N66: 13216910028 | O66: =(25279905446/25)*12 -> 1.2134355e+10 | P66: =((8076739200/25)*12)+#REF! -> #REF! | R66: =tProjectsMaster212[[#This Row],[Actual cost (admin)]]/tProjectsMaster212[[#This Row],[Costbased]] -> 0 | T66: 0.3546
A67: PS-015-00 | B67: =YEAR(tProjectsMaster212[[#This Row],[End Date]]) -> 2026 | C67: =IF(L67>TODAY(),"FUTURE",IF(M67>TODAY(),"ON GOING","CLOSED")) -> ON GOING | D67: YIYIP | E67: PTM | F67: WO | G67: Tindak Lanjut Pekerjaan Jasa Managed Service Security Assessment (MSSA) | H67: 3950380722 | I67: Kontrak Induk | J67: Back2Back | K67: 45603 | L67: 46023 | M67: 46387 | N67: 4264680000 | O67: =(25279905446/25)*12 -> 1.2134355e+10 | P67: =((8076739200/25)*12) -> 3876834816 | Q67: =SUMIF('REALISASI 2026'!$C$7:$C$1048576,tProjectsMaster212[[#This Row],[Project_ID]],'REALISASI 2026'!$I$7:$I$1048576) -> 1520509200 | R67: =tProjectsMaster212[[#This Row],[Actual cost (admin)]]/tProjectsMaster212[[#This Row],[Costbased]] -> 0.12530615 | T67: 0.3546
A68: PS-015-00 | B68: =YEAR(tProjectsMaster212[[#This Row],[End Date]]) -> 2027 | C68: =IF(L68>TODAY(),"FUTURE",IF(M68>TODAY(),"ON GOING","CLOSED")) -> FUTURE | D68: YIYIP | E68: PTM | F68: WO | G68: Tindak Lanjut Pekerjaan Jasa Managed Service Security Assessment (MSSA) | H68: 3950380722 | I68: Kontrak Tunggal | J68: Back2Back | K68: 45603 | L68: 46388 | M68: 46551 | N68: 0 | O68: MASA PEMELIHARAAN | P68: MASA PEMELIHARAAN | R68: =tProjectsMaster212[[#This Row],[Actual cost (admin)]]/tProjectsMaster212[[#This Row],[Costbased]] -> #VALUE! | T68: 0.3546
A69: PS-016-00 | B69: =YEAR(tProjectsMaster212[[#This Row],[End Date]]) -> 2025 | C69: =IF(L69>TODAY(),"FUTURE",IF(M69>TODAY(),"ON GOING","CLOSED")) -> CLOSED | D69: TAUFAN | E69: PGN | F69: MRC | G69: Jasa Managed Service Pengelolaan Layanan Pelanggan Melalui Contact Center 2025-2027 | H69: 083400.PK/PP.04/SCSM/2025 | I69: Kontrak Tunggal | J69: Back2Back | K69: 45922 | L69: 45931 | M69: 46022 | N69: 1083605000 | O69: 866580638 | P69: 616182300 | R69: =tProjectsMaster212[[#This Row],[Actual cost (admin)]]/tProjectsMaster212[[#This Row],[Costbased]] -> 0 | T69: 89,20%
A70: PS-016-00 | B70: =YEAR(tProjectsMaster212[[#This Row],[End Date]]) -> 2026 | C70: =IF(L70>TODAY(),"FUTURE",IF(M70>TODAY(),"ON GOING","CLOSED")) -> ON GOING | D70: TAUFAN | E70: PGN | F70: MRC | G70: Jasa Managed Service Pengelolaan Layanan Pelanggan Melalui Contact Center 2025-2027 | H70: 083400.PK/PP.04/SCSM/2025 | I70: Kontrak Tunggal | J70: Back2Back | K70: 45922 | L70: 46023 | M70: 46387 | N70: 3811175000 | O70: 3696137976 | Q70: =SUMIF('REALISASI 2026'!$C$7:$C$1048576,tProjectsMaster212[[#This Row],[Project_ID]],'REALISASI 2026'!$I$7:$I$1048576) -> 720083807 | R70: =tProjectsMaster212[[#This Row],[Actual cost (admin)]]/tProjectsMaster212[[#This Row],[Costbased]] -> 0.1948206 | T70: 89,20%
A71: PS-016-00 | B71: =YEAR(tProjectsMaster212[[#This Row],[End Date]]) -> 2027 | C71: =IF(L71>TODAY(),"FUTURE",IF(M71>TODAY(),"ON GOING","CLOSED")) -> FUTURE | D71: TAUFAN | E71: PGN | F71: MRC | G71: Jasa Managed Service Pengelolaan Layanan Pelanggan Melalui Contact Center 2025-2027 | H71: 083400.PK/PP.04/SCSM/2025 | I71: Kontrak Tunggal | J71: Back2Back | K71: 45922 | L71: 46388 | M71: 46660 | N71: 2905220000 | O71: 2865914055 | R71: =tProjectsMaster212[[#This Row],[Actual cost (admin)]]/tProjectsMaster212[[#This Row],[Costbased]] -> 0 | T71: 89,20%
A72: PS-017-00 | B72: =YEAR(tProjectsMaster212[[#This Row],[End Date]]) -> 2023 | C72: =IF(L72>TODAY(),"FUTURE",IF(M72>TODAY(),"ON GOING","CLOSED")) -> CLOSED | D72: TITA | E72: PGN | F72: MRC | G72: Jasa Penyediaan Perangkat Multimedia dan Peralatan Pendukung Ruang Integrated Monitoring Center (IMOC) | H72: 019700.PK/LG.01.01/GLM/2023 | I72: Kontrak Tunggal | J72: Back2Back | K72: 45162 | L72: 45231 | M72: 45291 | N72: =1100000000+((7500000000/60)*2) -> 1350000000 | O72: =952208424+((6309367234/60)*2) -> 1.1625207e+09 | P72: =(5689999260/60)*2 -> 189666642 | R72: =tProjectsMaster212[[#This Row],[Actual cost (admin)]]/tProjectsMaster212[[#This Row],[Costbased]] -> 0 | T72: 0.8513
A73: PS-017-00 | B73: =YEAR(tProjectsMaster212[[#This Row],[End Date]]) -> 2024 | C73: =IF(L73>TODAY(),"FUTURE",IF(M73>TODAY(),"ON GOING","CLOSED")) -> CLOSED | D73: TITA | E73: PGN | F73: MRC | G73: Jasa Penyediaan Perangkat Multimedia dan Peralatan Pendukung Ruang Integrated Monitoring Center (IMOC) | H73: 019700.PK/LG.01.01/GLM/2023 | I73: Kontrak Tunggal | J73: Back2Back | K73: 45162 | L73: 45292 | M73: 45657 | N73: =(7500000000/60)*12 -> 1500000000 | O73: =(6309367234/60)*12 -> 1.2618734e+09 | P73: =(5689999260/60)*12 -> 1137999852 | R73: =tProjectsMaster212[[#This Row],[Actual cost (admin)]]/tProjectsMaster212[[#This Row],[Costbased]] -> 0 | T73: 0.8513
A74: PS-017-00 | B74: =YEAR(tProjectsMaster212[[#This Row],[End Date]]) -> 2025 | C74: =IF(L74>TODAY(),"FUTURE",IF(M74>TODAY(),"ON GOING","CLOSED")) -> CLOSED | D74: TITA | E74: PGN | F74: MRC | G74: Jasa Penyediaan Perangkat Multimedia dan Peralatan Pendukung Ruang Integrated Monitoring Center (IMOC) | H74: 019700.PK/LG.01.01/GLM/2023 | I74: Kontrak Tunggal | J74: Back2Back | K74: 45162 | L74: 45658 | M74: 46022 | N74: =(7500000000/60)*12 -> 1500000000 | O74: =(6309367234/60)*12 -> 1.2618734e+09 | P74: =(5689999260/60)*12 -> 1137999852 | R74: =tProjectsMaster212[[#This Row],[Actual cost (admin)]]/tProjectsMaster212[[#This Row],[Costbased]] -> 0 | T74: 0.8513
A75: PS-017-00 | B75: =YEAR(tProjectsMaster212[[#This Row],[End Date]]) -> 2026 | C75: =IF(L75>TODAY(),"FUTURE",IF(M75>TODAY(),"ON GOING","CLOSED")) -> ON GOING | D75: TITA | E75: PGN | F75: MRC | G75: Jasa Penyediaan Perangkat Multimedia dan Peralatan Pendukung Ruang Integrated Monitoring Center (IMOC) | H75: 019700.PK/LG.01.01/GLM/2023 | I75: Kontrak Tunggal | J75: Back2Back | K75: 45162 | L75: 46023 | M75: 46387 | N75: =(7500000000/60)*12 -> 1500000000 | O75: =(6309367234/60)*12 -> 1.2618734e+09 | P75: =(5689999260/60)*12 -> 1137999852 | Q75: =SUMIF('REALISASI 2026'!$C$7:$C$1048576,tProjectsMaster212[[#This Row],[Project_ID]],'REALISASI 2026'!$I$7:$I$1048576) -> 879104886 | R75: =tProjectsMaster212[[#This Row],[Actual cost (admin)]]/tProjectsMaster212[[#This Row],[Costbased]] -> 0.69666644 | T75: 0.8513
A76: PS-017-00 | B76: =YEAR(tProjectsMaster212[[#This Row],[End Date]]) -> 2027 | C76: =IF(L76>TODAY(),"FUTURE",IF(M76>TODAY(),"ON GOING","CLOSED")) -> FUTURE | D76: TITA | E76: PGN | F76: MRC | G76: Jasa Penyediaan Perangkat Multimedia dan Peralatan Pendukung Ruang Integrated Monitoring Center (IMOC) | H76: 019700.PK/LG.01.01/GLM/2023 | I76: Kontrak Tunggal | J76: Back2Back | K76: 45162 | L76: 46388 | M76: 46752 | N76: =(7500000000/60)*12 -> 1500000000 | O76: =(6309367234/60)*12 -> 1.2618734e+09 | P76: =(5689999260/60)*12 -> 1137999852 | R76: =tProjectsMaster212[[#This Row],[Actual cost (admin)]]/tProjectsMaster212[[#This Row],[Costbased]] -> 0 | T76: 0.8513
A77: PS-017-00 | B77: =YEAR(tProjectsMaster212[[#This Row],[End Date]]) -> 2028 | C77: =IF(L77>TODAY(),"FUTURE",IF(M77>TODAY(),"ON GOING","CLOSED")) -> FUTURE | D77: TITA | E77: PGN | F77: MRC | G77: Jasa Penyediaan Perangkat Multimedia dan Peralatan Pendukung Ruang Integrated Monitoring Center (IMOC) | H77: 019700.PK/LG.01.01/GLM/2023 | I77: Kontrak Tunggal | J77: Back2Back | K77: 45162 | L77: 46753 | M77: 47057 | N77: =(7500000000/60)*12 -> 1500000000 | O77: =(6309367234/60)*10 -> 1.0515612e+09 | P77: =(5689999260/60)*10 -> 948333210 | R77: =tProjectsMaster212[[#This Row],[Actual cost (admin)]]/tProjectsMaster212[[#This Row],[Costbased]] -> 0 | T77: 0.8513
A78: PS-018-00 | B78: =YEAR(tProjectsMaster212[[#This Row],[End Date]]) -> 2026 | C78: =IF(L78>TODAY(),"FUTURE",IF(M78>TODAY(),"ON GOING","CLOSED")) -> ON GOING | D78: TAUFAN | E78: PGN | F78: MRC+WO | G78: Managed Service Aplication Integration Solutions (MSAIS) Tahun 2026 | H78: 004200.PK/LG.01/ICT/2026 | I78: kontrak Induk | J78: Inhouse | K78: 46078 | L78: 46023 | M78: 46387 | N78: 12100150000 | O78: 11738007071 | P78: TBC CHNYTIA + SIGIT | Q78: =SUMIF('REALISASI 2026'!$C$7:$C$1048576,tProjectsMaster212[[#This Row],[Project_ID]],'REALISASI 2026'!$I$7:$I$1048576) -> 7.5817275e+09 | R78: =tProjectsMaster212[[#This Row],[Actual cost (admin)]]/tProjectsMaster212[[#This Row],[Costbased]] -> 0.64591267 | T78: 84,45%
A79: PS-019-00 | B79: =YEAR(tProjectsMaster212[[#This Row],[End Date]]) -> 2025 | C79: =IF(L79>TODAY(),"FUTURE",IF(M79>TODAY(),"ON GOING","CLOSED")) -> CLOSED | D79: RIKI | E79: PGN | F79: MRC | G79: Managed Service Backup Management (Vinchin) | H79: 028000.PK/LG.01/ICT/2024 | I79: Kontrak Tunggal | J79: Back2Back | K79: 45608 | L79: 45658 | M79: 46022 | N79: =10570000000/3 -> 3.5233333e+09 | O79: =631471834+395687500+331200000+102400000+172618338+124800000+210246514+68800000+4019350000+432573333 -> 6489147519 | P79: =1260000000+860350000+2191200000+1616644852+(28356091*12) -> 6268467944 | R79: =tProjectsMaster212[[#This Row],[Actual cost (admin)]]/tProjectsMaster212[[#This Row],[Costbased]] -> 0 | T79: 0.5031
A80: PS-019-00 | B80: =YEAR(tProjectsMaster212[[#This Row],[End Date]]) -> 2026 | C80: =IF(L80>TODAY(),"FUTURE",IF(M80>TODAY(),"ON GOING","CLOSED")) -> ON GOING | D80: RIKI | E80: PGN | F80: MRC | G80: Managed Service Backup Management (Vinchin) | H80: 028000.PK/LG.01/ICT/2024 | I80: Kontrak Tunggal | J80: Back2Back | K80: 45608 | L80: 46023 | M80: 46387 | N80: =10570000000/3 -> 3.5233333e+09 | O80: =432573333 -> 432573333 | P80: =SUMIF('REALISASI 2026'!$C$7:$C$1048576,tProjectsMaster212[[#This Row],[Project_ID]],'REALISASI 2026'!$I$7:$I$1048576) -> 187317686 | Q80: =SUMIF('REALISASI 2026'!$C$7:$C$1048576,tProjectsMaster212[[#This Row],[Project_ID]],'REALISASI 2026'!$I$7:$I$1048576) -> 187317686 | R80: =tProjectsMaster212[[#This Row],[Actual cost (admin)]]/tProjectsMaster212[[#This Row],[Costbased]] -> 0.43303105 | T80: 0.5031
A81: PS-019-00 | B81: =YEAR(tProjectsMaster212[[#This Row],[End Date]]) -> 2027 | C81: =IF(L81>TODAY(),"FUTURE",IF(M81>TODAY(),"ON GOING","CLOSED")) -> FUTURE | D81: RIKI | E81: PGN | F81: MRC | G81: Managed Service Backup Management (Vinchin) | H81: 028000.PK/LG.01/ICT/2024 | I81: Kontrak Tunggal | J81: Back2Back | K81: 45608 | L81: 46388 | M81: 46752 | N81: =10570000000/3 -> 3.5233333e+09 | O81: =432573333 -> 432573333 | R81: =tProjectsMaster212[[#This Row],[Actual cost (admin)]]/tProjectsMaster212[[#This Row],[Costbased]] -> 0 | T81: 0.5031
A82: PS-020-00 | B82: =YEAR(tProjectsMaster212[[#This Row],[End Date]]) -> 2026 | C82: =IF(L82>TODAY(),"FUTURE",IF(M82>TODAY(),"ON GOING","CLOSED")) -> ON GOING | D82: YIYIP | E82: PGN | F82: MRC+WO | G82: Managed Service Cyber Security (MSCS) Tahun 2026 | H82: 003800.PK/LG.01/ICT/2026 | I82: Kontrak Tunggal | J82: Back2Back | K82: 46023 | L82: 46023 | M82: 46387 | N82: 8700000000 | O82: 8203835132 | P82: =2472000000+114905000 -> 2586905000 | Q82: =SUMIF('REALISASI 2026'!$C$7:$C$1048576,tProjectsMaster212[[#This Row],[Project_ID]],'REALISASI 2026'!$I$7:$I$1048576) -> 4696467997 | R82: =tProjectsMaster212[[#This Row],[Actual cost (admin)]]/tProjectsMaster212[[#This Row],[Costbased]] -> 0.57247225 | T82: 0.6632
A83: PS-021-00 | B83: =YEAR(tProjectsMaster212[[#This Row],[End Date]]) -> 2026 | C83: =IF(L83>TODAY(),"FUTURE",IF(M83>TODAY(),"ON GOING","CLOSED")) -> ON GOING | D83: YIYIP | E83: PGN | F83: WO | G83: Managed Service OT Security (MSOT) Tahun 2026 - 2028 | H83: 004400.PK/LG.01/ICT/2026 | I83: Kontrak Tunggal | J83: Back2Back | K83: 46078 | L83: 46023 | M83: 46387 | N83: =15400000000/3 -> 5.1333333e+09 | O83: =(12930184136/36)*12 -> 4.3100614e+09 | P83: 703200000 | Q83: =SUMIF('REALISASI 2026'!$C$7:$C$1048576,tProjectsMaster212[[#This Row],[Project_ID]],'REALISASI 2026'!$I$7:$I$1048576) -> 8655325000 | R83: =tProjectsMaster212[[#This Row],[Actual cost (admin)]]/tProjectsMaster212[[#This Row],[Costbased]] -> 2.0081675 | T83: 30,44%
A84: PS-021-00 | B84: =YEAR(tProjectsMaster212[[#This Row],[End Date]]) -> 2027 | C84: =IF(L84>TODAY(),"FUTURE",IF(M84>TODAY(),"ON GOING","CLOSED")) -> FUTURE | D84: YIYIP | E84: PGN | F84: WO | G84: Managed Service OT Security (MSOT) Tahun 2026 - 2028 | H84: 004400.PK/LG.01/ICT/2026 | I84: Kontrak Tunggal | J84: Back2Back | K84: 46078 | L84: 46388 | M84: 46752 | N84: =15400000000/3 -> 5.1333333e+09 | O84: =12930184136/3 -> 4.3100614e+09 | P84: TBC | R84: =tProjectsMaster212[[#This Row],[Actual cost (admin)]]/tProjectsMaster212[[#This Row],[Costbased]] -> 0 | T84: 30,44%
A85: PS-021-00 | B85: =YEAR(tProjectsMaster212[[#This Row],[End Date]]) -> 2028 | C85: =IF(L85>TODAY(),"FUTURE",IF(M85>TODAY(),"ON GOING","CLOSED")) -> FUTURE | D85: YIYIP | E85: PGN | F85: WO | G85: Managed Service OT Security (MSOT) Tahun 2026 - 2028 | H85: 004400.PK/LG.01/ICT/2026 | I85: Kontrak Tunggal | J85: Back2Back | K85: 46078 | L85: 46753 | M85: 47118 | N85: =15400000000/3 -> 5.1333333e+09 | O85: =12930184136/3 -> 4.3100614e+09 | R85: =tProjectsMaster212[[#This Row],[Actual cost (admin)]]/tProjectsMaster212[[#This Row],[Costbased]] -> 0 | T85: 30,44%
A86: PS-022-00 | B86: =YEAR(tProjectsMaster212[[#This Row],[End Date]]) -> 2022 | C86: =IF(L86>TODAY(),"FUTURE",IF(M86>TODAY(),"ON GOING","CLOSED")) -> CLOSED | D86: RIKI | E86: PGN | F86: MRC | G86: Managed Service Sewa Infrastruktur Data Center (Aletra) | H86: 034000.PK/LG.01/ICT/2022 | I86: Kontrak Tunggal | J86: Inhouse | K86: 44924 | L86: 44924 | M86: 44926 | N86: 0 | O86: 0 | R86: =tProjectsMaster212[[#This Row],[Actual cost (admin)]]/tProjectsMaster212[[#This Row],[Costbased]] -> #DIV/0! | T86: 0.66
A87: PS-022-00 | B87: =YEAR(tProjectsMaster212[[#This Row],[End Date]]) -> 2023 | C87: =IF(L87>TODAY(),"FUTURE",IF(M87>TODAY(),"ON GOING","CLOSED")) -> CLOSED | D87: RIKI | E87: PGN | F87: MRC | G87: Managed Service Sewa Infrastruktur Data Center (Aletra) | H87: 034000.PK/LG.01/ICT/2022 | I87: Kontrak Tunggal | J87: Inhouse | K87: 44924 | L87: 44927 | M87: 45291 | N87: =18200000000/5 -> 3640000000 | O87: =10000000+20000000+1000000+502640000+(8017520000/5) -> 2137144000 | P87: =5525000000+375000000+312000000 -> 6212000000 | R87: =tProjectsMaster212[[#This Row],[Actual cost (admin)]]/tProjectsMaster212[[#This Row],[Costbased]] -> 0 | T87: 0.66
A88: PS-022-00 | B88: =YEAR(tProjectsMaster212[[#This Row],[End Date]]) -> 2024 | C88: =IF(L88>TODAY(),"FUTURE",IF(M88>TODAY(),"ON GOING","CLOSED")) -> CLOSED | D88: RIKI | E88: PGN | F88: MRC | G88: Managed Service Sewa Infrastruktur Data Center (Aletra) | H88: 034000.PK/LG.01/ICT/2022 | I88: Kontrak Tunggal | J88: Inhouse | K88: 44924 | L88: 45292 | M88: 45657 | N88: =18200000000/5 -> 3640000000 | O88: =(8017520000/5)+(1680960000/4) -> 2023744000 | P88: 312000000 | R88: =tProjectsMaster212[[#This Row],[Actual cost (admin)]]/tProjectsMaster212[[#This Row],[Costbased]] -> 0 | T88: 0.66
A89: PS-022-00 | B89: =YEAR(tProjectsMaster212[[#This Row],[End Date]]) -> 2025 | C89: =IF(L89>TODAY(),"FUTURE",IF(M89>TODAY(),"ON GOING","CLOSED")) -> CLOSED | D89: RIKI | E89: PGN | F89: MRC | G89: Managed Service Sewa Infrastruktur Data Center (Aletra) | H89: 034000.PK/LG.01/ICT/2022 | I89: Kontrak Tunggal | J89: Inhouse | K89: 44924 | L89: 45658 | M89: 46022 | N89: =18200000000/5 -> 3640000000 | O89: =(8017520000/5)+(1680960000/4) -> 2023744000 | P89: 312000000 | R89: =tProjectsMaster212[[#This Row],[Actual cost (admin)]]/tProjectsMaster212[[#This Row],[Costbased]] -> 0 | T89: 0.66
A90: PS-022-00 | B90: =YEAR(tProjectsMaster212[[#This Row],[End Date]]) -> 2026 | C90: =IF(L90>TODAY(),"FUTURE",IF(M90>TODAY(),"ON GOING","CLOSED")) -> ON GOING | D90: RIKI | E90: PGN | F90: MRC | G90: Managed Service Sewa Infrastruktur Data Center (Aletra) | H90: 034000.PK/LG.01/ICT/2022 | I90: Kontrak Tunggal | J90: Inhouse | K90: 44924 | L90: 46023 | M90: 46387 | N90: =18200000000/5 -> 3640000000 | O90: =(8017520000/5)+(1680960000/4) -> 2023744000 | P90: 312000000 | Q90: =SUMIF('REALISASI 2026'!$C$7:$C$1048576,tProjectsMaster212[[#This Row],[Project_ID]],'REALISASI 2026'!$I$7:$I$1048576) -> 312000000 | R90: =tProjectsMaster212[[#This Row],[Actual cost (admin)]]/tProjectsMaster212[[#This Row],[Costbased]] -> 0.1541697 | T90: 0.66
A91: PS-022-00 | B91: =YEAR(tProjectsMaster212[[#This Row],[End Date]]) -> 2027 | C91: =IF(L91>TODAY(),"FUTURE",IF(M91>TODAY(),"ON GOING","CLOSED")) -> FUTURE | D91: RIKI | E91: PGN | F91: MRC | G91: Managed Service Sewa Infrastruktur Data Center (Aletra) | H91: 034000.PK/LG.01/ICT/2022 | I91: Kontrak Tunggal | J91: Inhouse | K91: 44924 | L91: 46388 | M91: 46749 | N91: =18200000000/5 -> 3640000000 | O91: =(8017520000/5)+(1680960000/4) -> 2023744000 | P91: 312000000 | R91: =tProjectsMaster212[[#This Row],[Actual cost (admin)]]/tProjectsMaster212[[#This Row],[Costbased]] -> 0 | T91: 0.66
A92: PS-023-00 | B92: =YEAR(tProjectsMaster212[[#This Row],[End Date]]) -> 2025 | C92: =IF(L92>TODAY(),"FUTURE",IF(M92>TODAY(),"ON GOING","CLOSED")) -> CLOSED | D92: TAUFAN | E92: PGN | F92: MRC+WO | G92: Managed Service Teknologi Informasi (MSTI) 2025 | H92: 037000.PKL/LG.01/ICT/2024 | I92: Kontrak Induk | J92: Inhouse | K92: 45657 | L92: 45658 | M92: 46022 | N92: 20019023471 | O92: 19452012822 | R92: =tProjectsMaster212[[#This Row],[Actual cost (admin)]]/tProjectsMaster212[[#This Row],[Costbased]] -> 0 | T92: 0.7124
A93: PS-023-00 | B93: =YEAR(tProjectsMaster212[[#This Row],[End Date]]) -> 2026 | C93: =IF(L93>TODAY(),"FUTURE",IF(M93>TODAY(),"ON GOING","CLOSED")) -> ON GOING | D93: TAUFAN | E93: PGN | F93: MRC+WO | G93: Managed Service Teknologi Informasi (MSTI) 2026 | H93: 003200.PK/LG.01/ICT/2026 | I93: Kontrak Induk | J93: Inhouse | K93: 46078 | L93: 46023 | M93: 46387 | N93: 23950000000 | O93: 22563728241 | Q93: =SUMIF('REALISASI 2026'!$C$7:$C$1048576,tProjectsMaster212[[#This Row],[Project_ID]],'REALISASI 2026'!$I$7:$I$1048576) -> 8815073119 | R93: =tProjectsMaster212[[#This Row],[Actual cost (admin)]]/tProjectsMaster212[[#This Row],[Costbased]] -> 0.39067449 | T93: 0.643
A94: PS-024-00 | B94: =YEAR(tProjectsMaster212[[#This Row],[End Date]]) -> 2025 | C94: =IF(L94>TODAY(),"FUTURE",IF(M94>TODAY(),"ON GOING","CLOSED")) -> CLOSED | D94: TITA | E94: PGN | F94: MRC+WO | G94: Pekerjaan Jasa Operasi dan Pemeliharaan Terintegrasi Gas Management System (PJOPTGMS) | H94: 009700.PK/HK.02/GLM/2025 | I94: Kontrak Induk | J94: Inhouse | K94: 45717 | L94: 45717 | M94: 46022 | N94: =ROUNDUP(59000000000/12,1)*10 -> 4.9166667e+10 | O94: =51530901364/12*10 -> 4.2942418e+10 | P94: 20653294878 | R94: =tProjectsMaster212[[#This Row],[Actual cost (admin)]]/tProjectsMaster212[[#This Row],[Costbased]] -> 0 | T94: 0.5918
A95: PS-024-00 | B95: =YEAR(tProjectsMaster212[[#This Row],[End Date]]) -> 2026 | C95: =IF(L95>TODAY(),"FUTURE",IF(M95>TODAY(),"ON GOING","CLOSED")) -> ON GOING | D95: TITA | E95: PGN | F95: MRC+WO | G95: Pekerjaan Jasa Operasi dan Pemeliharaan Terintegrasi Gas Management System (PJOPTGMS) | H95: 009700.PK/HK.02/GLM/2025 | I95: Kontrak Induk | J95: Inhouse | K95: 45717 | L95: 46023 | M95: 46387 | N95: =ROUNDUP(59000000000/12,1)*12 -> 5.9e+10 | O95: =51530901364 -> 51530901364 | Q95: =SUMIF('REALISASI 2026'!$C$7:$C$1048576,tProjectsMaster212[[#This Row],[Project_ID]],'REALISASI 2026'!$I$7:$I$1048576) -> 1.445519e+10 | R95: =tProjectsMaster212[[#This Row],[Actual cost (admin)]]/tProjectsMaster212[[#This Row],[Costbased]] -> 0.28051499 | T95: 0.5918
A96: PS-024-00 | B96: =YEAR(tProjectsMaster212[[#This Row],[End Date]]) -> 2027 | C96: =IF(L96>TODAY(),"FUTURE",IF(M96>TODAY(),"ON GOING","CLOSED")) -> FUTURE | D96: TITA | E96: PGN | F96: MRC+WO | G96: Pekerjaan Jasa Operasi dan Pemeliharaan Terintegrasi Gas Management System (PJOPTGMS) | H96: 009700.PK/HK.02/GLM/2025 | I96: Kontrak Induk | J96: Inhouse | K96: 45717 | L96: 46388 | M96: 46752 | N96: =ROUNDUP(59000000000/12,1)*12 -> 5.9e+10 | O96: =51530901364 -> 51530901364 | R96: =tProjectsMaster212[[#This Row],[Actual cost (admin)]]/tProjectsMaster212[[#This Row],[Costbased]] -> 0 | T96: 0.5918
A97: PS-024-00 | B97: =YEAR(tProjectsMaster212[[#This Row],[End Date]]) -> 2028 | C97: =IF(L97>TODAY(),"FUTURE",IF(M97>TODAY(),"ON GOING","CLOSED")) -> FUTURE | D97: TITA | E97: PGN | F97: MRC+WO | G97: Pekerjaan Jasa Operasi dan Pemeliharaan Terintegrasi Gas Management System (PJOPTGMS) | H97: 009700.PK/HK.02/GLM/2025 | I97: Kontrak Induk | J97: Inhouse | K97: 45717 | L97: 46753 | M97: 46812 | N97: =ROUNDUP(59000000000/12,1)*2 -> 9.8333333e+09 | O97: =51530901364/12*2 -> 8.5884836e+09 | R97: =tProjectsMaster212[[#This Row],[Actual cost (admin)]]/tProjectsMaster212[[#This Row],[Costbased]] -> 0 | T97: 0.5918
A98: PS-025-00 | B98: =YEAR(tProjectsMaster212[[#This Row],[End Date]]) -> 2026 | C98: =IF(L98>TODAY(),"FUTURE",IF(M98>TODAY(),"ON GOING","CLOSED")) -> ON GOING | D98: TAUFAN | E98: PGN | F98: MRC | G98: Pekerjaan Jasa Sewa Penyediaan Collocation Master Data Center dan Backup data Center | H98: 067400.ND/LG.01/DKP/2025 | I98: Kontrak Tunggal | J98: Inhouse | K98: 45979 | L98: 46023 | M98: 46387 | N98: 1200000000 | O98: 1038528000 | P98: =52000000*12 -> 624000000 | Q98: =SUMIF('REALISASI 2026'!$C$7:$C$1048576,tProjectsMaster212[[#This Row],[Project_ID]],'REALISASI 2026'!$I$7:$I$1048576) -> 0 | R98: =tProjectsMaster212[[#This Row],[Actual cost (admin)]]/tProjectsMaster212[[#This Row],[Costbased]] -> 0 | T98: 0.7741
A99: PS-026-00 | B99: =YEAR(tProjectsMaster212[[#This Row],[End Date]]) -> 2025 | C99: =IF(L99>TODAY(),"FUTURE",IF(M99>TODAY(),"ON GOING","CLOSED")) -> CLOSED | D99: SANDI | E99: PGN | F99: MRC | G99: Pengadaan Jasa Managed Service E-KYC | H99: 070300.PK/LG.01/GLS/2025 | I99: Kontrak Tunggal | J99: Back2Back | K99: 45975 | L99: 45972 | M99: 46022 | N99: =730000000*10% -> 73000000 | O99: =658568600*10% -> 65856860 | R99: =tProjectsMaster212[[#This Row],[Actual cost (admin)]]/tProjectsMaster212[[#This Row],[Costbased]] -> 0 | T99: 58,56%
A100: PS-026-00 | B100: =YEAR(tProjectsMaster212[[#This Row],[End Date]]) -> 2026 | C100: =IF(L100>TODAY(),"FUTURE",IF(M100>TODAY(),"ON GOING","CLOSED")) -> ON GOING | D100: SANDI | E100: PGN | F100: MRC | G100: Pengadaan Jasa Managed Service E-KYC | H100: 070300.PK/LG.01/GLS/2025 | I100: Kontrak Tunggal | J100: Back2Back | K100: 45975 | L100: 45972 | M100: 46387 | N100: =730000000*90% -> 657000000 | O100: =658568600*90% -> 592711740 | P100: =SUMIF('REALISASI 2026'!$C$7:$C$1048576,tProjectsMaster212[[#This Row],[Project_ID]],'REALISASI 2026'!$I$7:$I$1048576) -> 54585707 | Q100: =SUMIF('REALISASI 2026'!$C$7:$C$1048576,tProjectsMaster212[[#This Row],[Project_ID]],'REALISASI 2026'!$I$7:$I$1048576) -> 54585707 | R100: =tProjectsMaster212[[#This Row],[Actual cost (admin)]]/tProjectsMaster212[[#This Row],[Costbased]] -> 0.092094864 | T100: 58,56%
...

Sheet Pivot
A1: Year | B1: 2026
A3: Label Baris | B3: Count of Project Name | C3: Count of Skema
A4: Back2Back | B4: 45 | C4: 45
A5: Inhouse | B5: 31 | C5: 31
A6: (kosong) | B6: 8
A7: Total Keseluruhan | B7: 84 | C7: 76
A9: Year | B9: 2026
A11: Label Baris | B11: Count of Project Name | C11: Sum of Project_Value
A12: CLOSED | B12: 14 | C12: 8.7362659e+09
A13: ON GOING | B13: 70 | C13: 3.0059871e+11
A14: Total Keseluruhan | B14: 84 | C14: 3.0933498e+11
A18: Year | B18: 2026
A20: Label Baris | B20: Hitung dari TKDN
A21: CLOSED | B21: 4
A22: ON GOING | B22: 42
A23: Total Keseluruhan | B23: 46
